Workbook

Sheet NMG
A1: StartDate | B1: EndDate | C1: Status | D1: IPAddress | E1: Progress | F1: Duration (in seconds) | G1: Finished | H1: RecordedDate | I1: ResponseId | J1: RecipientLastName | K1: RecipientFirstName | L1: RecipientEmail | M1: ExternalReference | N1: LocationLatitude | O1: LocationLongitude | P1: DistributionChannel | Q1: UserLanguage | R1: Q1 | S1: Q2 | T1: Q3 | U1: Q4 | V1: Q4_5_TEXT | W1: Q5 | X1: Q5_4_TEXT | Y1: Q6 | Z1: Q7 | AA1: Q8 | AB1: Q9 | AC1: Q10 | AD1: Q11 | AE1: Q12 | AF1: Q13_1 | AG1: Q13_2 | AH1: Q13_3 | AI1: Q14_0 | AJ1: Q14 | AK1: Q15 | AL1: Q16 | AM1: Q16_1_TEXT | AN1: Q17 | AO1: Q18 | AP1: Q19 | AQ1: Q19_4_TEXT | AR1: Q20 | AS1: Q21_1 | AT1: Q21_2 | AU1: Q21_3 | AV1: Q21_4 | AW1: Q21_5 | AX1: Q21_6 | AY1: Q21_7 | AZ1: Q21_8 | BA1: Q21_9 | BB1: Q21_10 | BC1: Q21_11 | BD1: Q21_12 | BE1: Q21_13 | BF1: Q21_14 | BG1: Q21_15 | BH1: Q22_1 | BI1: Q22_2 | BJ1: Q22_3 | BK1: Q22_4 | BL1: Q22_5 | BM1: Q22_6 | BN1: Q22_7 | BO1: Q22_8 | BP1: Q22_9 | BQ1: Q22_10 | BR1: Q22_11 | BS1: Q23 | BT1: Q24_1 | BU1: Q24_2 | BV1: Q25_1 | BW1: Q25_2 | BX1: Q25_3 | BY1: Q25_4 | BZ1: Q25_5 | CA1: Q25_6 | CB1: Q25_7 | CC1: Q25_8 | CD1: Q25_9 | CE1: Q26 | CF1: Q27 | CG1: Q28 | CH1: Q29 | CI1: Q30 | CJ1: Q31 | CK1: Q32 | CL1: Q33 | CM1: Q34_1 | CN1: Q34_2 | CO1: Q34_3 | CP1: Q34_4 | CQ1: Q35 | CR1: Q35_5_TEXT | CS1: Q36 | CT1: Q37 | CU1: Q38 | CV1: Q39 | CW1: Q39_5_TEXT | CX1: Q40 | CY1: Q41 | CZ1: Q42 | DA1: Q42_8_TEXT | DB1: Q43 | DC1: Q44 | DD1: Q45 | DE1: PROLIFIC_PID | DF1: Indicators_Satisfied
A2: 45718.427 | B2: 45718.431 | C2: 0 | D2: 67.81.6.206 | E2: 100 | F2: 354 | G2: 1 | H2: 45718.431 | I2: R_7CkbrcvxqUIp5ex | N2: 40.8534 | O2: -73.4115 | P2: anonymous | Q2: EN | R2: 1 | S2: 611037a84b048a5bed5c3c96 | T2: 2 | U2: 1 | W2: 2 | Y2: 7 | Z2: 1 | AA2: 1 | AB2: 2 | AC2: 3 | AD2: 5 | AE2: 1 | AF2: 2 | AG2: 2 | AH2: 2 | AI2: 1 | AJ2: 2 | AK2: 1 | AL2: 2 | AN2: 4 | AO2: 2 | AP2: 4 | AQ2: install pumps | AR2: 1 | AS2: 4 | AT2: 4 | AU2: 3 | AV2: 3 | AW2: 3 | AX2: 2 | AY2: 2 | AZ2: 1 | BA2: 3 | BB2: 3 | BC2: 3 | BD2: 1 | BE2: 3 | BF2: 4 | BG2: 3 | BH2: 4 | BI2: 4 | BJ2: 4 | BK2: 4 | BL2: 2 | BM2: 4 | BN2: 2 | BO2: 2 | BP2: 4 | BQ2: 4 | BR2: 3 | BS2: 3 | BT2: 2 | BU2: 2 | BV2: 3 | BW2: 3 | BX2: 2 | BY2: 3 | BZ2: 3 | CA2: 3 | CB2: 3 | CC2: 3 | CD2: 3 | CE2: 4 | CF2: 2 | CG2: 2 | CH2: 1 | CI2: 1 | CJ2: 1 | CK2: 3 | CM2: 2 | CN2: 3 | CO2: 4 | CP2: 1 | CQ2: 1 | CS2: 1 | CT2: 3 | CU2: 4 | CV2: 2 | CX2: 1 | CY2: 1 | CZ2: 3 | DB2: 10 | DC2: 11743 | DE2: 611037a84b048a5bed5c3c96 | DF2: 0
A3: 45718.43 | B3: 45718.437 | C3: 0 | D3: 24.44.50.98 | E3: 100 | F3: 593 | G3: 1 | H3: 45718.437 | I3: R_5r248g6QqsZYeYk | N3: 40.608 | O3: -74.5265 | P3: anonymous | Q3: EN | R3: 1 | S3: 65fc7aec8851ded695c2fd8a | T3: 1 | U3: 2 | W3: 2 | Y3: 1 | Z3: 1 | AA3: 1 | AB3: 2 | AC3: 1 | AD3: 2 | AE3: 1 | AF3: 2 | AG3: 2 | AH3: 2 | AI3: 2 | AJ3: 1 | AS3: 4 | AT3: 4 | AU3: 3 | AV3: 3 | AW3: 3 | AX3: 4 | AY3: 3 | AZ3: 2 | BA3: 3 | BB3: 2 | BC3: 2 | BD3: 3 | BE3: 3 | BF3: 4 | BG3: 3 | BH3: 3 | BI3: 4 | BJ3: 3 | BK3: 4 | BL3: 5 | BM3: 2 | BN3: 2 | BO3: 4 | BP3: 4 | BQ3: 4 | BR3: 2 | BS3: 3 | BT3: 2 | BU3: 2 | BV3: 3 | BW3: 3 | BX3: 2 | BY3: 4 | BZ3: 3 | CA3: 3 | CB3: 5 | CC3: 2 | CD3: 3 | CE3: 1 | CF3: 5 | CG3: 1 | CH3: 2 | CI3: 1 | CJ3: 2 | CK3: 2 | CM3: 1 | CN3: 3 | CO3: 2 | CP3: 4 | CQ3: 2 | CS3: 2 | CT3: 3 | CU3: 4 | CV3: 1 | CX3: 1 | CY3: 1 | CZ3: 8 | DA3: Technical Support | DB3: 10 | DC3: 08869 | DE3: 65fc7aec8851ded695c2fd8a | DF3: 0
A4: 45718.426 | B4: 45718.437 | C4: 0 | D4: 172.59.208.237 | E4: 100 | F4: 942 | G4: 1 | H4: 45718.437 | I4: R_7CiUYRtayo3pZFH | N4: 40.7463 | O4: -74.1553 | P4: anonymous | Q4: EN | R4: 1 | S4: 67c0c4f757d625c937fa4cf9 | T4: 1 | U4: 1 | W4: 3 | Y4: 5 | Z4: 1 | AA4: 1 | AB4: 1 | AC4: 3 | AD4: 2 | AE4: 1 | AF4: 1 | AG4: 2 | AH4: 2 | AI4: 1 | AJ4: 2 | AK4: 2 | AL4: 1 | AN4: 2 | AO4: 1 | AP4: 3 | AR4: 1 | AS4: 3 | AT4: 3 | AU4: 4 | AV4: 4 | AW4: 2 | AX4: 2 | AY4: 3 | AZ4: 4 | BA4: 4 | BB4: 4 | BC4: 4 | BD4: 5 | BE4: 4 | BF4: 4 | BG4: 2 | BH4: 4 | BI4: 3 | BJ4: 5 | BK4: 4 | BL4: 4 | BM4: 5 | BN4: 4 | BO4: 4 | BP4: 2 | BQ4: 4 | BR4: 4 | BS4: 3 | BT4: 4 | BU4: 5 | BV4: 4 | BW4: 4 | BX4: 5 | BY4: 5 | BZ4: 5 | CA4: 5 | CB4: 5 | CC4: 4 | CD4: 5 | CE4: 2 | CF4: 5 | CG4: 4 | CH4: 4 | CI4: 4 | CJ4: 4 | CK4: 2 | CM4: 3 | CN4: 1 | CO4: 2 | CP4: 4 | CQ4: 2 | CS4: 1 | CT4: 3 | CU4: 2 | CV4: 1 | CX4: 1 | CY4: 2 | CZ4: 8 | DB4: 10 | DC4: 07206 | DE4: 67c0c4f757d625c937fa4cf9 | DF4: 0
A5: 45718.432 | B5: 45718.438 | C5: 0 | D5: 74.102.159.69 | E5: 100 | F5: 569 | G5: 1 | H5: 45718.438 | I5: R_7QryMPJ8k5wNCWm | N5: 40.7463 | O5: -74.1553 | P5: anonymous | Q5: EN | R5: 1 | S5: 65635241f6b4756ac64c57eb | T5: 1 | U5: 1 | W5: 2 | Y5: 1 | Z5: 1 | AA5: 1 | AB5: 2 | AC5: 2 | AD5: 3 | AE5: 1 | AF5: 2 | AG5: 2 | AH5: 2 | AI5: 2 | AJ5: 1 | AS5: 5 | AT5: 5 | AU5: 5 | AV5: 4 | AW5: 4 | AX5: 4 | AY5: 3 | AZ5: 3 | BA5: 4 | BB5: 3 | BC5: 4 | BD5: 4 | BE5: 4 | BF5: 4 | BG5: 4 | BH5: 5 | BI5: 1 | BJ5: 2 | BK5: 2 | BL5: 2 | BM5: 2 | BN5: 2 | BO5: 1 | BP5: 1 | BQ5: 1 | BR5: 1 | BS5: 3 | BT5: 2 | BU5: 2 | BV5: 2 | BW5: 2 | BX5: 4 | BY5: 4 | BZ5: 4 | CA5: 4 | CB5: 5 | CC5: 4 | CD5: 4 | CE5: 1 | CF5: 2 | CG5: 1 | CH5: 4 | CI5: 2 | CJ5: 4 | CK5: 2 | CM5: 2 | CN5: 1 | CO5: 3 | CP5: 4 | CQ5: 2 | CS5: 1 | CT5: 3 | CU5: 1 | CV5: 1 | CX5: 1 | CY5: 1 | CZ5: 4 | DB5: 10 | DC5: 07604 | DE5: 65635241f6b4756ac64c57eb | DF5: 0
A6: 45718.433 | B6: 45718.441 | C6: 0 | D6: 140.174.71.233 | E6: 100 | F6: 612 | G6: 1 | H6: 45718.441 | I6: R_1NKghBSgfSUuAE4 | N6: 41.0534 | O6: -73.5387 | P6: anonymous | Q6: EN | R6: 1 | S6: 654fe6af3517f92a06444ca5 | T6: 2 | U6: 3 | W6: 1 | Y6: 6 | Z6: 2 | AA6: 1 | AB6: 2 | AC6: 2 | AD6: 2 | AE6: 1 | AF6: 2 | AG6: 2 | AH6: 2 | AI6: 2 | AJ6: 1 | AS6: 2 | AT6: 3 | AU6: 3 | AV6: 2 | AW6: 3 | AX6: 3 | AY6: 3 | AZ6: 3 | BA6: 3 | BB6: 2 | BC6: 3 | BD6: 3 | BE6: 3 | BF6: 2 | BG6: 2 | BH6: 4 | BI6: 4 | BJ6: 2 | BK6: 2 | BL6: 2 | BM6: 2 | BN6: 2 | BO6: 4 | BP6: 4 | BQ6: 4 | BR6: 3 | BS6: 3 | BT6: 1 | BU6: 1 | BV6: 4 | BW6: 4 | BX6: 2 | BY6: 3 | BZ6: 2 | CA6: 2 | CB6: 3 | CC6: 2 | CD6: 2 | CE6: 1 | CF6: 4 | CG6: 1 | CL6: 4 | CQ6: 2 | CS6: 2 | CT6: 3 | CU6: 1 | CV6: 1 | CX6: 1 | CY6: 2 | CZ6: 4 | DB6: 10 | DC6: 10016 | DE6: 654fe6af3517f92a06444ca5 | DF6: 0
A7: 45718.436 | B7: 45718.441 | C7: 0 | D7: 68.192.75.150 | E7: 100 | F7: 484 | G7: 1 | H7: 45718.441 | I7: R_5sV6WsT12XDr7pL | N7: 41.1484 | O7: -74.5827 | P7: anonymous | Q7: EN | R7: 1 | S7: 5f6e04d24dfd8f2c88366a29 | T7: 1 | U7: 2 | W7: 1 | Y7: 1 | Z7: 2 | AA7: 1 | AB7: 2 | AC7: 2 | AD7: 2 | AE7: 1 | AF7: 2 | AG7: 2 | AH7: 2 | AI7: 2 | AJ7: 1 | AS7: 3 | AT7: 3 | AU7: 3 | AV7: 2 | AW7: 4 | AX7: 3 | AY7: 1 | AZ7: 1 | BA7: 1 | BB7: 1 | BC7: 2 | BD7: 1 | BE7: 1 | BF7: 4 | BG7: 1 | BH7: 1 | BI7: 1 | BJ7: 1 | BK7: 1 | BL7: 3 | BM7: 1 | BN7: 1 | BO7: 3 | BP7: 1 | BQ7: 1 | BR7: 1 | BS7: 3 | BT7: 1 | BU7: 2 | BV7: 2 | BW7: 3 | BX7: 1 | BY7: 4 | BZ7: 4 | CA7: 2 | CB7: 3 | CC7: 1 | CD7: 2 | CE7: 4 | CF7: 1 | CG7: 1 | CL7: 1 | CQ7: 3 | CS7: 1 | CT7: 2 | CU7: 4 | CV7: 2 | CX7: 1 | CY7: 1 | CZ7: 3 | DB7: 10 | DC7: 07416 | DE7: 5f6e04d24dfd8f2c88366a29 | DF7: 0
A8: 45718.427 | B8: 45718.442 | C8: 0 | D8: 69.122.18.136 | E8: 100 | F8: 1316 | G8: 1 | H8: 45718.442 | I8: R_6D76h8bDEQy3HyC | N8: 40.5175 | O8: -74.3991 | P8: anonymous | Q8: EN | R8: 1 | S8: 66a2fc3f7be0914ea068ea6a | T8: 1 | U8: 1 | W8: 1 | Y8: 7 | Z8: 1 | AA8: 1 | AB8: 1 | AC8: 3 | AD8: 3 | AE8: 1 | AF8: 2 | AG8: 2 | AH8: 2 | AI8: 2 | AJ8: 1 | AS8: 3 | AT8: 3 | AU8: 3 | AV8: 3 | AW8: 3 | AX8: 3 | AY8: 1 | AZ8: 1 | BA8: 3 | BB8: 1 | BC8: 3 | BD8: 2 | BE8: 3 | BF8: 3 | BG8: 3 | BH8: 4 | BI8: 2 | BJ8: 2 | BK8: 2 | BL8: 4 | BM8: 2 | BN8: 4 | BO8: 2 | BP8: 3 | BQ8: 2 | BR8: 2 | BS8: 3 | BT8: 2 | BU8: 2 | BV8: 4 | BW8: 3 | BX8: 2 | BY8: 4 | BZ8: 3 | CA8: 2 | CB8: 4 | CC8: 3 | CD8: 2 | CE8: 1 | CF8: 2 | CG8: 1 | CL8: 3 | CQ8: 2 | CS8: 1 | CT8: 2 | CU8: 3 | CV8: 2 | CX8: 1 | CY8: 2 | CZ8: 6 | DB8: 6 | DC8: 08854 | DE8: 66a2fc3f7be0914ea068ea6a | DF8: 0
A9: 45718.434 | B9: 45718.443 | C9: 0 | D9: 108.5.179.42 | E9: 100 | F9: 719 | G9: 1 | H9: 45718.443 | I9: R_3iepfnPlDsSzVqg | N9: 40.6342 | O9: -74.2427 | P9: anonymous | Q9: EN | R9: 1 | S9: 5e1a3bc7477f3b2ba490bde1 | T9: 1 | U9: 2 | W9: 1 | Y9: 6 | Z9: 2 | AA9: 1 | AB9: 2 | AC9: 1 | AD9: 2 | AE9: 1 | AF9: 2 | AG9: 2 | AH9: 2 | AI9: 2 | AJ9: 1 | AS9: 4 | AT9: 4 | AU9: 4 | AV9: 4 | AW9: 3 | AX9: 3 | AY9: 3 | AZ9: 2 | BA9: 3 | BB9: 5 | BC9: 4 | BD9: 2 | BE9: 2 | BF9: 5 | BG9: 5 | BH9: 1 | BI9: 1 | BJ9: 2 | BK9: 4 | BL9: 4 | BM9: 4 | BN9: 2 | BO9: 1 | BP9: 1 | BQ9: 3 | BR9: 1 | BS9: 3 | BT9: 3 | BU9: 4 | BV9: 4 | BW9: 2 | BX9: 5 | BY9: 5 | BZ9: 1 | CA9: 4 | CB9: 4 | CC9: 1 | CD9: 4 | CE9: 4 | CF9: 2 | CG9: 1 | CL9: 3 | CQ9: 1 | CS9: 2 | CT9: 4 | CU9: 4 | CV9: 1 | CX9: 1 | CY9: 1 | CZ9: 3 | DB9: 8 | DC9: 07203 | DD9: Some of the questions I might have had different answers for if they were phrased slightly differently. For instance, my larger community, like the town I live in, floods all the time, but my immediate community, the apartment complex I live in, is higher in elevation and never floods, even when everyone around us does. I answered questions based on defining community as my apartment community, but I'm not sure if all would have interpreted the questions like that. | DE9: 5e1a3bc7477f3b2ba490bde1 | DF9: 0
A10: 45718.44 | B10: 45718.444 | C10: 0 | D10: 74.90.37.4 | E10: 100 | F10: 297 | G10: 1 | H10: 45718.444 | I10: R_3EaW5xxnTIE5h8t | N10: 40.9451 | O10: -74.2531 | P10: anonymous | Q10: EN | R10: 1 | S10: 66d06fd15b37d17345069c4c | T10: 1 | U10: 1 | W10: 2 | Y10: 1 | Z10: 2 | AA10: 1 | AB10: 2 | AC10: 4 | AD10: 4 | AE10: 1 | AF10: 2 | AG10: 1 | AH10: 2 | AI10: 2 | AJ10: 1 | AS10: 5 | AT10: 4 | AU10: 4 | AV10: 4 | AW10: 4 | AX10: 4 | AY10: 5 | AZ10: 4 | BA10: 4 | BB10: 5 | BC10: 5 | BD10: 3 | BE10: 5 | BF10: 4 | BG10: 3 | BH10: 1 | BI10: 1 | BJ10: 2 | BK10: 4 | BL10: 3 | BM10: 4 | BN10: 2 | BO10: 2 | BP10: 2 | BQ10: 2 | BR10: 1 | BS10: 3 | BT10: 4 | BU10: 4 | BV10: 2 | BW10: 2 | BX10: 2 | BY10: 4 | BZ10: 2 | CA10: 2 | CB10: 2 | CC10: 2 | CD10: 2 | CE10: 4 | CF10: 2 | CG10: 1 | CH10: 1 | CI10: 1 | CJ10: 1 | CK10: 1 | CM10: 2 | CN10: 3 | CO10: 4 | CP10: 1 | CQ10: 2 | CS10: 3 | CT10: 4 | CU10: 4 | CV10: 2 | CX10: 1 | CY10: 2 | CZ10: 4 | DB10: 10 | DC10: 07470 | DE10: 66d06fd15b37d17345069c4c | DF10: 0
A11: 45718.443 | B11: 45718.449 | C11: 0 | D11: 174.229.241.241 | E11: 100 | F11: 549 | G11: 1 | H11: 45718.449 | I11: R_5rTupkC4wUKF5Vg | N11: 40.9261 | O11: -74.1419 | P11: anonymous | Q11: EN | R11: 1 | S11: 653403fb4c4cee1065807251 | T11: 1 | U11: 3 | W11: 1 | Y11: 1 | Z11: 1 | AA11: 1 | AB11: 2 | AC11: 1 | AD11: 2 | AE11: 1 | AF11: 2 | AG11: 2 | AH11: 2 | AI11: 2 | AJ11: 1 | AS11: 3 | AT11: 3 | AU11: 4 | AV11: 3 | AW11: 3 | AX11: 3 | AY11: 3 | AZ11: 3 | BA11: 3 | BB11: 3 | BC11: 3 | BD11: 3 | BE11: 3 | BF11: 4 | BG11: 3 | BH11: 3 | BI11: 3 | BJ11: 2 | BK11: 3 | BL11: 3 | BM11: 2 | BN11: 2 | BO11: 3 | BP11: 3 | BQ11: 3 | BR11: 3 | BS11: 3 | BT11: 2 | BU11: 2 | BV11: 3 | BW11: 3 | BX11: 2 | BY11: 3 | BZ11: 3 | CA11: 2 | CB11: 3 | CC11: 3 | CD11: 2 | CE11: 4 | CF11: 4 | CG11: 1 | CL11: 3 | CQ11: 2 | CS11: 3 | CT11: 3 | CU11: 4 | CV11: 1 | CX11: 1 | CY11: 1 | CZ11: 4 | DB11: 9 | DC11: 07047 | DE11: 653403fb4c4cee1065807251 | DF11: 0
A12: 45718.445 | B12: 45718.449 | C12: 0 | D12: 73.198.91.94 | E12: 100 | F12: 329 | G12: 1 | H12: 45718.449 | I12: R_5zQQPdbSkYD8Pp7 | N12: 39.7513 | O12: -74.9999 | P12: anonymous | Q12: EN | R12: 1 | S12: 6647c117352b708167ccfd48 | T12: 1 | U12: 1 | W12: 2 | Y12: 4 | Z12: 2 | AA12: 1 | AB12: 2 | AC12: 4 | AD12: 4 | AE12: 1 | AF12: 2 | AG12: 2 | AH12: 2 | AI12: 2 | AJ12: 1 | AS12: 4 | AT12: 4 | AU12: 5 | AV12: 4 | AW12: 3 | AX12: 3 | AY12: 4 | AZ12: 5 | BA12: 5 | BB12: 4 | BC12: 3 | BD12: 3 | BE12: 4 | BF12: 3 | BG12: 3 | BH12: 4 | BI12: 3 | BJ12: 2 | BK12: 2 | BL12: 1 | BM12: 1 | BN12: 1 | BO12: 4 | BP12: 4 | BQ12: 3 | BR12: 2 | BS12: 3 | BT12: 1 | BU12: 1 | BV12: 3 | BW12: 2 | BX12: 3 | BY12: 4 | BZ12: 4 | CA12: 3 | CB12: 4 | CC12: 2 | CD12: 3 | CE12: 4 | CF12: 4 | CG12: 1 | CH12: 3 | CI12: 2 | CJ12: 3 | CK12: 4 | CM12: 1 | CN12: 2 | CO12: 3 | CP12: 4 | CQ12: 1 | CS12: 4 | CT12: 3 | CU12: 4 | CV12: 1 | CX12: 1 | CY12: 2 | CZ12: 3 | DB12: 10 | DC12: 08051 | DE12: 6647c117352b708167ccfd48 | DF12: 0
A13: 45718.436 | B13: 45718.449 | C13: 0 | D13: 131.125.11.1 | E13: 100 | F13: 1149 | G13: 1 | H13: 45718.449 | I13: R_1h6j419H5CulNWM | N13: 40.6947 | O13: -74.2688 | P13: anonymous | Q13: EN | R13: 1 | S13: 6789c5aa3a931b6efcc2ea61 | T13: 1 | U13: 2 | W13: 2 | Y13: 4 | Z13: 1 | AA13: 1 | AB13: 2 | AC13: 5 | AD13: 3 | AE13: 1 | AF13: 2 | AG13: 1 | AH13: 2 | AI13: 1 | AJ13: 2 | AK13: 2 | AL13: 2 | AN13: 2 | AO13: 2 | AP13: 1 | AR13: 1 | AS13: 5 | AT13: 5 | AU13: 5 | AV13: 5 | AW13: 5 | AX13: 2 | AY13: 5 | AZ13: 5 | BA13: 5 | BB13: 5 | BC13: 4 | BD13: 5 | BE13: 5 | BF13: 5 | BG13: 5 | BH13: 4 | BI13: 4 | BJ13: 3 | BK13: 5 | BL13: 5 | BM13: 5 | BN13: 4 | BO13: 4 | BP13: 3 | BQ13: 4 | BR13: 4 | BS13: 3 | BT13: 5 | BU13: 5 | BV13: 4 | BW13: 3 | BX13: 5 | BY13: 4 | BZ13: 5 | CA13: 4 | CB13: 2 | CC13: 3 | CD13: 3 | CE13: 2 | CF13: 3 | CG13: 1 | CH13: 4 | CI13: 2 | CJ13: 2 | CK13: 1 | CM13: 1 | CN13: 2 | CO13: 3 | CP13: 4 | CQ13: 2 | CS13: 1 | CT13: 2 | CU13: 4 | CV13: 1 | CX13: 1 | CY13: 2 | CZ13: 4 | DB13: 7 | DC13: 08831 | DE13: 6789c5aa3a931b6efcc2ea61 | DF13: 0
A14: 45718.443 | B14: 45718.449 | C14: 0 | D14: 69.125.203.57 | E14: 100 | F14: 593 | G14: 1 | H14: 45718.449 | I14: R_5o1xo7wN5E9KMox | N14: 40.2066 | O14: -74.0727 | P14: anonymous | Q14: EN | R14: 1 | S14: 594d4f0aa186be000114ce1d | T14: 1 | U14: 1 | W14: 2 | Y14: 3 | Z14: 1 | AA14: 1 | AB14: 2 | AC14: 3 | AD14: 2 | AE14: 1 | AF14: 1 | AG14: 2 | AH14: 2 | AI14: 2 | AJ14: 1 | AS14: 4 | AT14: 4 | AU14: 4 | AV14: 4 | AW14: 2 | AX14: 2 | AY14: 3 | AZ14: 4 | BA14: 3 | BB14: 3 | BC14: 2 | BD14: 2 | BE14: 3 | BF14: 4 | BG14: 2 | BH14: 2 | BI14: 2 | BJ14: 2 | BK14: 3 | BL14: 4 | BM14: 3 | BN14: 4 | BO14: 2 | BP14: 2 | BQ14: 2 | BR14: 1 | BS14: 3 | BT14: 2 | BU14: 3 | BV14: 2 | BW14: 2 | BX14: 2 | BY14: 4 | BZ14: 2 | CA14: 2 | CB14: 5 | CC14: 3 | CD14: 3 | CE14: 1 | CF14: 2 | CG14: 1 | CH14: 1 | CI14: 1 | CJ14: 1 | CK14: 3 | CM14: 1 | CN14: 3 | CO14: 4 | CP14: 2 | CQ14: 2 | CS14: 1 | CT14: 3 | CU14: 3 | CV14: 1 | CX14: 1 | CY14: 1 | CZ14: 3 | DB14: 10 | DC14: 07719 | DE14: 594d4f0aa186be000114ce1d | DF14: 0
A15: 45718.444 | B15: 45718.449 | C15: 0 | D15: 71.58.35.0 | E15: 100 | F15: 435 | G15: 1 | H15: 45718.449 | I15: R_7d6UYadE8f2Ca3J | N15: 39.9733 | O15: -74.248 | P15: anonymous | Q15: EN | R15: 1 | S15: 67a4fb352efb6fe83eb694c7 | T15: 1 | U15: 1 | W15: 1 | Y15: 2 | Z15: 2 | AA15: 1 | AB15: 2 | AC15: 1 | AD15: 2 | AE15: 1 | AF15: 2 | AG15: 2 | AH15: 1 | AI15: 2 | AJ15: 1 | AS15: 4 | AT15: 4 | AU15: 4 | AV15: 4 | AW15: 4 | AX15: 4 | AY15: 3 | AZ15: 3 | BA15: 3 | BB15: 4 | BC15: 3 | BD15: 2 | BE15: 3 | BF15: 4 | BG15: 3 | BH15: 2 | BI15: 2 | BJ15: 2 | BK15: 4 | BL15: 4 | BM15: 4 | BN15: 4 | BO15: 4 | BP15: 4 | BQ15: 2 | BR15: 2 | BS15: 3 | BT15: 4 | BU15: 4 | BV15: 4 | BW15: 2 | BX15: 3 | BY15: 4 | BZ15: 3 | CA15: 3 | CB15: 4 | CC15: 3 | CD15: 4 | CE15: 4 | CF15: 1 | CG15: 2 | CL15: 2 | CQ15: 2 | CS15: 6 | CT15: 3 | CU15: 4 | CV15: 4 | CX15: 1 | CY15: 1 | CZ15: 8 | DB15: 2 | DC15: 08757 | DE15: 67a4fb352efb6fe83eb694c7 | DF15: 0
A16: 45718.443 | B16: 45718.451 | C16: 0 | D16: 96.250.56.141 | E16: 100 | F16: 742 | G16: 1 | H16: 45718.451 | I16: R_1ZWxUgOMe8mCpuV | N16: 41.0155 | O16: -73.8635 | P16: anonymous | Q16: EN | R16: 1 | S16: 67aa8ca32e7acec145f34f7a | T16: 2 | U16: 1 | W16: 1 | Y16: 1 | Z16: 2 | AA16: 1 | AB16: 2 | AC16: 6 | AD16: 7 | AE16: 2 | AF16: 1 | AG16: 1 | AH16: 1 | AI16: 2 | AJ16: 1 | AS16: 4 | AT16: 4 | AU16: 5 | AV16: 5 | AW16: 4 | AX16: 4 | AY16: 4 | AZ16: 4 | BA16: 4 | BB16: 4 | BC16: 4 | BD16: 3 | BE16: 4 | BF16: 4 | BG16: 4 | BH16: 2 | BI16: 2 | BJ16: 4 | BK16: 4 | BL16: 2 | BM16: 4 | BN16: 2 | BO16: 4 | BP16: 4 | BQ16: 4 | BR16: 2 | BS16: 3 | BT16: 4 | BU16: 4 | BV16: 2 | BW16: 2 | BX16: 2 | BY16: 2 | BZ16: 2 | CA16: 2 | CB16: 2 | CC16: 2 | CD16: 2 | CE16: 4 | CF16: 2 | CG16: 2 | CL16: 2 | CQ16: 1 | CS16: 3 | CT16: 4 | CU16: 1 | CV16: 1 | CX16: 1 | CY16: 1 | CZ16: 3 | DB16: 10 | DC16: 10533 | DE16: 67aa8ca32e7acec145f34f7a | DF16: 0
A17: 45718.449 | B17: 45718.451 | C17: 0 | D17: 174.193.17.253 | E17: 100 | F17: 181 | G17: 1 | H17: 45718.451 | I17: R_53r0zR46p8tkHDK | N17: 40.7643 | O17: -74.148 | P17: anonymous | Q17: EN | R17: 1 | S17: 5d1e4f1d51bab90018162332 | T17: 1 | U17: 2 | W17: 1 | Y17: 3 | Z17: 1 | AA17: 1 | AB17: 2 | AC17: 2 | AD17: 2 | AE17: 1 | AF17: 2 | AG17: 2 | AH17: 2 | AI17: 1 | AJ17: 2 | AK17: 2 | AL17: 2 | AN17: 2 | AO17: 2 | AP17: 5 | AR17: 1 | AS17: 4 | AT17: 4 | AU17: 4 | AV17: 4 | AW17: 3 | AX17: 3 | AY17: 2 | AZ17: 3 | BA17: 3 | BB17: 3 | BC17: 3 | BD17: 4 | BE17: 4 | BF17: 4 | BG17: 3 | BH17: 4 | BI17: 4 | BJ17: 2 | BK17: 4 | BL17: 4 | BM17: 4 | BN17: 3 | BO17: 3 | BP17: 4 | BQ17: 4 | BR17: 3 | BS17: 3 | BT17: 4 | BU17: 4 | BV17: 4 | BW17: 4 | BX17: 4 | BY17: 4 | BZ17: 4 | CA17: 3 | CB17: 3 | CC17: 4 | CD17: 4 | CE17: 1 | CF17: 3 | CG17: 2 | CL17: 4 | CQ17: 1 | CS17: 2 | CT17: 3 | CU17: 4 | CV17: 1 | CX17: 1 | CY17: 1 | CZ17: 3 | DB17: 10 | DC17: 07644 | DE17: 5d1e4f1d51bab90018162332 | DF17: 0
A18: 45718.445 | B18: 45718.452 | C18: 0 | D18: 174.228.168.94 | E18: 100 | F18: 573 | G18: 1 | H18: 45718.452 | I18: R_5Pvqp2y5OE8crYY | N18: 28.4883 | O18: -81.4061 | P18: anonymous | Q18: EN | R18: 1 | S18: 673801f035173a7a962e8a7b | T18: 2 | U18: 1 | W18: 3 | Y18: 1 | Z18: 1 | AA18: 1 | AB18: 2 | AC18: 1 | AD18: 6 | AE18: 2 | AF18: 2 | AG18: 2 | AH18: 1 | AI18: 2 | AJ18: 1 | AS18: 4 | AT18: 4 | AU18: 4 | AV18: 4 | AW18: 3 | AX18: 3 | AY18: 4 | AZ18: 4 | BA18: 4 | BB18: 4 | BC18: 3 | BD18: 3 | BE18: 3 | BF18: 2 | BG18: 3 | BH18: 4 | BI18: 1 | BJ18: 3 | BK18: 3 | BL18: 4 | BM18: 4 | BN18: 4 | BO18: 3 | BP18: 2 | BQ18: 2 | BR18: 3 | BS18: 3 | BT18: 4 | BU18: 3 | BV18: 3 | BW18: 3 | BX18: 4 | BY18: 3 | BZ18: 2 | CA18: 3 | CB18: 3 | CC18: 3 | CD18: 3 | CE18: 4 | CF18: 2 | CG18: 1 | CH18: 3 | CI18: 1 | CJ18: 3 | CK18: 4 | CM18: 1 | CN18: 2 | CO18: 3 | CP18: 4 | CQ18: 1 | CS18: 6 | CT18: 2 | CU18: 4 | CV18: 4 | CX18: 1 | CY18: 2 | CZ18: 8 | DB18: 2 | DC18: 13905 | DE18: 673801f035173a7a962e8a7b | DF18: 0
A19: 45718.447 | B19: 45718.452 | C19: 0 | D19: 206.171.36.86 | E19: 100 | F19: 475 | G19: 1 | H19: 45718.452 | I19: R_6wzqVxZvgKxsGaQ | N19: 40.7785 | O19: -73.9898 | P19: anonymous | Q19: EN | R19: 1 | S19: 66844b7e12b7e64a89b7161e | T19: 2 | U19: 3 | W19: 2 | Y19: 1 | Z19: 1 | AA19: 1 | AB19: 2 | AC19: 3 | AD19: 3 | AE19: 2 | AF19: 1 | AG19: 2 | AH19: 2 | AI19: 2 | AJ19: 1 | AS19: 4 | AT19: 4 | AU19: 4 | AV19: 4 | AW19: 3 | AX19: 3 | AY19: 3 | AZ19: 2 | BA19: 4 | BB19: 4 | BC19: 3 | BD19: 4 | BE19: 3 | BF19: 5 | BG19: 4 | BH19: 5 | BI19: 3 | BJ19: 5 | BK19: 4 | BL19: 4 | BM19: 4 | BN19: 4 | BO19: 3 | BP19: 5 | BQ19: 4 | BR19: 4 | BS19: 3 | BT19: 3 | BU19: 3 | BV19: 3 | BW19: 2 | BX19: 3 | BY19: 3 | BZ19: 2 | CA19: 2 | CB19: 1 | CC19: 1 | CD19: 2 | CE19: 2 | CF19: 1 | CG19: 1 | CH19: 1 | CI19: 1 | CJ19: 2 | CK19: 4 | CM19: 2 | CN19: 4 | CO19: 3 | CP19: 1 | CQ19: 1 | CS19: 2 | CT19: 4 | CU19: 4 | CV19: 1 | CX19: 1 | CY19: 1 | CZ19: 3 | DB19: 10 | DC19: 10065 | DE19: 66844b7e12b7e64a89b7161e | DF19: 0
A20: 45718.445 | B20: 45718.452 | C20: 0 | D20: 69.122.17.118 | E20: 100 | F20: 680 | G20: 1 | H20: 45718.452 | I20: R_5EhysVaDFYIVjUQ | N20: 40.5175 | O20: -74.3991 | P20: anonymous | Q20: EN | R20: 1 | S20: 5f32e130f2bc3308c42ca980 | T20: 1 | U20: 2 | W20: 1 | Y20: 1 | Z20: 2 | AA20: 1 | AB20: 2 | AC20: 2 | AD20: 5 | AE20: 1 | AF20: 2 | AG20: 2 | AH20: 2 | AI20: 2 | AJ20: 1 | AS20: 3 | AT20: 3 | AU20: 4 | AV20: 3 | AW20: 3 | AX20: 4 | AY20: 1 | AZ20: 3 | BA20: 2 | BB20: 2 | BC20: 2 | BD20: 1 | BE20: 2 | BF20: 1 | BG20: 1 | BH20: 4 | BI20: 2 | BJ20: 1 | BK20: 4 | BL20: 2 | BM20: 2 | BN20: 2 | BO20: 1 | BP20: 4 | BQ20: 2 | BR20: 2 | BS20: 3 | BT20: 1 | BU20: 2 | BV20: 4 | BW20: 3 | BX20: 2 | BY20: 2 | BZ20: 2 | CA20: 4 | CB20: 4 | CC20: 2 | CD20: 4 | CE20: 4 | CF20: 4 | CG20: 2 | CL20: 4 | CQ20: 1 | CS20: 1 | CT20: 2 | CU20: 4 | CV20: 2 | CX20: 1 | CY20: 1 | CZ20: 3 | DB20: 9 | DC20: 08812 | DE20: 5f32e130f2bc3308c42ca980 | DF20: 0
A21: 45718.438 | B21: 45718.453 | C21: 0 | D21: 100.1.103.81 | E21: 100 | F21: 1295 | G21: 1 | H21: 45718.453 | I21: R_1rYPsnL5gvUgEpI | N21: 40.6342 | O21: -74.2427 | P21: anonymous | Q21: EN | R21: 1 | S21: 5fe17e28d8918b3fae67ec4d | T21: 1 | U21: 5 | V21: Apartment | W21: 1 | Y21: 2 | Z21: 1 | AA21: 1 | AB21: 1 | AC21: 1 | AD21: 2 | AE21: 1 | AF21: 2 | AG21: 2 | AH21: 2 | AI21: 2 | AJ21: 1 | AS21: 4 | AT21: 4 | AU21: 3 | AV21: 5 | AW21: 3 | AX21: 4 | AY21: 4 | AZ21: 4 | BA21: 3 | BB21: 3 | BC21: 3 | BD21: 5 | BE21: 5 | BF21: 5 | BG21: 3 | BH21: 5 | BI21: 5 | BJ21: 5 | BK21: 3 | BL21: 4 | BM21: 3 | BN21: 4 | BO21: 4 | BP21: 3 | BQ21: 4 | BR21: 4 | BS21: 3 | BT21: 5 | BU21: 4 | BV21: 4 | BW21: 4 | BX21: 4 | BY21: 3 | BZ21: 5 | CA21: 5 | CB21: 3 | CC21: 4 | CD21: 4 | CE21: 4 | CF21: 4 | CG21: 5 | CL21: 4 | CQ21: 2 | CS21: 3 | CT21: 2 | CU21: 2 | CV21: 2 | CX21: 1 | CY21: 2 | CZ21: 8 | DA21: Self Employed | DB21: 7 | DC21: 07203 | DE21: 5fe17e28d8918b3fae67ec4d | DF21: 0
A22: 45718.448 | B22: 45718.453 | C22: 0 | D22: 24.45.107.178 | E22: 100 | F22: 401 | G22: 1 | H22: 45718.453 | I22: R_8rPdCIJV9rEWXdd | N22: 40.9451 | O22: -74.2531 | P22: anonymous | Q22: EN | R22: 1 | S22: 673248c019806a9412a13c6a | T22: 1 | U22: 1 | W22: 2 | Y22: 1 | Z22: 2 | AA22: 1 | AB22: 2 | AC22: 2 | AD22: 2 | AE22: 1 | AF22: 2 | AG22: 2 | AH22: 2 | AI22: 2 | AJ22: 1 | AS22: 2 | AT22: 2 | AU22: 2 | AV22: 2 | AW22: 2 | AX22: 3 | AY22: 1 | AZ22: 1 | BA22: 1 | BB22: 1 | BC22: 1 | BD22: 1 | BE22: 1 | BF22: 4 | BG22: 3 | BH22: 4 | BI22: 4 | BJ22: 3 | BK22: 3 | BL22: 3 | BM22: 4 | BN22: 2 | BO22: 4 | BP22: 4 | BQ22: 4 | BR22: 5 | BS22: 3 | BT22: 3 | BU22: 3 | BV22: 4 | BW22: 4 | BX22: 4 | BY22: 4 | BZ22: 3 | CA22: 3 | CB22: 3 | CC22: 1 | CD22: 3 | CE22: 4 | CF22: 2 | CG22: 1 | CH22: 1 | CI22: 1 | CJ22: 4 | CK22: 3 | CM22: 2 | CN22: 4 | CO22: 3 | CP22: 1 | CQ22: 2 | CS22: 2 | CT22: 3 | CU22: 4 | CV22: 1 | CX22: 1 | CY22: 1 | CZ22: 8 | DA22: Consulting | DB22: 10 | DC22: 07055 | DE22: 673248c019806a9412a13c6a | DF22: 0
A23: 45718.448 | B23: 45718.453 | C23: 0 | D23: 73.197.61.23 | E23: 100 | F23: 463 | G23: 1 | H23: 45718.454 | I23: R_5gUbb8dSsYwb7fo | N23: 39.9152 | O23: -75.0739 | P23: anonymous | Q23: EN | R23: 1 | S23: 66d9e222230df4e7c576f1b2 | T23: 1 | U23: 1 | W23: 1 | Y23: 1 | Z23: 2 | AA23: 1 | AB23: 1 | AC23: 4 | AD23: 3 | AE23: 1 | AF23: 2 | AG23: 1 | AH23: 2 | AI23: 1 | AJ23: 2 | AK23: 1 | AL23: 2 | AN23: 5 | AO23: 2 | AP23: 5 | AR23: 1 | AS23: 4 | AT23: 4 | AU23: 4 | AV23: 4 | AW23: 4 | AX23: 4 | AY23: 4 | AZ23: 4 | BA23: 4 | BB23: 3 | BC23: 4 | BD23: 1 | BE23: 4 | BF23: 2 | BG23: 1 | BH23: 4 | BI23: 4 | BJ23: 4 | BK23: 4 | BL23: 4 | BM23: 4 | BN23: 2 | BO23: 4 | BP23: 4 | BQ23: 4 | BR23: 3 | BS23: 3 | BT23: 4 | BU23: 4 | BV23: 3 | BW23: 2 | BX23: 3 | BY23: 3 | BZ23: 1 | CA23: 3 | CB23: 3 | CC23: 1 | CD23: 3 | CE23: 1 | CF23: 3 | CG23: 1 | CL23: 3 | CQ23: 1 | CS23: 3 | CT23: 2 | CU23: 4 | CV23: 1 | CX23: 1 | CY23: 1 | CZ23: 8 | DB23: 7 | DC23: 08107 | DE23: 66d9e222230df4e7c576f1b2 | DF23: 0
A24: 45718.437 | B24: 45718.454 | C24: 0 | D24: 97.216.98.43 | E24: 100 | F24: 1506 | G24: 1 | H24: 45718.454 | I24: R_7qvLwtxdOOTTTKP | N24: 40.5995 | O24: -75.3763 | P24: anonymous | Q24: EN | R24: 1 | S24: 666c44e0af1439ede48b2d93 | T24: 1 | U24: 2 | W24: 1 | Y24: 7 | Z24: 1 | AA24: 1 | AB24: 2 | AC24: 2 | AD24: 3 | AE24: 1 | AF24: 2 | AG24: 1 | AH24: 2 | AI24: 2 | AJ24: 1 | AS24: 3 | AT24: 3 | AU24: 4 | AV24: 3 | AW24: 2 | AX24: 3 | AY24: 2 | AZ24: 2 | BA24: 3 | BB24: 3 | BC24: 2 | BD24: 3 | BE24: 3 | BF24: 4 | BG24: 2 | BH24: 4 | BI24: 3 | BJ24: 3 | BK24: 4 | BL24: 2 | BM24: 3 | BN24: 3 | BO24: 4 | BP24: 3 | BQ24: 3 | BR24: 2 | BS24: 3 | BT24: 3 | BU24: 4 | BV24: 4 | BW24: 3 | BX24: 4 | BY24: 4 | BZ24: 3 | CA24: 3 | CB24: 4 | CC24: 3 | CD24: 3 | CE24: 4 | CF24: 3 | CG24: 2 | CL24: 4 | CQ24: 1 | CS24: 2 | CT24: 3 | CU24: 1 | CV24: 1 | CX24: 1 | CY24: 1 | CZ24: 6 | DB24: 9 | DC24: 07522 | DE24: 666c44e0af1439ede48b2d93 | DF24: 0
A25: 45718.449 | B25: 45718.455 | C25: 0 | D25: 71.187.58.246 | E25: 100 | F25: 480 | G25: 1 | H25: 45718.455 | I25: R_3liyglzDTPXMRxI | N25: 40.8897 | O25: -74.4847 | P25: anonymous | Q25: EN | R25: 1 | S25: 66d62734985c822b67585824 | T25: 1 | U25: 1 | W25: 2 | Y25: 4 | Z25: 1 | AA25: 1 | AB25: 1 | AC25: 5 | AD25: 2 | AE25: 1 | AF25: 2 | AG25: 1 | AH25: 1 | AI25: 1 | AJ25: 2 | AK25: 1 | AL25: 2 | AN25: 2 | AO25: 2 | AP25: 4 | AQ25: trenches | AR25: 2 | AS25: 5 | AT25: 5 | AU25: 5 | AV25: 5 | AW25: 5 | AX25: 4 | AY25: 4 | AZ25: 5 | BA25: 5 | BB25: 5 | BC25: 5 | BD25: 4 | BE25: 4 | BF25: 5 | BG25: 3 | BH25: 3 | BI25: 4 | BJ25: 5 | BK25: 5 | BL25: 5 | BM25: 5 | BN25: 5 | BO25: 3 | BP25: 4 | BQ25: 4 | BR25: 4 | BS25: 3 | BT25: 5 | BU25: 4 | BV25: 2 | BW25: 1 | BX25: 2 | BY25: 4 | BZ25: 2 | CA25: 2 | CB25: 4 | CC25: 2 | CD25: 2 | CE25: 3 | CF25: 4 | CG25: 1 | CH25: 3 | CI25: 2 | CJ25: 2 | CK25: 3 | CM25: 1 | CN25: 3 | CO25: 4 | CP25: 2 | CQ25: 2 | CS25: 6 | CT25: 4 | CU25: 4 | CV25: 4 | CX25: 1 | CY25: 2 | CZ25: 4 | DB25: 10 | DC25: 07834 | DE25: 66d62734985c822b67585824 | DF25: 0
A26: 45718.451 | B26: 45718.455 | C26: 0 | D26: 173.70.93.189 | E26: 100 | F26: 357 | G26: 1 | H26: 45718.455 | I26: R_6lZCLQhEvYvmac1 | N26: 40.7938 | O26: -74.4878 | P26: anonymous | Q26: EN | R26: 1 | S26: 6785ca7bd996dd759b99217c | T26: 1 | U26: 1 | W26: 1 | Y26: 4 | Z26: 2 | AA26: 1 | AB26: 2 | AC26: 5 | AD26: 2 | AE26: 1 | AF26: 2 | AG26: 1 | AH26: 2 | AI26: 2 | AJ26: 1 | AS26: 4 | AT26: 4 | AU26: 4 | AV26: 4 | AW26: 4 | AX26: 4 | AY26: 3 | AZ26: 3 | BA26: 4 | BB26: 4 | BC26: 2 | BD26: 4 | BE26: 2 | BF26: 5 | BG26: 2 | BH26: 4 | BI26: 2 | BJ26: 2 | BK26: 2 | BL26: 2 | BM26: 2 | BN26: 2 | BO26: 4 | BP26: 4 | BQ26: 4 | BR26: 4 | BS26: 3 | BT26: 2 | BU26: 2 | BV26: 4 | BW26: 4 | BX26: 4 | BY26: 5 | BZ26: 4 | CA26: 4 | CB26: 4 | CC26: 2 | CD26: 4 | CE26: 4 | CF26: 3 | CG26: 1 | CL26: 1 | CQ26: 1 | CS26: 1 | CT26: 2 | CU26: 4 | CV26: 3 | CX26: 1 | CY26: 2 | CZ26: 3 | DB26: 10 | DC26: 07960 | DE26: 6785ca7bd996dd759b99217c | DF26: 0
A27: 45718.446 | B27: 45718.455 | C27: 0 | D27: 68.198.232.88 | E27: 100 | F27: 840 | G27: 1 | H27: 45718.455 | I27: R_5GLWmm5OtVYqHbH | N27: 41.5965 | O27: -73.911 | P27: anonymous | Q27: EN | R27: 1 | S27: 677618e6c8caeb6caebd74a3 | T27: 2 | U27: 3 | W27: 2 | Y27: 3 | Z27: 1 | AA27: 1 | AB27: 1 | AC27: 2 | AD27: 4 | AE27: 1 | AF27: 2 | AG27: 2 | AH27: 1 | AI27: 2 | AJ27: 1 | AS27: 3 | AT27: 4 | AU27: 4 | AV27: 4 | AW27: 4 | AX27: 4 | AY27: 3 | AZ27: 3 | BA27: 3 | BB27: 2 | BC27: 3 | BD27: 2 | BE27: 2 | BF27: 4 | BG27: 1 | BH27: 3 | BI27: 3 | BJ27: 3 | BK27: 4 | BL27: 4 | BM27: 4 | BN27: 4 | BO27: 3 | BP27: 3 | BQ27: 4 | BR27: 2 | BS27: 3 | BT27: 4 | BU27: 4 | BV27: 3 | BW27: 3 | BX27: 3 | BY27: 3 | BZ27: 3 | CA27: 2 | CB27: 4 | CC27: 3 | CD27: 3 | CE27: 4 | CF27: 3 | CG27: 1 | CH27: 3 | CI27: 1 | CJ27: 4 | CK27: 4 | CM27: 2 | CN27: 3 | CO27: 1 | CP27: 4 | CQ27: 1 | CS27: 6 | CT27: 3 | CU27: 1 | CV27: 2 | CX27: 1 | CY27: 2 | CZ27: 2 | DB27: 6 | DC27: 10516 | DE27: 677618e6c8caeb6caebd74a3 | DF27: 0
A28: 45718.452 | B28: 45718.456 | C28: 0 | D28: 172.56.34.232 | E28: 100 | F28: 378 | G28: 1 | H28: 45718.456 | I28: R_1DAbsY8hNr79C9I | N28: 40.7252 | O28: -73.944 | P28: anonymous | Q28: EN | R28: 1 | S28: 67670cf22cf98294c8fbcfbc | T28: 2 | U28: 1 | W28: 1 | Y28: 4 | Z28: 1 | AA28: 1 | AB28: 1 | AC28: 2 | AD28: 2 | AE28: 2 | AF28: 2 | AG28: 2 | AH28: 2 | AI28: 1 | AJ28: 2 | AK28: 3 | AL28: 1 | AN28: 2 | AO28: 1 | AP28: 1 | AR28: 2 | AS28: 5 | AT28: 5 | AU28: 5 | AV28: 5 | AW28: 5 | AX28: 4 | AY28: 5 | AZ28: 5 | BA28: 5 | BB28: 5 | BC28: 5 | BD28: 5 | BE28: 4 | BF28: 4 | BG28: 5 | BH28: 5 | BI28: 5 | BJ28: 5 | BK28: 5 | BL28: 5 | BM28: 5 | BN28: 5 | BO28: 5 | BP28: 5 | BQ28: 5 | BR28: 4 | BS28: 3 | BT28: 5 | BU28: 5 | BV28: 4 | BW28: 4 | BX28: 5 | BY28: 5 | BZ28: 5 | CA28: 4 | CB28: 4 | CC28: 4 | CD28: 4 | CE28: 1 | CF28: 3 | CG28: 4 | CL28: 4 | CQ28: 1 | CS28: 3 | CT28: 4 | CU28: 2 | CV28: 1 | CX28: 1 | CY28: 1 | CZ28: 2 | DB28: 10 | DC28: 10007 | DE28: 67670cf22cf98294c8fbcfbc | DF28: 0
A29: 45718.453 | B29: 45718.457 | C29: 0 | D29: 100.33.47.210 | E29: 100 | F29: 288 | G29: 1 | H29: 45718.457 | I29: R_3KKRE7EjOiT1EfD | N29: 40.6952 | O29: -73.6596 | P29: anonymous | Q29: EN | R29: 1 | S29: 6647b8648a67a4ef6585458a | T29: 2 | U29: 1 | W29: 4 | X29: live with partner who owns | Y29: 1 | Z29: 2 | AA29: 1 | AB29: 2 | AC29: 2 | AD29: 2 | AE29: 1 | AF29: 2 | AG29: 2 | AH29: 2 | AI29: 2 | AJ29: 1 | AS29: 4 | AT29: 4 | AU29: 5 | AV29: 5 | AW29: 4 | AX29: 3 | AY29: 2 | AZ29: 2 | BA29: 3 | BB29: 3 | BC29: 1 | BD29: 1 | BE29: 4 | BF29: 3 | BG29: 1 | BH29: 1 | BI29: 1 | BJ29: 2 | BK29: 2 | BL29: 2 | BM29: 2 | BN29: 1 | BO29: 1 | BP29: 2 | BQ29: 2 | BR29: 1 | BS29: 3 | BT29: 1 | BU29: 1 | BV29: 4 | BW29: 3 | BX29: 4 | BY29: 5 | BZ29: 3 | CA29: 4 | CB29: 4 | CC29: 3 | CD29: 3 | CE29: 4 | CF29: 4 | CG29: 2 | CQ29: 1 | CS29: 2 | CT29: 2 | CU29: 3 | CV29: 5 | CW29: self employed | CX29: 1 | CY29: 2 | CZ29: 8 | DA29: online sales | DB29: 1 | DC29: 11554 | DE29: 6647b8648a67a4ef6585458a | DF29: 0
A30: 45718.443 | B30: 45718.457 | C30: 0 | D30: 73.29.45.64 | E30: 100 | F30: 1196 | G30: 1 | H30: 45718.457 | I30: R_7Us9ZnBCXDFuPWV | N30: 40.8566 | O30: -74.8389 | P30: anonymous | Q30: EN | R30: 1 | S30: 65e235e4ac7b9bc14ae3e92e | T30: 1 | U30: 1 | W30: 2 | Y30: 2 | Z30: 1 | AA30: 1 | AB30: 2 | AC30: 5 | AD30: 4 | AE30: 1 | AF30: 1 | AG30: 1 | AH30: 2 | AI30: 2 | AJ30: 1 | AS30: 5 | AT30: 5 | AU30: 5 | AV30: 5 | AW30: 5 | AX30: 5 | AY30: 5 | AZ30: 5 | BA30: 5 | BB30: 5 | BC30: 5 | BD30: 5 | BE30: 5 | BF30: 5 | BG30: 5 | BH30: 2 | BI30: 2 | BJ30: 4 | BK30: 4 | BL30: 5 | BM30: 4 | BN30: 4 | BO30: 2 | BP30: 2 | BQ30: 2 | BR30: 2 | BS30: 3 | BT30: 4 | BU30: 4 | BV30: 1 | BW30: 1 | BX30: 3 | BY30: 4 | BZ30: 2 | CA30: 4 | CB30: 4 | CC30: 3 | CD30: 5 | CE30: 4 | CF30: 2 | CG30: 3 | CH30: 1 | CI30: 2 | CJ30: 1 | CK30: 2 | CM30: 1 | CN30: 2 | CO30: 4 | CP30: 3 | CQ30: 5 | CR30: non binary | CS30: 2 | CT30: 3 | CU30: 3 | CV30: 1 | CX30: 1 | CY30: 2 | CZ30: 2 | DB30: 10 | DC30: 07840 | DE30: 65e235e4ac7b9bc14ae3e92e | DF30: 0
A31: 45718.453 | B31: 45718.457 | C31: 0 | D31: 68.174.198.200 | E31: 100 | F31: 335 | G31: 1 | H31: 45718.457 | I31: R_5S81XwVoPSccmwp | N31: 40.7484 | O31: -73.862 | P31: anonymous | Q31: EN | R31: 1 | S31: 66b963229da98baf6c9d457d | T31: 2 | U31: 3 | W31: 2 | Y31: 1 | Z31: 2 | AA31: 1 | AB31: 2 | AC31: 2 | AD31: 5 | AE31: 1 | AF31: 2 | AG31: 1 | AH31: 2 | AI31: 2 | AJ31: 1 | AS31: 2 | AT31: 2 | AU31: 4 | AV31: 3 | AW31: 3 | AX31: 4 | AY31: 2 | AZ31: 2 | BA31: 2 | BB31: 2 | BC31: 3 | BD31: 1 | BE31: 3 | BF31: 4 | BG31: 1 | BH31: 2 | BI31: 2 | BJ31: 3 | BK31: 3 | BL31: 2 | BM31: 2 | BN31: 2 | BO31: 2 | BP31: 2 | BQ31: 2 | BR31: 2 | BS31: 3 | BT31: 2 | BU31: 2 | BV31: 2 | BW31: 2 | BX31: 1 | BY31: 3 | BZ31: 3 | CA31: 2 | CB31: 3 | CC31: 3 | CD31: 1 | CE31: 1 | CF31: 4 | CG31: 1 | CH31: 1 | CI31: 1 | CJ31: 3 | CK31: 1 | CM31: 2 | CN31: 3 | CO31: 1 | CP31: 4 | CQ31: 2 | CS31: 4 | CT31: 2 | CU31: 4 | CV31: 1 | CX31: 1 | CY31: 2 | CZ31: 8 | DA31: technology | DB31: 10 | DC31: 11372 | DE31: 66b963229da98baf6c9d457d | DF31: 0
A32: 45718.454 | B32: 45718.459 | C32: 0 | D32: 174.166.162.165 | E32: 100 | F32: 442 | G32: 1 | H32: 45718.459 | I32: R_1Hq3RYDnjMEYzGj | N32: 40.4668 | O32: -74.6607 | P32: anonymous | Q32: EN | R32: 1 | S32: 5f4f9bc1f7598f06b2dc816f | T32: 1 | U32: 1 | W32: 3 | Y32: 4 | Z32: 1 | AA32: 1 | AB32: 2 | AC32: 2 | AD32: 3 | AE32: 1 | AF32: 2 | AG32: 2 | AH32: 1 | AI32: 2 | AJ32: 1 | AS32: 4 | AT32: 4 | AU32: 4 | AV32: 4 | AW32: 2 | AX32: 4 | AY32: 1 | AZ32: 3 | BA32: 2 | BB32: 2 | BC32: 4 | BD32: 2 | BE32: 4 | BF32: 2 | BG32: 1 | BH32: 2 | BI32: 2 | BJ32: 2 | BK32: 4 | BL32: 2 | BM32: 2 | BN32: 2 | BO32: 2 | BP32: 2 | BQ32: 2 | BR32: 2 | BS32: 3 | BT32: 2 | BU32: 2 | BV32: 2 | BW32: 2 | BX32: 2 | BY32: 4 | BZ32: 2 | CA32: 2 | CB32: 4 | CC32: 2 | CD32: 2 | CE32: 4 | CF32: 2 | CG32: 1 | CH32: 2 | CI32: 1 | CJ32: 2 | CK32: 3 | CM32: 2 | CN32: 4 | CO32: 3 | CP32: 1 | CQ32: 2 | CS32: 6 | CT32: 4 | CU32: 4 | CV32: 4 | CX32: 1 | CY32: 2 | CZ32: 8 | DA32: Tech | DB32: 10 | DC32: 07052 | DE32: 5f4f9bc1f7598f06b2dc816f | DF32: 0
A33: 45718.456 | B33: 45718.459 | C33: 0 | D33: 47.18.97.210 | E33: 100 | F33: 291 | G33: 1 | H33: 45718.459 | I33: R_6Lh77PphWYamqEa | N33: 40.5802 | O33: -74.3594 | P33: anonymous | Q33: EN | R33: 1 | S33: 67ad00c159b7e9d25ec4e04c | T33: 1 | U33: 1 | W33: 2 | Y33: 5 | Z33: 2 | AA33: 1 | AB33: 1 | AC33: 4 | AD33: 4 | AE33: 1 | AF33: 2 | AG33: 2 | AH33: 2 | AI33: 2 | AJ33: 1 | AS33: 4 | AT33: 4 | AU33: 3 | AV33: 3 | AW33: 3 | AX33: 4 | AY33: 2 | AZ33: 3 | BA33: 3 | BB33: 3 | BC33: 4 | BD33: 4 | BE33: 3 | BF33: 5 | BG33: 3 | BH33: 5 | BI33: 2 | BJ33: 2 | BK33: 2 | BL33: 2 | BM33: 2 | BN33: 1 | BO33: 1 | BP33: 1 | BQ33: 2 | BR33: 4 | BS33: 3 | BT33: 1 | BU33: 1 | BV33: 4 | BW33: 3 | BX33: 3 | BY33: 4 | BZ33: 2 | CA33: 2 | CB33: 4 | CC33: 2 | CD33: 3 | CE33: 4 | CF33: 1 | CG33: 1 | CH33: 4 | CI33: 1 | CJ33: 3 | CK33: 3 | CM33: 1 | CN33: 2 | CO33: 3 | CP33: 4 | CQ33: 1 | CS33: 1 | CT33: 3 | CU33: 1 | CV33: 5 | CW33: Student | CX33: 1 | CY33: 1 | CZ33: 3 | DB33: 10 | DC33: 08902 | DE33: 67ad00c159b7e9d25ec4e04c | DF33: 0
A34: 45718.434 | B34: 45718.46 | C34: 0 | D34: 172.59.211.131 | E34: 100 | F34: 2243 | G34: 1 | H34: 45718.46 | I34: R_1MoHhb8nOc7fyiR | N34: 40.7463 | O34: -74.1553 | P34: anonymous | Q34: EN | R34: 1 | S34: 67be05692b18b631ece5fd2e | T34: 1 | U34: 2 | W34: 1 | Y34: 5 | Z34: 2 | AA34: 1 | AB34: 1 | AC34: 4 | AD34: 2 | AE34: 1 | AF34: 1 | AG34: 2 | AH34: 2 | AI34: 2 | AJ34: 1 | AS34: 3 | AT34: 4 | AU34: 4 | AV34: 4 | AW34: 4 | AX34: 4 | AY34: 4 | AZ34: 5 | BA34: 5 | BB34: 4 | BC34: 4 | BD34: 5 | BE34: 5 | BF34: 5 | BG34: 4 | BH34: 4 | BI34: 4 | BJ34: 3 | BK34: 4 | BL34: 4 | BM34: 4 | BN34: 4 | BO34: 4 | BP34: 4 | BQ34: 4 | BR34: 4 | BS34: 3 | BT34: 4 | BU34: 4 | BV34: 4 | BW34: 5 | BX34: 4 | BY34: 4 | BZ34: 4 | CA34: 5 | CB34: 5 | CC34: 4 | CD34: 5 | CE34: 4 | CF34: 4 | CG34: 1 | CL34: 1 | CQ34: 1 | CS34: 1 | CT34: 4 | CU34: 4 | CV34: 1 | CX34: 1 | CY34: 1 | CZ34: 4 | DB34: 7 | DC34: 07206 | DE34: 67be05692b18b631ece5fd2e | DF34: 0
A35: 45718.45 | B35: 45718.46 | C35: 0 | D35: 216.59.90.100 | E35: 100 | F35: 939 | G35: 1 | H35: 45718.46 | I35: R_8PGhRhNqdcHJ29r | N35: 42.1254 | O35: -75.9664 | P35: anonymous | Q35: EN | R35: 1 | S35: 669aabcd5c4869b3bb6d7761 | T35: 2 | U35: 1 | W35: 2 | Y35: 1 | Z35: 1 | AA35: 1 | AB35: 2 | AC35: 4 | AD35: 3 | AE35: 1 | AF35: 1 | AG35: 1 | AH35: 2 | AI35: 2 | AJ35: 1 | AS35: 3 | AT35: 4 | AU35: 4 | AV35: 4 | AW35: 4 | AX35: 4 | AY35: 3 | AZ35: 4 | BA35: 4 | BB35: 4 | BC35: 2 | BD35: 4 | BE35: 4 | BF35: 4 | BG35: 4 | BH35: 2 | BI35: 2 | BJ35: 2 | BK35: 4 | BL35: 4 | BM35: 4 | BN35: 4 | BO35: 4 | BP35: 3 | BQ35: 2 | BR35: 2 | BS35: 3 | BT35: 3 | BU35: 2 | BV35: 4 | BW35: 3 | BX35: 4 | BY35: 4 | BZ35: 2 | CA35: 3 | CB35: 5 | CC35: 4 | CD35: 4 | CE35: 4 | CF35: 1 | CG35: 1 | CH35: 4 | CI35: 2 | CJ35: 4 | CK35: 4 | CM35: 2 | CN35: 4 | CO35: 3 | CP35: 1 | CQ35: 1 | CS35: 3 | CT35: 3 | CU35: 4 | CV35: 2 | CX35: 1 | CY35: 1 | CZ35: 8 | DA35: Religious | DB35: 10 | DC35: 13760 | DD35: Add a section for community college level education. I have a two year associates degree. | DE35: 669aabcd5c4869b3bb6d7761 | DF35: 0
A36: 45718.455 | B36: 45718.461 | C36: 0 | D36: 73.226.240.208 | E36: 100 | F36: 500 | G36: 1 | H36: 45718.461 | I36: R_3oXUSI5RONhDdLb | N36: 40.7238 | O36: -74.2293 | P36: anonymous | Q36: EN | R36: 1 | S36: 660ec4452539f6860b02db7a | T36: 1 | U36: 1 | W36: 2 | Y36: 1 | Z36: 1 | AA36: 1 | AB36: 2 | AC36: 4 | AD36: 3 | AE36: 1 | AF36: 1 | AG36: 1 | AH36: 2 | AI36: 1 | AJ36: 2 | AK36: 1 | AL36: 1 | AM36: 2024 | AN36: 2 | AO36: 2 | AP36: 4 | AQ36: Fix sump pump | AR36: 1 | AS36: 4 | AT36: 4 | AU36: 4 | AV36: 4 | AW36: 3 | AX36: 3 | AY36: 2 | AZ36: 3 | BA36: 4 | BB36: 5 | BC36: 3 | BD36: 1 | BE36: 1 | BF36: 4 | BG36: 2 | BH36: 2 | BI36: 4 | BJ36: 4 | BK36: 4 | BL36: 3 | BM36: 3 | BN36: 2 | BO36: 1 | BP36: 4 | BQ36: 4 | BR36: 4 | BS36: 3 | BT36: 2 | BU36: 4 | BV36: 2 | BW36: 2 | BX36: 1 | BY36: 2 | BZ36: 2 | CA36: 4 | CB36: 5 | CC36: 2 | CD36: 3 | CE36: 4 | CF36: 1 | CG36: 1 | CH36: 2 | CI36: 1 | CJ36: 4 | CK36: 5 | CM36: 4 | CN36: 3 | CO36: 1 | CP36: 2 | CQ36: 2 | CS36: 3 | CT36: 3 | CU36: 4 | CV36: 1 | CX36: 1 | CY36: 1 | CZ36: 6 | DB36: 10 | DC36: 07033 | DE36: 660ec4452539f6860b02db7a | DF36: 0
A37: 45718.453 | B37: 45718.461 | C37: 0 | D37: 75.208.4.36 | E37: 100 | F37: 665 | G37: 1 | H37: 45718.461 | I37: R_5clmEpgYZUy7Ovv | N37: 35.8677 | O37: -86.4174 | P37: anonymous | Q37: EN | R37: 1 | S37: 67a9addacffc14df077673fe | T37: 1 | U37: 1 | W37: 2 | Y37: 1 | Z37: 2 | AA37: 1 | AB37: 2 | AC37: 8 | AD37: 5 | AE37: 1 | AF37: 2 | AG37: 1 | AH37: 2 | AI37: 1 | AJ37: 2 | AK37: 2 | AL37: 1 | AM37: 2021 | AN37: 2 | AO37: 2 | AP37: 5 | AR37: 1 | AS37: 4 | AT37: 4 | AU37: 4 | AV37: 4 | AW37: 4 | AX37: 5 | AY37: 3 | AZ37: 3 | BA37: 3 | BB37: 3 | BC37: 2 | BD37: 2 | BE37: 3 | BF37: 4 | BG37: 2 | BH37: 5 | BI37: 3 | BJ37: 2 | BK37: 2 | BL37: 2 | BM37: 2 | BN37: 2 | BO37: 3 | BP37: 3 | BQ37: 4 | BR37: 2 | BS37: 3 | BT37: 2 | BU37: 2 | BV37: 4 | BW37: 3 | BX37: 2 | BY37: 4 | BZ37: 3 | CA37: 2 | CB37: 4 | CC37: 3 | CD37: 2 | CE37: 4 | CF37: 2 | CG37: 1 | CH37: 2 | CI37: 1 | CJ37: 2 | CK37: 4 | CM37: 2 | CN37: 3 | CO37: 4 | CP37: 1 | CQ37: 1 | CS37: 1 | CT37: 2 | CU37: 4 | CV37: 5 | CW37: Student | CX37: 1 | CY37: 1 | CZ37: 8 | DA37: Student | DB37: 10 | DC37: 07044 | DE37: 67a9addacffc14df077673fe | DF37: 0
A38: 45718.456 | B38: 45718.461 | C38: 0 | D38: 173.70.61.204 | E38: 100 | F38: 463 | G38: 1 | H38: 45718.461 | I38: R_3v6lRkl3O5SDcbL | N38: 40.8177 | O38: -73.9771 | P38: anonymous | Q38: EN | R38: 1 | S38: 5e35e01b5bfa43595d69621d | T38: 1 | U38: 2 | W38: 2 | Y38: 1 | Z38: 2 | AA38: 1 | AB38: 2 | AC38: 7 | AD38: 6 | AE38: 3 | AF38: 2 | AG38: 1 | AH38: 2 | AI38: 1 | AJ38: 2 | AK38: 4 | AL38: 1 | AM38: none | AN38: 2 | AO38: 2 | AP38: 5 | AR38: 1 | AS38: 4 | AT38: 4 | AU38: 5 | AV38: 5 | AW38: 2 | AX38: 3 | AY38: 4 | AZ38: 5 | BA38: 5 | BB38: 5 | BC38: 3 | BD38: 2 | BE38: 4 | BF38: 5 | BG38: 3 | BH38: 4 | BI38: 4 | BJ38: 3 | BK38: 2 | BL38: 1 | BM38: 3 | BN38: 2 | BO38: 4 | BP38: 5 | BQ38: 5 | BR38: 2 | BS38: 3 | BT38: 2 | BU38: 2 | BV38: 1 | BW38: 2 | BX38: 3 | BY38: 4 | BZ38: 2 | CA38: 1 | CB38: 2 | CC38: 1 | CD38: 1 | CE38: 1 | CF38: 3 | CG38: 2 | CH38: 3 | CI38: 1 | CJ38: 2 | CK38: 4 | CM38: 1 | CN38: 4 | CO38: 2 | CP38: 3 | CQ38: 1 | CS38: 4 | CT38: 2 | CU38: 4 | CV38: 1 | CX38: 1 | CY38: 2 | CZ38: 3 | DB38: 10 | DC38: 07010 | DE38: 5e35e01b5bfa43595d69621d | DF38: 0
A39: 45718.449 | B39: 45718.462 | C39: 0 | D39: 108.27.129.2 | E39: 100 | F39: 1111 | G39: 1 | H39: 45718.462 | I39: R_3rccvsqNdiu4z1t | N39: 40.5828 | O39: -73.9532 | P39: anonymous | Q39: EN | R39: 1 | S39: 5b4991de56e0140001acb76b | T39: 2 | U39: 3 | W39: 1 | Y39: 2 | Z39: 1 | AA39: 1 | AB39: 2 | AC39: 4 | AD39: 4 | AE39: 2 | AF39: 2 | AG39: 2 | AH39: 2 | AI39: 1 | AJ39: 2 | AK39: 2 | AL39: 1 | AM39: 2023 | AN39: 2 | AO39: 2 | AP39: 3 | AR39: 1 | AS39: 4 | AT39: 3 | AU39: 4 | AV39: 3 | AW39: 3 | AX39: 4 | AY39: 3 | AZ39: 4 | BA39: 3 | BB39: 4 | BC39: 5 | BD39: 4 | BE39: 4 | BF39: 3 | BG39: 3 | BH39: 4 | BI39: 3 | BJ39: 4 | BK39: 4 | BL39: 4 | BM39: 5 | BN39: 4 | BO39: 4 | BP39: 4 | BQ39: 3 | BR39: 4 | BS39: 3 | BT39: 3 | BU39: 3 | BV39: 4 | BW39: 3 | BX39: 4 | BY39: 4 | BZ39: 3 | CA39: 4 | CB39: 3 | CC39: 4 | CD39: 4 | CE39: 1 | CF39: 4 | CG39: 1 | CL39: 3 | CQ39: 2 | CS39: 1 | CT39: 3 | CU39: 1 | CV39: 1 | CX39: 1 | CY39: 1 | CZ39: 4 | DB39: 7 | DC39: 11229 | DE39: 5b4991de56e0140001acb76b | DF39: 0
A40: 45718.457 | B40: 45718.463 | C40: 0 | D40: 76.37.0.39 | E40: 100 | F40: 452 | G40: 1 | H40: 45718.463 | I40: R_6c6BsxgV6QyXN05 | N40: 42.7227 | O40: -73.8178 | P40: anonymous | Q40: EN | R40: 1 | S40: 663e3c2870a87bac315ac450 | T40: 2 | U40: 1 | W40: 2 | Y40: 1 | Z40: 1 | AA40: 1 | AB40: 2 | AC40: 2 | AD40: 2 | AE40: 1 | AF40: 2 | AG40: 2 | AH40: 2 | AI40: 2 | AJ40: 1 | AS40: 4 | AT40: 4 | AU40: 5 | AV40: 5 | AW40: 4 | AX40: 3 | AY40: 4 | AZ40: 4 | BA40: 5 | BB40: 4 | BC40: 3 | BD40: 4 | BE40: 4 | BF40: 4 | BG40: 3 | BH40: 3 | BI40: 2 | BJ40: 2 | BK40: 4 | BL40: 4 | BM40: 3 | BN40: 3 | BO40: 3 | BP40: 3 | BQ40: 4 | BR40: 3 | BS40: 3 | BT40: 3 | BU40: 2 | BV40: 4 | BW40: 2 | BX40: 2 | BY40: 3 | BZ40: 2 | CA40: 2 | CB40: 3 | CC40: 1 | CD40: 3 | CE40: 4 | CF40: 4 | CG40: 1 | CH40: 3 | CI40: 2 | CJ40: 4 | CK40: 4 | CM40: 1 | CN40: 2 | CO40: 3 | CP40: 4 | CQ40: 1 | CS40: 1 | CT40: 3 | CU40: 4 | CV40: 1 | CX40: 1 | CY40: 2 | CZ40: 5 | DB40: 10 | DC40: 12208 | DE40: 663e3c2870a87bac315ac450 | DF40: 0
A41: 45718.459 | B41: 45718.463 | C41: 0 | D41: 67.82.209.86 | E41: 100 | F41: 327 | G41: 1 | H41: 45718.463 | I41: R_60oVePqoZbeyGC6 | N41: 40.6033 | O41: -74.633 | P41: anonymous | Q41: EN | R41: 1 | S41: 601e13b872774f263d64acac | T41: 1 | U41: 1 | W41: 1 | Y41: 1 | Z41: 1 | AA41: 1 | AB41: 2 | AC41: 1 | AD41: 3 | AE41: 1 | AF41: 2 | AG41: 2 | AH41: 2 | AI41: 2 | AJ41: 1 | AS41: 4 | AT41: 4 | AU41: 4 | AV41: 4 | AW41: 4 | AX41: 4 | AY41: 4 | AZ41: 4 | BA41: 4 | BB41: 4 | BC41: 3 | BD41: 3 | BE41: 3 | BF41: 3 | BG41: 3 | BH41: 3 | BI41: 3 | BJ41: 2 | BK41: 2 | BL41: 2 | BM41: 2 | BN41: 2 | BO41: 2 | BP41: 2 | BQ41: 2 | BR41: 2 | BS41: 3 | BT41: 3 | BU41: 3 | BV41: 3 | BW41: 3 | BX41: 2 | BY41: 3 | BZ41: 2 | CA41: 2 | CB41: 3 | CC41: 2 | CD41: 2 | CE41: 4 | CF41: 2 | CG41: 1 | CL41: 2 | CQ41: 2 | CS41: 2 | CT41: 4 | CU41: 4 | CV41: 1 | CX41: 1 | CY41: 2 | CZ41: 3 | DB41: 10 | DC41: 08880 | DE41: 601e13b872774f263d64acac | DF41: 0
A42: 45718.458 | B42: 45718.464 | C42: 0 | D42: 76.37.136.142 | E42: 100 | F42: 491 | G42: 1 | H42: 45718.464 | I42: R_7oBDnjdr1RLUjIS | N42: 43.114 | O42: -77.5689 | P42: anonymous | Q42: EN | R42: 1 | S42: 5ce83f6ffdd26c00193b9611 | T42: 2 | U42: 1 | W42: 1 | Y42: 7 | Z42: 2 | AA42: 1 | AB42: 2 | AC42: 1 | AD42: 2 | AE42: 1 | AF42: 2 | AG42: 2 | AH42: 2 | AI42: 2 | AJ42: 1 | AS42: 4 | AT42: 3 | AU42: 3 | AV42: 3 | AW42: 2 | AX42: 3 | AY42: 1 | AZ42: 4 | BA42: 3 | BB42: 4 | BC42: 3 | BD42: 2 | BE42: 2 | BF42: 4 | BG42: 3 | BH42: 1 | BI42: 1 | BJ42: 1 | BK42: 2 | BL42: 3 | BM42: 2 | BN42: 2 | BO42: 1 | BP42: 1 | BQ42: 1 | BR42: 1 | BS42: 3 | BT42: 2 | BU42: 3 | BV42: 3 | BW42: 2 | BX42: 4 | BY42: 4 | BZ42: 2 | CA42: 3 | CB42: 3 | CC42: 2 | CD42: 3 | CE42: 4 | CF42: 4 | CG42: 1 | CL42: 2 | CQ42: 2 | CS42: 4 | CT42: 3 | CU42: 4 | CV42: 2 | CX42: 1 | CY42: 2 | CZ42: 4 | DB42: 5 | DC42: 14618 | DE42: 5ce83f6ffdd26c00193b9611 | DF42: 0
A43: 45718.46 | B43: 45718.464 | C43: 0 | D43: 24.29.92.166 | E43: 100 | F43: 360 | G43: 1 | H43: 45718.464 | I43: R_1PbgeEd6MeA9Ogl | N43: 43.2312 | O43: -76.3008 | P43: anonymous | Q43: EN | R43: 1 | S43: 5ea4c85a360fe448ea95349d | T43: 2 | U43: 1 | W43: 1 | Y43: 6 | Z43: 2 | AA43: 1 | AB43: 2 | AC43: 1 | AD43: 1 | AE43: 1 | AF43: 2 | AG43: 2 | AH43: 2 | AI43: 2 | AJ43: 1 | AS43: 4 | AT43: 4 | AU43: 4 | AV43: 4 | AW43: 3 | AX43: 3 | AY43: 4 | AZ43: 4 | BA43: 4 | BB43: 4 | BC43: 3 | BD43: 3 | BE43: 4 | BF43: 4 | BG43: 3 | BH43: 2 | BI43: 2 | BJ43: 4 | BK43: 3 | BL43: 2 | BM43: 3 | BN43: 3 | BO43: 4 | BP43: 4 | BQ43: 3 | BR43: 3 | BS43: 3 | BT43: 3 | BU43: 3 | BV43: 3 | BW43: 3 | BX43: 3 | BY43: 4 | BZ43: 2 | CA43: 3 | CB43: 4 | CC43: 2 | CD43: 3 | CE43: 4 | CF43: 3 | CG43: 1 | CL43: 1 | CQ43: 1 | CS43: 4 | CT43: 4 | CU43: 4 | CV43: 1 | CX43: 1 | CY43: 1 | CZ43: 3 | DB43: 10 | DC43: 13090 | DE43: 5ea4c85a360fe448ea95349d | DF43: 0
A44: 45718.456 | B44: 45718.465 | C44: 0 | D44: 72.88.214.189 | E44: 100 | F44: 765 | G44: 1 | H44: 45718.465 | I44: R_5rPxYAZ0opJ1xJC | N44: 40.4992 | O44: -74.4996 | P44: anonymous | Q44: EN | R44: 1 | S44: 6770b51ac79cec8770eb7db3 | T44: 1 | U44: 1 | W44: 2 | Y44: 1 | Z44: 2 | AA44: 1 | AB44: 2 | AC44: 6 | AD44: 3 | AE44: 1 | AF44: 2 | AG44: 1 | AH44: 2 | AI44: 1 | AJ44: 2 | AK44: 2 | AL44: 2 | AN44: 2 | AO44: 2 | AP44: 5 | AR44: 1 | AS44: 3 | AT44: 3 | AU44: 3 | AV44: 3 | AW44: 4 | AX44: 4 | AY44: 2 | AZ44: 2 | BA44: 3 | BB44: 2 | BC44: 3 | BD44: 2 | BE44: 3 | BF44: 3 | BG44: 2 | BH44: 3 | BI44: 2 | BJ44: 2 | BK44: 4 | BL44: 2 | BM44: 4 | BN44: 2 | BO44: 2 | BP44: 4 | BQ44: 2 | BR44: 1 | BS44: 3 | BT44: 4 | BU44: 3 | BV44: 3 | BW44: 3 | BX44: 4 | BY44: 4 | BZ44: 2 | CA44: 3 | CB44: 4 | CC44: 3 | CD44: 4 | CE44: 1 | CF44: 4 | CG44: 1 | CH44: 4 | CI44: 3 | CJ44: 3 | CK44: 4 | CM44: 1 | CN44: 2 | CO44: 3 | CP44: 4 | CQ44: 2 | CS44: 3 | CT44: 3 | CU44: 4 | CV44: 1 | CX44: 1 | CY44: 2 | CZ44: 6 | DB44: 5 | DC44: 08902 | DD44: On Question 4, I wasn't sure if you were asking if we are aware of the flood zone status, or if we were or weren't in a flood zone. | DE44: 6770b51ac79cec8770eb7db3 | DF44: 0
A45: 45718.458 | B45: 45718.465 | C45: 0 | D45: 98.3.77.176 | E45: 100 | F45: 619 | G45: 1 | H45: 45718.465 | I45: R_7KwGcEqZvTFB9o8 | N45: 43.0151 | O45: -75.0354 | P45: anonymous | Q45: EN | R45: 1 | S45: 64a0240af7461068d2e1e1c0 | T45: 2 | U45: 1 | W45: 3 | Y45: 1 | Z45: 2 | AA45: 1 | AB45: 2 | AC45: 2 | AD45: 3 | AE45: 1 | AF45: 2 | AG45: 2 | AH45: 1 | AI45: 2 | AJ45: 1 | AS45: 5 | AT45: 5 | AU45: 5 | AV45: 5 | AW45: 5 | AX45: 4 | AY45: 5 | AZ45: 5 | BA45: 5 | BB45: 5 | BC45: 5 | BD45: 5 | BE45: 5 | BF45: 5 | BG45: 4 | BH45: 2 | BI45: 1 | BJ45: 4 | BK45: 1 | BL45: 1 | BM45: 1 | BN45: 1 | BO45: 4 | BP45: 5 | BQ45: 5 | BR45: 3 | BS45: 3 | BT45: 2 | BU45: 2 | BV45: 4 | BW45: 4 | BX45: 4 | BY45: 5 | BZ45: 3 | CA45: 5 | CB45: 3 | CC45: 3 | CD45: 4 | CE45: 4 | CF45: 2 | CG45: 1 | CH45: 4 | CI45: 2 | CJ45: 5 | CK45: 4 | CM45: 2 | CN45: 3 | CO45: 1 | CP45: 4 | CQ45: 1 | CS45: 6 | CT45: 3 | CU45: 4 | CV45: 2 | CX45: 1 | CY45: 2 | CZ45: 8 | DA45: public library | DB45: 8 | DC45: 13407 | DE45: 64a0240af7461068d2e1e1c0 | DF45: 0
A46: 45718.459 | B46: 45718.466 | C46: 0 | D46: 68.174.81.188 | E46: 100 | F46: 579 | G46: 1 | H46: 45718.466 | I46: R_6KQjQxtUwF0hvfr | N46: 40.6744 | O46: -73.8016 | P46: anonymous | Q46: EN | R46: 1 | S46: 6711e6eca31cad18eb52e462 | T46: 2 | U46: 2 | W46: 2 | Y46: 7 | Z46: 2 | AA46: 1 | AB46: 2 | AC46: 5 | AD46: 5 | AE46: 2 | AF46: 1 | AG46: 2 | AH46: 2 | AI46: 2 | AJ46: 1 | AS46: 3 | AT46: 4 | AU46: 4 | AV46: 3 | AW46: 4 | AX46: 3 | AY46: 4 | AZ46: 3 | BA46: 4 | BB46: 3 | BC46: 3 | BD46: 3 | BE46: 3 | BF46: 3 | BG46: 3 | BH46: 3 | BI46: 3 | BJ46: 4 | BK46: 3 | BL46: 3 | BM46: 3 | BN46: 4 | BO46: 3 | BP46: 3 | BQ46: 3 | BR46: 3 | BS46: 3 | BT46: 4 | BU46: 3 | BV46: 2 | BW46: 3 | BX46: 3 | BY46: 4 | BZ46: 3 | CA46: 3 | CB46: 3 | CC46: 4 | CD46: 3 | CE46: 4 | CF46: 3 | CG46: 1 | CH46: 4 | CI46: 1 | CJ46: 3 | CK46: 3 | CM46: 1 | CN46: 3 | CO46: 2 | CP46: 4 | CQ46: 2 | CS46: 1 | CT46: 2 | CU46: 5 | CV46: 2 | CX46: 1 | CY46: 1 | CZ46: 2 | DB46: 9 | DC46: 11101 | DD46: The survey was interesting, making me take new things into consideration. | DE46: 6711e6eca31cad18eb52e462 | DF46: 0
A47: 45718.461 | B47: 45718.466 | C47: 0 | D47: 208.83.170.144 | E47: 100 | F47: 441 | G47: 1 | H47: 45718.466 | I47: R_3yknFoIRXObPLvY | N47: 42.2781 | O47: -74.916 | P47: anonymous | Q47: EN | R47: 1 | S47: 6759d14e34269a7b10ee3f36 | T47: 2 | U47: 1 | W47: 3 | Y47: 3 | Z47: 1 | AA47: 1 | AB47: 2 | AC47: 3 | AD47: 5 | AE47: 3 | AF47: 2 | AG47: 2 | AH47: 1 | AI47: 1 | AJ47: 2 | AK47: 4 | AL47: 2 | AN47: 2 | AO47: 2 | AP47: 1 | AR47: 1 | AS47: 1 | AT47: 1 | AU47: 1 | AV47: 1 | AW47: 1 | AX47: 2 | AY47: 1 | AZ47: 1 | BA47: 1 | BB47: 1 | BC47: 1 | BD47: 1 | BE47: 1 | BF47: 1 | BG47: 1 | BH47: 2 | BI47: 2 | BJ47: 5 | BK47: 5 | BL47: 5 | BM47: 5 | BN47: 5 | BO47: 1 | BP47: 1 | BQ47: 3 | BR47: 1 | BS47: 3 | BT47: 5 | BU47: 4 | BV47: 2 | BW47: 3 | BX47: 1 | BY47: 4 | BZ47: 4 | CA47: 2 | CB47: 2 | CC47: 1 | CD47: 1 | CE47: 1 | CF47: 4 | CG47: 1 | CH47: 1 | CI47: 1 | CJ47: 1 | CK47: 4 | CM47: 1 | CN47: 2 | CO47: 3 | CP47: 4 | CQ47: 2 | CS47: 3 | CT47: 3 | CU47: 4 | CV47: 1 | CX47: 1 | CY47: 2 | CZ47: 7 | DB47: 9 | DC47: 13782 | DE47: 6759d14e34269a7b10ee3f36 | DF47: 0
A48: 45718.455 | B48: 45718.466 | C48: 0 | D48: 45.87.62.11 | E48: 100 | F48: 915 | G48: 1 | H48: 45718.466 | I48: R_1R3QkJCvGZ6fYBq | N48: 32.8137 | O48: -96.8704 | P48: anonymous | Q48: EN | R48: 1 | S48: 67bb624a611c6d05dcd26641 | T48: 2 | U48: 2 | W48: 3 | Y48: 5 | Z48: 1 | AA48: 1 | AB48: 2 | AC48: 5 | AD48: 3 | AE48: 1 | AF48: 2 | AG48: 1 | AH48: 2 | AI48: 2 | AJ48: 1 | AS48: 3 | AT48: 4 | AU48: 3 | AV48: 4 | AW48: 4 | AX48: 4 | AY48: 4 | AZ48: 3 | BA48: 3 | BB48: 4 | BC48: 3 | BD48: 4 | BE48: 3 | BF48: 4 | BG48: 4 | BH48: 4 | BI48: 4 | BJ48: 4 | BK48: 3 | BL48: 4 | BM48: 4 | BN48: 3 | BO48: 2 | BP48: 4 | BQ48: 3 | BR48: 3 | BS48: 3 | BT48: 4 | BU48: 4 | BV48: 4 | BW48: 3 | BX48: 3 | BY48: 4 | BZ48: 3 | CA48: 4 | CB48: 3 | CC48: 3 | CD48: 3 | CE48: 4 | CF48: 2 | CG48: 1 | CH48: 4 | CI48: 3 | CJ48: 4 | CK48: 1 | CM48: 2 | CN48: 1 | CO48: 3 | CP48: 4 | CQ48: 2 | CS48: 4 | CT48: 4 | CU48: 4 | CV48: 1 | CX48: 1 | CY48: 2 | CZ48: 1 | DB48: 10 | DC48: 11434 | DE48: 67bb624a611c6d05dcd26641 | DF48: 0
A49: 45718.462 | B49: 45718.466 | C49: 0 | D49: 73.175.241.177 | E49: 100 | F49: 347 | G49: 1 | H49: 45718.466 | I49: R_71AjcumaL3GBLpq | N49: 41.2382 | O49: -76.9978 | P49: anonymous | Q49: EN | R49: 1 | S49: 673ddcf4add9c2caab06882e | T49: 2 | U49: 1 | W49: 1 | Y49: 3 | Z49: 2 | AA49: 1 | AB49: 1 | AC49: 2 | AD49: 2 | AE49: 1 | AF49: 2 | AG49: 2 | AH49: 2 | AI49: 2 | AJ49: 1 | AS49: 3 | AT49: 3 | AU49: 3 | AV49: 3 | AW49: 3 | AX49: 3 | AY49: 3 | AZ49: 3 | BA49: 3 | BB49: 3 | BC49: 3 | BD49: 3 | BE49: 3 | BF49: 3 | BG49: 3 | BH49: 5 | BI49: 5 | BJ49: 3 | BK49: 3 | BL49: 3 | BM49: 3 | BN49: 3 | BO49: 5 | BP49: 4 | BQ49: 5 | BR49: 4 | BS49: 3 | BT49: 3 | BU49: 3 | BV49: 3 | BW49: 2 | BX49: 3 | BY49: 4 | BZ49: 2 | CA49: 3 | CB49: 4 | CC49: 2 | CD49: 3 | CE49: 4 | CF49: 3 | CG49: 2 | CL49: 5 | CQ49: 1 | CS49: 1 | CT49: 2 | CU49: 4 | CV49: 2 | CX49: 1 | CY49: 1 | CZ49: 6 | DB49: 3 | DC49: 14845 | DE49: 673ddcf4add9c2caab06882e | DF49: 0
A50: 45718.46 | B50: 45718.466 | C50: 0 | D50: 148.135.157.144 | E50: 100 | F50: 568 | G50: 1 | H50: 45718.466 | I50: R_7cYNsfpqsZVYuTQ | N50: 37.914 | O50: -122.0703 | P50: anonymous | Q50: EN | R50: 1 | S50: 67c359d897a9b2de6dcad244 | T50: 2 | U50: 1 | W50: 3 | Y50: 4 | Z50: 2 | AA50: 1 | AB50: 2 | AC50: 4 | AD50: 2 | AE50: 1 | AF50: 2 | AG50: 1 | AH50: 2 | AI50: 2 | AJ50: 1 | AS50: 4 | AT50: 4 | AU50: 5 | AV50: 3 | AW50: 4 | AX50: 4 | AY50: 4 | AZ50: 5 | BA50: 4 | BB50: 3 | BC50: 4 | BD50: 4 | BE50: 4 | BF50: 4 | BG50: 4 | BH50: 4 | BI50: 2 | BJ50: 4 | BK50: 5 | BL50: 4 | BM50: 3 | BN50: 4 | BO50: 3 | BP50: 4 | BQ50: 3 | BR50: 4 | BS50: 3 | BT50: 4 | BU50: 3 | BV50: 5 | BW50: 4 | BX50: 4 | BY50: 3 | BZ50: 4 | CA50: 3 | CB50: 4 | CC50: 3 | CD50: 4 | CE50: 1 | CF50: 4 | CG50: 2 | CH50: 4 | CI50: 1 | CJ50: 4 | CK50: 1 | CM50: 1 | CN50: 2 | CO50: 3 | CP50: 4 | CQ50: 1 | CS50: 3 | CT50: 3 | CU50: 4 | CV50: 2 | CX50: 1 | CY50: 1 | CZ50: 3 | DB50: 8 | DC50: 37024 | DD50: how can elevation of an house be done | DE50: 67c359d897a9b2de6dcad244 | DF50: 0
A51: 45718.464 | B51: 45718.467 | C51: 0 | D51: 98.116.80.174 | E51: 100 | F51: 190 | G51: 1 | H51: 45718.467 | I51: R_72yvvwvNdZ6Ie20 | N51: 40.7746 | O51: -73.4761 | P51: anonymous | Q51: EN | R51: 1 | S51: 67c04f7ebfc2ca8077973d7c | T51: 2 | U51: 3 | W51: 1 | Y51: 1 | Z51: 2 | AA51: 1 | AB51: 2 | AC51: 2 | AD51: 1 | AE51: 1 | AF51: 2 | AG51: 2 | AH51: 2 | AI51: 2 | AJ51: 1 | AS51: 3 | AT51: 3 | AU51: 4 | AV51: 4 | AW51: 4 | AX51: 4 | AY51: 3 | AZ51: 1 | BA51: 4 | BB51: 3 | BC51: 3 | BD51: 5 | BE51: 3 | BF51: 4 | BG51: 3 | BH51: 4 | BI51: 5 | BJ51: 5 | BK51: 2 | BL51: 2 | BM51: 3 | BN51: 3 | BO51: 3 | BP51: 4 | BQ51: 4 | BR51: 4 | BS51: 3 | BT51: 4 | BU51: 3 | BV51: 4 | BW51: 4 | BX51: 3 | BY51: 3 | BZ51: 4 | CA51: 3 | CB51: 5 | CC51: 5 | CD51: 2 | CE51: 2 | CF51: 4 | CG51: 1 | CL51: 3 | CQ51: 2 | CS51: 2 | CT51: 5 | CU51: 1 | CV51: 1 | CX51: 1 | CY51: 1 | CZ51: 3 | DB51: 10 | DC51: 11802 | DE51: 67c04f7ebfc2ca8077973d7c | DF51: 0
A52: 45718.457 | B52: 45718.467 | C52: 0 | D52: 69.119.116.28 | E52: 100 | F52: 799 | G52: 1 | H52: 45718.467 | I52: R_3UE8ZDOUdFaG74d | N52: 40.9238 | O52: -73.9989 | P52: anonymous | Q52: EN | R52: 1 | S52: 5fd9ad6dab00c64c8a45c9fc | T52: 1 | U52: 1 | W52: 2 | Y52: 1 | Z52: 2 | AA52: 1 | AB52: 2 | AC52: 3 | AD52: 4 | AE52: 1 | AF52: 2 | AG52: 1 | AH52: 2 | AI52: 1 | AJ52: 2 | AK52: 2 | AL52: 2 | AN52: 2 | AO52: 2 | AP52: 5 | AR52: 1 | AS52: 4 | AT52: 4 | AU52: 4 | AV52: 4 | AW52: 4 | AX52: 4 | AY52: 2 | AZ52: 2 | BA52: 3 | BB52: 2 | BC52: 3 | BD52: 1 | BE52: 2 | BF52: 2 | BG52: 1 | BH52: 2 | BI52: 2 | BJ52: 3 | BK52: 4 | BL52: 3 | BM52: 3 | BN52: 3 | BO52: 2 | BP52: 2 | BQ52: 2 | BR52: 2 | BS52: 3 | BT52: 2 | BU52: 2 | BV52: 3 | BW52: 2 | BX52: 1 | BY52: 3 | BZ52: 2 | CA52: 1 | CB52: 1 | CC52: 1 | CD52: 1 | CE52: 4 | CF52: 2 | CG52: 1 | CH52: 1 | CI52: 1 | CJ52: 1 | CK52: 4 | CM52: 2 | CN52: 4 | CO52: 3 | CP52: 1 | CQ52: 1 | CS52: 5 | CT52: 3 | CU52: 4 | CV52: 1 | CX52: 1 | CY52: 2 | CZ52: 8 | DA52: IT Analyst | DB52: 10 | DC52: 07621 | DE52: 5fd9ad6dab00c64c8a45c9fc | DF52: 0
A53: 45718.46 | B53: 45718.467 | C53: 0 | D53: 174.229.85.135 | E53: 100 | F53: 599 | G53: 1 | H53: 45718.467 | I53: R_5TsPg3L9uaapovn | N53: 40.7653 | O53: -73.9589 | P53: anonymous | Q53: EN | R53: 1 | S53: 632afc7f3b9d358de63670f1 | T53: 2 | U53: 1 | W53: 2 | Y53: 1 | Z53: 2 | AA53: 1 | AB53: 2 | AC53: 4 | AD53: 2 | AE53: 1 | AF53: 1 | AG53: 2 | AH53: 2 | AI53: 2 | AJ53: 1 | AS53: 4 | AT53: 5 | AU53: 5 | AV53: 4 | AW53: 4 | AX53: 4 | AY53: 3 | AZ53: 4 | BA53: 4 | BB53: 4 | BC53: 4 | BD53: 3 | BE53: 3 | BF53: 2 | BG53: 3 | BH53: 1 | BI53: 1 | BJ53: 2 | BK53: 4 | BL53: 3 | BM53: 4 | BN53: 2 | BO53: 5 | BP53: 4 | BQ53: 1 | BR53: 1 | BS53: 3 | BT53: 2 | BU53: 4 | BV53: 4 | BW53: 4 | BX53: 4 | BY53: 5 | BZ53: 4 | CA53: 3 | CB53: 4 | CC53: 4 | CD53: 4 | CE53: 4 | CF53: 4 | CG53: 1 | CH53: 5 | CI53: 2 | CJ53: 3 | CK53: 2 | CM53: 1 | CN53: 3 | CO53: 2 | CP53: 4 | CQ53: 2 | CS53: 2 | CT53: 4 | CU53: 4 | CV53: 1 | CX53: 1 | CY53: 2 | CZ53: 8 | DA53: Legal | DB53: 10 | DC53: 14223 | DE53: 632afc7f3b9d358de63670f1 | DF53: 0
A54: 45718.462 | B54: 45718.467 | C54: 0 | D54: 100.1.113.80 | E54: 100 | F54: 469 | G54: 1 | H54: 45718.467 | I54: R_7kM8zsViMOi9KrQ | N54: 40.8022 | O54: -74.1914 | P54: anonymous | Q54: EN | R54: 1 | S54: 5611f6dd7ffc8a00058117e7 | T54: 1 | U54: 2 | W54: 1 | Y54: 1 | Z54: 2 | AA54: 1 | AB54: 2 | AC54: 7 | AD54: 1 | AE54: 1 | AF54: 2 | AG54: 2 | AH54: 1 | AI54: 2 | AJ54: 1 | AS54: 4 | AT54: 4 | AU54: 4 | AV54: 4 | AW54: 3 | AX54: 3 | AY54: 4 | AZ54: 3 | BA54: 4 | BB54: 2 | BC54: 4 | BD54: 2 | BE54: 2 | BF54: 4 | BG54: 2 | BH54: 1 | BI54: 1 | BJ54: 1 | BK54: 4 | BL54: 4 | BM54: 5 | BN54: 3 | BO54: 1 | BP54: 1 | BQ54: 1 | BR54: 1 | BS54: 3 | BT54: 4 | BU54: 4 | BV54: 1 | BW54: 1 | BX54: 3 | BY54: 5 | BZ54: 1 | CA54: 2 | CB54: 1 | CC54: 1 | CD54: 1 | CE54: 4 | CF54: 4 | CG54: 1 | CL54: 4 | CQ54: 2 | CS54: 2 | CT54: 2 | CU54: 4 | CV54: 3 | CX54: 1 | CY54: 2 | CZ54: 1 | DB54: 5 | DC54: 07003 | DE54: 5611f6dd7ffc8a00058117e7 | DF54: 0
A55: 45718.464 | B55: 45718.468 | C55: 0 | D55: 71.187.179.111 | E55: 100 | F55: 300 | G55: 1 | H55: 45718.468 | I55: R_7GTAZAWHZ6aMuCp | N55: 40.8177 | O55: -73.9771 | P55: anonymous | Q55: EN | R55: 1 | S55: 6630e01b7d69d22b8be429a6 | T55: 1 | U55: 2 | W55: 1 | Y55: 5 | Z55: 2 | AA55: 1 | AB55: 2 | AC55: 2 | AD55: 2 | AE55: 1 | AF55: 2 | AG55: 2 | AH55: 2 | AI55: 2 | AJ55: 1 | AS55: 3 | AT55: 3 | AU55: 4 | AV55: 3 | AW55: 4 | AX55: 4 | AY55: 2 | AZ55: 4 | BA55: 4 | BB55: 4 | BC55: 4 | BD55: 1 | BE55: 3 | BF55: 5 | BG55: 4 | BH55: 2 | BI55: 2 | BJ55: 2 | BK55: 2 | BL55: 2 | BM55: 3 | BN55: 2 | BO55: 2 | BP55: 2 | BQ55: 3 | BR55: 2 | BS55: 3 | BT55: 2 | BU55: 3 | BV55: 2 | BW55: 2 | BX55: 2 | BY55: 3 | BZ55: 2 | CA55: 1 | CB55: 3 | CC55: 2 | CD55: 3 | CE55: 4 | CF55: 1 | CG55: 1 | CL55: 1 | CQ55: 2 | CS55: 1 | CT55: 3 | CU55: 1 | CV55: 1 | CX55: 1 | CY55: 2 | CZ55: 6 | DB55: 9 | DC55: 07650 | DE55: 6630e01b7d69d22b8be429a6 | DF55: 0
A56: 45718.464 | B56: 45718.468 | C56: 0 | D56: 97.216.84.131 | E56: 100 | F56: 315 | G56: 1 | H56: 45718.468 | I56: R_7eh5H0WOX5i8kIm | N56: 40.5885 | O56: -75.4642 | P56: anonymous | Q56: EN | R56: 1 | S56: 63ea4d3b920d683ac61a1ea0 | T56: 1 | U56: 1 | W56: 2 | Y56: 4 | Z56: 2 | AA56: 1 | AB56: 1 | AC56: 3 | AD56: 2 | AE56: 1 | AF56: 2 | AG56: 1 | AH56: 2 | AI56: 1 | AJ56: 2 | AK56: 2 | AL56: 1 | AM56: 2023 | AN56: 2 | AO56: 2 | AP56: 1 | AR56: 1 | AS56: 3 | AT56: 2 | AU56: 3 | AV56: 4 | AW56: 4 | AX56: 3 | AY56: 3 | AZ56: 3 | BA56: 4 | BB56: 4 | BC56: 4 | BD56: 3 | BE56: 4 | BF56: 5 | BG56: 4 | BH56: 4 | BI56: 4 | BJ56: 4 | BK56: 3 | BL56: 5 | BM56: 4 | BN56: 3 | BO56: 4 | BP56: 4 | BQ56: 4 | BR56: 4 | BS56: 3 | BT56: 4 | BU56: 4 | BV56: 3 | BW56: 3 | BX56: 2 | BY56: 4 | BZ56: 4 | CA56: 4 | CB56: 3 | CC56: 4 | CD56: 2 | CE56: 1 | CF56: 4 | CG56: 2 | CH56: 3 | CI56: 3 | CJ56: 3 | CK56: 3 | CM56: 2 | CN56: 1 | CO56: 3 | CP56: 4 | CQ56: 2 | CS56: 2 | CT56: 3 | CU56: 4 | CV56: 1 | CX56: 1 | CY56: 1 | CZ56: 8 | DA56: military | DB56: 10 | DC56: 08865 | DD56: great study | DE56: 63ea4d3b920d683ac61a1ea0 | DF56: 0
A57: 45718.464 | B57: 45718.469 | C57: 0 | D57: 68.83.24.200 | E57: 100 | F57: 463 | G57: 1 | H57: 45718.469 | I57: R_7SmwAhRFTw9mXTP | N57: 39.9203 | O57: -75.1108 | P57: anonymous | Q57: EN | R57: 1 | S57: 5efe6daf6a2551378201893e | T57: 1 | U57: 1 | W57: 1 | Y57: 1 | Z57: 1 | AA57: 1 | AB57: 1 | AC57: 1 | AD57: 2 | AE57: 1 | AF57: 2 | AG57: 2 | AH57: 2 | AI57: 2 | AJ57: 1 | AS57: 3 | AT57: 3 | AU57: 3 | AV57: 3 | AW57: 2 | AX57: 3 | AY57: 2 | AZ57: 2 | BA57: 3 | BB57: 2 | BC57: 2 | BD57: 2 | BE57: 3 | BF57: 2 | BG57: 3 | BH57: 1 | BI57: 1 | BJ57: 3 | BK57: 3 | BL57: 2 | BM57: 2 | BN57: 2 | BO57: 2 | BP57: 1 | BQ57: 1 | BR57: 1 | BS57: 3 | BT57: 2 | BU57: 2 | BV57: 3 | BW57: 3 | BX57: 1 | BY57: 4 | BZ57: 3 | CA57: 1 | CB57: 3 | CC57: 3 | CD57: 3 | CE57: 4 | CF57: 5 | CG57: 1 | CL57: 3 | CQ57: 2 | CS57: 4 | CT57: 2 | CU57: 4 | CV57: 5 | CW57: self employed | CX57: 1 | CY57: 2 | CZ57: 4 | DB57: 2 | DC57: 08083 | DD57: nothing | DE57: 5efe6daf6a2551378201893e | DF57: 0
A58: 45718.465 | B58: 45718.47 | C58: 0 | D58: 98.109.118.136 | E58: 100 | F58: 435 | G58: 1 | H58: 45718.47 | I58: R_7paR9iWtYc3uRoh | N58: 40.9238 | O58: -73.9989 | P58: anonymous | Q58: EN | R58: 1 | S58: 67857ecb1647649435b3898f | T58: 1 | U58: 1 | W58: 2 | Y58: 7 | Z58: 2 | AA58: 1 | AB58: 2 | AC58: 4 | AD58: 2 | AE58: 1 | AF58: 2 | AG58: 2 | AH58: 2 | AI58: 2 | AJ58: 1 | AS58: 4 | AT58: 4 | AU58: 4 | AV58: 4 | AW58: 4 | AX58: 3 | AY58: 3 | AZ58: 4 | BA58: 3 | BB58: 3 | BC58: 2 | BD58: 1 | BE58: 3 | BF58: 2 | BG58: 1 | BH58: 5 | BI58: 2 | BJ58: 2 | BK58: 1 | BL58: 1 | BM58: 1 | BN58: 1 | BO58: 4 | BP58: 4 | BQ58: 2 | BR58: 1 | BS58: 3 | BT58: 2 | BU58: 2 | BV58: 3 | BW58: 3 | BX58: 2 | BY58: 4 | BZ58: 3 | CA58: 1 | CB58: 3 | CC58: 2 | CD58: 1 | CE58: 4 | CF58: 4 | CG58: 1 | CH58: 3 | CI58: 1 | CJ58: 3 | CK58: 1 | CM58: 1 | CN58: 3 | CO58: 4 | CP58: 2 | CQ58: 2 | CS58: 1 | CT58: 2 | CU58: 1 | CV58: 3 | CX58: 1 | CY58: 2 | CZ58: 4 | DB58: 1 | DC58: 07628 | DE58: 67857ecb1647649435b3898f | DF58: 0
A59: 45718.466 | B59: 45718.47 | C59: 0 | D59: 50.49.30.32 | E59: 100 | F59: 312 | G59: 1 | H59: 45718.47 | I59: R_119RK7AOr45fyZH | N59: 42.87 | O59: -77.2791 | P59: anonymous | Q59: EN | R59: 1 | S59: 6572244f5a6d2b943074aa73 | T59: 2 | U59: 1 | W59: 3 | Y59: 1 | Z59: 2 | AA59: 1 | AB59: 2 | AC59: 1 | AD59: 4 | AE59: 1 | AF59: 2 | AG59: 2 | AH59: 1 | AI59: 2 | AJ59: 1 | AS59: 3 | AT59: 3 | AU59: 4 | AV59: 3 | AW59: 4 | AX59: 4 | AY59: 1 | AZ59: 2 | BA59: 3 | BB59: 1 | BC59: 2 | BD59: 1 | BE59: 2 | BF59: 1 | BG59: 1 | BH59: 2 | BI59: 2 | BJ59: 3 | BK59: 5 | BL59: 4 | BM59: 4 | BN59: 3 | BO59: 2 | BP59: 2 | BQ59: 3 | BR59: 3 | BS59: 3 | BT59: 4 | BU59: 3 | BV59: 4 | BW59: 3 | BX59: 3 | BY59: 4 | BZ59: 2 | CA59: 3 | CB59: 4 | CC59: 2 | CD59: 4 | CE59: 4 | CF59: 2 | CG59: 1 | CH59: 3 | CI59: 1 | CJ59: 4 | CK59: 4 | CM59: 4 | CN59: 3 | CO59: 2 | CP59: 1 | CQ59: 1 | CS59: 6 | CT59: 4 | CU59: 4 | CV59: 1 | CX59: 1 | CY59: 2 | CZ59: 8 | DA59: professional services | DB59: 6 | DC59: 14826 | DE59: 6572244f5a6d2b943074aa73 | DF59: 0
A60: 45718.464 | B60: 45718.47 | C60: 0 | D60: 69.114.77.207 | E60: 100 | F60: 507 | G60: 1 | H60: 45718.47 | I60: R_70Dv6nnGTTl4Dvi | N60: 40.7964 | O60: -74.0203 | P60: anonymous | Q60: EN | R60: 1 | S60: 646a74a7aadc8d532a2f34dd | T60: 1 | U60: 2 | W60: 1 | Y60: 1 | Z60: 2 | AA60: 2 | AB60: 2 | AC60: 2 | AD60: 1 | AE60: 1 | AF60: 2 | AG60: 2 | AH60: 2 | AI60: 2 | AJ60: 1 | AS60: 4 | AT60: 4 | AU60: 4 | AV60: 4 | AW60: 4 | AX60: 4 | AY60: 3 | AZ60: 4 | BA60: 4 | BB60: 3 | BC60: 2 | BD60: 4 | BE60: 4 | BF60: 5 | BG60: 4 | BH60: 3 | BI60: 2 | BJ60: 2 | BK60: 4 | BL60: 3 | BM60: 2 | BN60: 1 | BO60: 2 | BP60: 2 | BQ60: 2 | BR60: 1 | BS60: 3 | BT60: 2 | BU60: 3 | BV60: 2 | BW60: 3 | BX60: 2 | BY60: 4 | BZ60: 4 | CA60: 4 | CB60: 5 | CC60: 3 | CD60: 2 | CE60: 4 | CF60: 2 | CG60: 1 | CL60: 3 | CQ60: 1 | CS60: 3 | CT60: 3 | CU60: 4 | CV60: 2 | CX60: 1 | CY60: 2 | CZ60: 3 | DB60: 10 | DC60: 07086 | DE60: 646a74a7aadc8d532a2f34dd | DF60: 0
A61: 45718.459 | B61: 45718.47 | C61: 0 | D61: 47.230.173.19 | E61: 100 | F61: 967 | G61: 1 | H61: 45718.47 | I61: R_7LnF6xqRqIl0Gzs | N61: 40.6295 | O61: -74.0938 | P61: anonymous | Q61: EN | R61: 1 | S61: 66f091e2be9a6301cd4ec51c | T61: 2 | U61: 1 | W61: 2 | Y61: 5 | Z61: 2 | AA61: 1 | AB61: 2 | AC61: 4 | AD61: 3 | AE61: 1 | AF61: 2 | AG61: 1 | AH61: 2 | AI61: 2 | AJ61: 1 | AS61: 4 | AT61: 4 | AU61: 2 | AV61: 2 | AW61: 4 | AX61: 3 | AY61: 2 | AZ61: 4 | BA61: 4 | BB61: 5 | BC61: 4 | BD61: 2 | BE61: 5 | BF61: 4 | BG61: 4 | BH61: 2 | BI61: 1 | BJ61: 2 | BK61: 4 | BL61: 4 | BM61: 4 | BN61: 2 | BO61: 2 | BP61: 3 | BQ61: 2 | BR61: 1 | BS61: 3 | BT61: 3 | BU61: 2 | BV61: 2 | BW61: 1 | BX61: 3 | BY61: 4 | BZ61: 2 | CA61: 3 | CB61: 2 | CC61: 4 | CD61: 2 | CE61: 1 | CF61: 2 | CG61: 4 | CH61: 2 | CI61: 2 | CJ61: 2 | CK61: 2 | CM61: 3 | CN61: 1 | CO61: 2 | CP61: 4 | CQ61: 2 | CS61: 1 | CT61: 2 | CU61: 1 | CV61: 3 | CX61: 2 | CY61: 1 | CZ61: 8 | DA61: Student | DB61: 8 | DC61: 10306 | DE61: 66f091e2be9a6301cd4ec51c | DF61: 0
A62: 45718.456 | B62: 45718.47 | C62: 0 | D62: 194.26.21.198 | E62: 100 | F62: 1186 | G62: 1 | H62: 45718.47 | I62: R_3GwR34yk3XNGTfK | N62: 33.5407 | O62: -89.267 | P62: anonymous | Q62: EN | R62: 1 | S62: 673a4a4738521c3458ee43fb | T62: 1 | U62: 3 | W62: 2 | Y62: 5 | Z62: 2 | AA62: 1 | AB62: 2 | AC62: 4 | AD62: 3 | AE62: 1 | AF62: 1 | AG62: 1 | AH62: 2 | AI62: 2 | AJ62: 1 | AS62: 3 | AT62: 4 | AU62: 3 | AV62: 3 | AW62: 5 | AX62: 4 | AY62: 4 | AZ62: 4 | BA62: 4 | BB62: 4 | BC62: 5 | BD62: 5 | BE62: 3 | BF62: 4 | BG62: 1 | BH62: 5 | BI62: 3 | BJ62: 2 | BK62: 1 | BL62: 2 | BM62: 2 | BN62: 1 | BO62: 4 | BP62: 5 | BQ62: 5 | BR62: 5 | BS62: 3 | BT62: 1 | BU62: 1 | BV62: 5 | BW62: 5 | BX62: 4 | BY62: 5 | BZ62: 4 | CA62: 4 | CB62: 5 | CC62: 3 | CD62: 5 | CE62: 4 | CF62: 5 | CG62: 2 | CH62: 5 | CI62: 2 | CJ62: 5 | CK62: 2 | CM62: 2 | CN62: 3 | CO62: 1 | CP62: 4 | CQ62: 2 | CS62: 2 | CT62: 3 | CU62: 2 | CV62: 1 | CX62: 1 | CY62: 1 | CZ62: 1 | DB62: 7 | DC62: 07047 | DE62: 673a4a4738521c3458ee43fb | DF62: 0
A63: 45718.465 | B63: 45718.471 | C63: 0 | D63: 24.194.197.72 | E63: 100 | F63: 477 | G63: 1 | H63: 45718.471 | I63: R_61KT2KHNt1xlWMI | N63: 42.6466 | O63: -73.7462 | P63: anonymous | Q63: EN | R63: 1 | S63: 663275876de1bd5e86d04517 | T63: 2 | U63: 1 | W63: 2 | Y63: 2 | Z63: 1 | AA63: 1 | AB63: 2 | AC63: 2 | AD63: 4 | AE63: 1 | AF63: 2 | AG63: 2 | AH63: 2 | AI63: 2 | AJ63: 1 | AS63: 3 | AT63: 3 | AU63: 4 | AV63: 3 | AW63: 2 | AX63: 2 | AY63: 2 | AZ63: 2 | BA63: 2 | BB63: 2 | BC63: 2 | BD63: 1 | BE63: 2 | BF63: 1 | BG63: 2 | BH63: 2 | BI63: 2 | BJ63: 1 | BK63: 2 | BL63: 2 | BM63: 1 | BN63: 1 | BO63: 1 | BP63: 1 | BQ63: 3 | BR63: 1 | BS63: 3 | BT63: 1 | BU63: 2 | BV63: 4 | BW63: 3 | BX63: 2 | BY63: 5 | BZ63: 4 | CA63: 4 | CB63: 4 | CC63: 1 | CD63: 2 | CE63: 1 | CF63: 4 | CG63: 1 | CH63: 2 | CI63: 2 | CJ63: 3 | CK63: 3 | CM63: 1 | CN63: 3 | CO63: 2 | CP63: 4 | CQ63: 2 | CS63: 3 | CT63: 3 | CU63: 4 | CV63: 1 | CX63: 1 | CY63: 1 | CZ63: 4 | DB63: 10 | DC63: 12018 | DE63: 663275876de1bd5e86d04517 | DF63: 0
A64: 45718.468 | B64: 45718.471 | C64: 0 | D64: 73.178.38.80 | E64: 100 | F64: 259 | G64: 1 | H64: 45718.471 | I64: R_7sYzMugv83yWcAV | N64: 40.5163 | O64: -74.2696 | P64: anonymous | Q64: EN | R64: 1 | S64: 671b2b60d78afebe3b78319a | T64: 1 | U64: 1 | W64: 2 | Y64: 1 | Z64: 1 | AA64: 1 | AB64: 2 | AC64: 2 | AD64: 1 | AE64: 1 | AF64: 2 | AG64: 2 | AH64: 2 | AI64: 2 | AJ64: 1 | AS64: 4 | AT64: 4 | AU64: 4 | AV64: 4 | AW64: 4 | AX64: 3 | AY64: 4 | AZ64: 4 | BA64: 4 | BB64: 4 | BC64: 4 | BD64: 4 | BE64: 5 | BF64: 4 | BG64: 4 | BH64: 4 | BI64: 2 | BJ64: 4 | BK64: 4 | BL64: 2 | BM64: 4 | BN64: 4 | BO64: 5 | BP64: 4 | BQ64: 4 | BR64: 2 | BS64: 3 | BT64: 3 | BU64: 4 | BV64: 2 | BW64: 4 | BX64: 2 | BY64: 4 | BZ64: 2 | CA64: 4 | CB64: 4 | CC64: 2 | CD64: 2 | CE64: 4 | CF64: 2 | CG64: 1 | CH64: 2 | CI64: 1 | CJ64: 2 | CK64: 1 | CM64: 2 | CN64: 4 | CO64: 3 | CP64: 1 | CQ64: 2 | CS64: 1 | CT64: 4 | CU64: 4 | CV64: 1 | CX64: 1 | CY64: 1 | CZ64: 1 | DB64: 10 | DC64: 08853 | DE64: 671b2b60d78afebe3b78319a | DF64: 0
A65: 45718.467 | B65: 45718.471 | C65: 0 | D65: 74.89.222.95 | E65: 100 | F65: 360 | G65: 1 | H65: 45718.471 | I65: R_7qy9phMxo5RCaOt | N65: 40.8931 | O65: -74.5818 | P65: anonymous | Q65: EN | R65: 1 | S65: 6792fd93cb6de36b6c49021d | T65: 1 | U65: 2 | W65: 1 | Y65: 1 | Z65: 2 | AA65: 1 | AB65: 2 | AC65: 4 | AD65: 2 | AE65: 1 | AF65: 1 | AG65: 1 | AH65: 2 | AI65: 2 | AJ65: 1 | AS65: 5 | AT65: 4 | AU65: 4 | AV65: 5 | AW65: 4 | AX65: 4 | AY65: 4 | AZ65: 4 | BA65: 3 | BB65: 3 | BC65: 4 | BD65: 3 | BE65: 4 | BF65: 4 | BG65: 3 | BH65: 3 | BI65: 2 | BJ65: 2 | BK65: 2 | BL65: 2 | BM65: 2 | BN65: 2 | BO65: 4 | BP65: 4 | BQ65: 3 | BR65: 2 | BS65: 3 | BT65: 2 | BU65: 2 | BV65: 4 | BW65: 2 | BX65: 4 | BY65: 5 | BZ65: 5 | CA65: 4 | CB65: 2 | CC65: 2 | CD65: 4 | CE65: 4 | CF65: 4 | CG65: 1 | CL65: 4 | CQ65: 1 | CS65: 2 | CT65: 3 | CU65: 3 | CV65: 1 | CX65: 1 | CY65: 1 | CZ65: 3 | DB65: 10 | DC65: 07885 | DE65: 6792fd93cb6de36b6c49021d | DF65: 0
A66: 45718.461 | B66: 45718.471 | C66: 0 | D66: 73.194.213.5 | E66: 100 | F66: 861 | G66: 1 | H66: 45718.471 | I66: R_6y2YQaOiTYokH48 | N66: 39.6999 | O66: -74.2633 | P66: anonymous | Q66: EN | R66: 1 | S66: 66b410222681531f50b06b85 | T66: 1 | U66: 1 | W66: 1 | Y66: 5 | Z66: 2 | AA66: 1 | AB66: 2 | AC66: 1 | AD66: 3 | AE66: 2 | AF66: 2 | AG66: 2 | AH66: 2 | AI66: 2 | AJ66: 1 | AS66: 4 | AT66: 3 | AU66: 4 | AV66: 3 | AW66: 4 | AX66: 4 | AY66: 2 | AZ66: 2 | BA66: 3 | BB66: 1 | BC66: 3 | BD66: 1 | BE66: 2 | BF66: 2 | BG66: 1 | BH66: 2 | BI66: 2 | BJ66: 2 | BK66: 3 | BL66: 4 | BM66: 3 | BN66: 3 | BO66: 2 | BP66: 4 | BQ66: 3 | BR66: 1 | BS66: 3 | BT66: 3 | BU66: 2 | BV66: 3 | BW66: 2 | BX66: 2 | BY66: 4 | BZ66: 3 | CA66: 1 | CB66: 5 | CC66: 3 | CD66: 2 | CE66: 1 | CF66: 2 | CG66: 1 | CL66: 2 | CQ66: 2 | CS66: 2 | CT66: 3 | CU66: 4 | CV66: 1 | CX66: 1 | CY66: 1 | CZ66: 2 | DB66: 7 | DC66: 08005 | DD66: Insurance isn’t designed to help people, it’s designed to provide a 0 sense of security, while the insurance company gambles that you will continue paying and never need their assistance. But when you do need the assistance of your insurance, they use every loophole in the book to withhold payments, deny payments, or minimize payments. | DE66: 66b410222681531f50b06b85 | DF66: 0
A67: 45718.458 | B67: 45718.472 | C67: 0 | D67: 68.84.232.52 | E67: 100 | F67: 1213 | G67: 1 | H67: 45718.472 | I67: R_6JUNROgUfrlTSnL | N67: 39.4826 | O67: -75.0027 | P67: anonymous | Q67: EN | R67: 1 | S67: 6633a0c9953e744f48788d5e | T67: 1 | U67: 1 | W67: 2 | Y67: 1 | Z67: 2 | AA67: 1 | AB67: 2 | AC67: 1 | AD67: 4 | AE67: 1 | AF67: 2 | AG67: 2 | AH67: 2 | AI67: 1 | AJ67: 2 | AK67: 3 | AL67: 2 | AN67: 3 | AO67: 2 | AP67: 5 | AR67: 1 | AS67: 4 | AT67: 4 | AU67: 4 | AV67: 4 | AW67: 3 | AX67: 4 | AY67: 4 | AZ67: 4 | BA67: 4 | BB67: 4 | BC67: 4 | BD67: 4 | BE67: 4 | BF67: 2 | BG67: 2 | BH67: 2 | BI67: 2 | BJ67: 2 | BK67: 2 | BL67: 4 | BM67: 4 | BN67: 4 | BO67: 2 | BP67: 2 | BQ67: 4 | BR67: 2 | BS67: 3 | BT67: 4 | BU67: 4 | BV67: 3 | BW67: 3 | BX67: 4 | BY67: 4 | BZ67: 4 | CA67: 4 | CB67: 3 | CC67: 3 | CD67: 3 | CE67: 1 | CF67: 2 | CG67: 1 | CH67: 2 | CI67: 1 | CJ67: 2 | CK67: 5 | CM67: 1 | CN67: 2 | CO67: 3 | CP67: 4 | CQ67: 1 | CS67: 4 | CT67: 3 | CU67: 4 | CV67: 1 | CX67: 1 | CY67: 2 | CZ67: 3 | DB67: 10 | DC67: 08310 | DE67: 6633a0c9953e744f48788d5e | DF67: 0
A68: 45718.457 | B68: 45718.472 | C68: 0 | D68: 172.59.208.188 | E68: 100 | F68: 1297 | G68: 1 | H68: 45718.472 | I68: R_7bKtiQ9BeayJDAx | N68: 40.7463 | O68: -74.1553 | P68: anonymous | Q68: EN | R68: 1 | S68: 67bcc6febed588e0aba55153 | T68: 1 | U68: 1 | W68: 3 | Y68: 7 | Z68: 1 | AA68: 1 | AB68: 1 | AC68: 4 | AD68: 3 | AE68: 1 | AF68: 2 | AG68: 1 | AH68: 2 | AI68: 1 | AJ68: 2 | AK68: 2 | AL68: 2 | AN68: 2 | AO68: 1 | AP68: 3 | AR68: 3 | AS68: 5 | AT68: 4 | AU68: 4 | AV68: 5 | AW68: 4 | AX68: 5 | AY68: 5 | AZ68: 4 | BA68: 5 | BB68: 5 | BC68: 3 | BD68: 4 | BE68: 4 | BF68: 5 | BG68: 5 | BH68: 5 | BI68: 4 | BJ68: 5 | BK68: 5 | BL68: 4 | BM68: 4 | BN68: 5 | BO68: 4 | BP68: 5 | BQ68: 4 | BR68: 5 | BS68: 3 | BT68: 4 | BU68: 4 | BV68: 4 | BW68: 3 | BX68: 4 | BY68: 5 | BZ68: 4 | CA68: 4 | CB68: 5 | CC68: 3 | CD68: 4 | CE68: 3 | CF68: 2 | CG68: 2 | CH68: 4 | CI68: 3 | CJ68: 3 | CK68: 4 | CM68: 3 | CN68: 1 | CO68: 2 | CP68: 4 | CQ68: 1 | CS68: 2 | CT68: 4 | CU68: 4 | CV68: 1 | CX68: 1 | CY68: 2 | CZ68: 2 | DB68: 10 | DC68: 08816 | DE68: 67bcc6febed588e0aba55153 | DF68: 0
A69: 45718.457 | B69: 45718.473 | C69: 0 | D69: 100.35.237.154 | E69: 100 | F69: 1354 | G69: 1 | H69: 45718.473 | I69: R_31tNYRY4akIv17k | N69: 40.7053 | O69: -74.0866 | P69: anonymous | Q69: EN | R69: 1 | S69: 63d69e4d6648b39324fdf0ad | T69: 1 | U69: 3 | W69: 1 | Y69: 6 | Z69: 2 | AA69: 1 | AB69: 2 | AC69: 1 | AD69: 2 | AE69: 1 | AF69: 2 | AG69: 2 | AH69: 2 | AI69: 2 | AJ69: 1 | AS69: 4 | AT69: 4 | AU69: 4 | AV69: 3 | AW69: 4 | AX69: 4 | AY69: 3 | AZ69: 4 | BA69: 4 | BB69: 3 | BC69: 3 | BD69: 5 | BE69: 5 | BF69: 3 | BG69: 3 | BH69: 1 | BI69: 1 | BJ69: 3 | BK69: 5 | BL69: 5 | BM69: 4 | BN69: 3 | BO69: 1 | BP69: 1 | BQ69: 1 | BR69: 1 | BS69: 3 | BT69: 4 | BU69: 4 | BV69: 3 | BW69: 3 | BX69: 4 | BY69: 5 | BZ69: 4 | CA69: 3 | CB69: 4 | CC69: 2 | CD69: 3 | CE69: 4 | CF69: 2 | CG69: 1 | CL69: 3 | CQ69: 2 | CS69: 2 | CT69: 3 | CU69: 1 | CV69: 1 | CX69: 1 | CY69: 1 | CZ69: 4 | DB69: 10 | DC69: 07304 | DE69: 63d69e4d6648b39324fdf0ad | DF69: 0
A70: 45718.461 | B70: 45718.473 | C70: 0 | D70: 8.41.195.33 | E70: 100 | F70: 1058 | G70: 1 | H70: 45718.473 | I70: R_7nSfTJE8e5ekqyg | N70: 40.1791 | O70: -75.2546 | P70: anonymous | Q70: EN | R70: 1 | S70: 6760e1f18f719b6fea6bca0c | T70: 1 | U70: 1 | W70: 2 | Y70: 4 | Z70: 2 | AA70: 1 | AB70: 2 | AC70: 5 | AD70: 5 | AE70: 1 | AF70: 2 | AG70: 1 | AH70: 2 | AI70: 1 | AJ70: 2 | AK70: 4 | AL70: 2 | AN70: 3 | AO70: 2 | AP70: 5 | AR70: 1 | AS70: 4 | AT70: 4 | AU70: 4 | AV70: 4 | AW70: 3 | AX70: 4 | AY70: 3 | AZ70: 4 | BA70: 4 | BB70: 4 | BC70: 3 | BD70: 4 | BE70: 4 | BF70: 4 | BG70: 4 | BH70: 3 | BI70: 2 | BJ70: 4 | BK70: 4 | BL70: 4 | BM70: 3 | BN70: 3 | BO70: 2 | BP70: 2 | BQ70: 2 | BR70: 2 | BS70: 3 | BT70: 4 | BU70: 3 | BV70: 2 | BW70: 3 | BX70: 4 | BY70: 4 | BZ70: 4 | CA70: 3 | CB70: 4 | CC70: 3 | CD70: 4 | CE70: 4 | CF70: 4 | CG70: 2 | CH70: 2 | CI70: 1 | CJ70: 2 | CK70: 5 | CM70: 1 | CN70: 3 | CO70: 4 | CP70: 2 | CQ70: 1 | CS70: 1 | CT70: 2 | CU70: 4 | CV70: 5 | CW70: student | CX70: 1 | CY70: 1 | CZ70: 8 | DB70: 10 | DC70: 08822 | DE70: 6760e1f18f719b6fea6bca0c | DF70: 0
A71: 45718.468 | B71: 45718.473 | C71: 0 | D71: 69.248.110.90 | E71: 100 | F71: 398 | G71: 1 | H71: 45718.473 | I71: R_3S2DPieCWHS2lJG | N71: 39.8066 | O71: -74.5282 | P71: anonymous | Q71: EN | R71: 1 | S71: 651c1abbc73b6eea8fa97193 | T71: 1 | U71: 1 | W71: 2 | Y71: 2 | Z71: 2 | AA71: 1 | AB71: 2 | AC71: 2 | AD71: 4 | AE71: 1 | AF71: 2 | AG71: 2 | AH71: 1 | AI71: 2 | AJ71: 1 | AS71: 4 | AT71: 4 | AU71: 4 | AV71: 4 | AW71: 5 | AX71: 5 | AY71: 3 | AZ71: 5 | BA71: 5 | BB71: 4 | BC71: 4 | BD71: 1 | BE71: 4 | BF71: 2 | BG71: 1 | BH71: 2 | BI71: 2 | BJ71: 3 | BK71: 4 | BL71: 4 | BM71: 3 | BN71: 2 | BO71: 2 | BP71: 4 | BQ71: 2 | BR71: 2 | BS71: 3 | BT71: 3 | BU71: 3 | BV71: 3 | BW71: 3 | BX71: 2 | BY71: 4 | BZ71: 2 | CA71: 3 | CB71: 2 | CC71: 2 | CD71: 2 | CE71: 4 | CF71: 3 | CG71: 1 | CH71: 2 | CI71: 1 | CJ71: 4 | CK71: 4 | CM71: 1 | CN71: 4 | CO71: 2 | CP71: 3 | CQ71: 1 | CS71: 6 | CT71: 2 | CU71: 4 | CV71: 4 | CX71: 1 | CY71: 2 | CZ71: 8 | DA71: retired | DB71: 5 | DC71: 08088 | DE71: 651c1abbc73b6eea8fa97193 | DF71: 0
A72: 45718.467 | B72: 45718.473 | C72: 0 | D72: 172.59.210.114 | E72: 100 | F72: 538 | G72: 1 | H72: 45718.473 | I72: R_7wLx6qtbNJ869KR | N72: 40.7463 | O72: -74.1553 | P72: anonymous | Q72: EN | R72: 1 | S72: 66e32aaad05615cfd9fcbe48 | T72: 1 | U72: 1 | W72: 2 | Y72: 4 | Z72: 2 | AA72: 1 | AB72: 2 | AC72: 2 | AD72: 5 | AE72: 1 | AF72: 2 | AG72: 2 | AH72: 1 | AI72: 2 | AJ72: 1 | AS72: 3 | AT72: 4 | AU72: 4 | AV72: 3 | AW72: 4 | AX72: 5 | AY72: 4 | AZ72: 4 | BA72: 5 | BB72: 4 | BC72: 4 | BD72: 2 | BE72: 4 | BF72: 2 | BG72: 1 | BH72: 4 | BI72: 2 | BJ72: 2 | BK72: 2 | BL72: 4 | BM72: 2 | BN72: 2 | BO72: 1 | BP72: 2 | BQ72: 4 | BR72: 2 | BS72: 3 | BT72: 2 | BU72: 2 | BV72: 4 | BW72: 2 | BX72: 4 | BY72: 5 | BZ72: 4 | CA72: 4 | CB72: 2 | CC72: 1 | CD72: 3 | CE72: 1 | CF72: 4 | CG72: 1 | CH72: 2 | CI72: 1 | CJ72: 4 | CK72: 4 | CM72: 1 | CN72: 4 | CO72: 2 | CP72: 3 | CQ72: 2 | CS72: 4 | CT72: 3 | CU72: 4 | CV72: 1 | CX72: 1 | CY72: 1 | CZ72: 4 | DB72: 5 | DC72: 08005 | DD72: no problems | DE72: 66e32aaad05615cfd9fcbe48 | DF72: 0
A73: 45718.47 | B73: 45718.474 | C73: 0 | D73: 24.59.214.69 | E73: 100 | F73: 282 | G73: 1 | H73: 45718.474 | I73: R_1yntdojz8g7a9IB | N73: 43.0825 | O73: -75.6473 | P73: anonymous | Q73: EN | R73: 1 | S73: 66697feac4c3bc98619563af | T73: 2 | U73: 1 | W73: 3 | Y73: 4 | Z73: 2 | AA73: 1 | AB73: 1 | AC73: 1 | AD73: 3 | AE73: 1 | AF73: 2 | AG73: 2 | AH73: 2 | AI73: 2 | AJ73: 1 | AS73: 3 | AT73: 4 | AU73: 4 | AV73: 3 | AW73: 3 | AX73: 2 | AY73: 2 | AZ73: 2 | BA73: 2 | BB73: 2 | BC73: 2 | BD73: 1 | BE73: 2 | BF73: 2 | BG73: 2 | BH73: 2 | BI73: 3 | BJ73: 1 | BK73: 2 | BL73: 2 | BM73: 2 | BN73: 2 | BO73: 2 | BP73: 2 | BQ73: 2 | BR73: 2 | BS73: 3 | BT73: 2 | BU73: 2 | BV73: 3 | BW73: 3 | BX73: 3 | BY73: 3 | BZ73: 3 | CA73: 3 | CB73: 3 | CC73: 3 | CD73: 1 | CE73: 4 | CF73: 3 | CG73: 1 | CH73: 1 | CI73: 1 | CJ73: 1 | CK73: 4 | CM73: 2 | CN73: 4 | CO73: 3 | CP73: 1 | CQ73: 2 | CS73: 2 | CT73: 3 | CU73: 5 | CV73: 1 | CX73: 1 | CY73: 2 | CZ73: 8 | DA73: Information Technology | DB73: 7 | DC73: 13477 | DE73: 66697feac4c3bc98619563af | DF73: 0
A74: 45718.47 | B74: 45718.474 | C74: 0 | D74: 67.80.22.36 | E74: 100 | F74: 364 | G74: 1 | H74: 45718.474 | I74: R_3d0w8LwkJu8QuAQ | N74: 40.0923 | O74: -74.2252 | P74: anonymous | Q74: EN | R74: 1 | S74: 65f0e3c717f275b543199dbc | T74: 1 | U74: 1 | W74: 2 | Y74: 6 | Z74: 1 | AA74: 1 | AB74: 1 | AC74: 4 | AD74: 4 | AE74: 1 | AF74: 2 | AG74: 1 | AH74: 2 | AI74: 1 | AJ74: 2 | AK74: 2 | AL74: 1 | AM74: 2022 | AN74: 2 | AO74: 2 | AP74: 5 | AR74: 1 | AS74: 4 | AT74: 4 | AU74: 4 | AV74: 4 | AW74: 4 | AX74: 4 | AY74: 4 | AZ74: 4 | BA74: 4 | BB74: 4 | BC74: 3 | BD74: 4 | BE74: 4 | BF74: 5 | BG74: 4 | BH74: 2 | BI74: 2 | BJ74: 2 | BK74: 3 | BL74: 3 | BM74: 3 | BN74: 3 | BO74: 2 | BP74: 2 | BQ74: 2 | BR74: 2 | BS74: 3 | BT74: 3 | BU74: 3 | BV74: 2 | BW74: 2 | BX74: 2 | BY74: 2 | BZ74: 2 | CA74: 2 | CB74: 2 | CC74: 2 | CD74: 2 | CE74: 1 | CF74: 3 | CG74: 1 | CH74: 3 | CI74: 1 | CJ74: 3 | CK74: 4 | CM74: 2 | CN74: 3 | CO74: 4 | CP74: 1 | CQ74: 1 | CS74: 1 | CT74: 2 | CU74: 4 | CV74: 1 | CX74: 1 | CY74: 1 | CZ74: 4 | DB74: 6 | DC74: 08701 | DD74: Thank you! | DE74: 65f0e3c717f275b543199dbc | DF74: 0
A75: 45718.47 | B75: 45718.474 | C75: 0 | D75: 69.126.69.103 | E75: 100 | F75: 391 | G75: 1 | H75: 45718.474 | I75: R_7KMzr0E58sfq41Z | N75: 40.6844 | O75: -73.4814 | P75: anonymous | Q75: EN | R75: 1 | S75: 5f0b7f45bd7f5a0e21a8b561 | T75: 2 | U75: 1 | W75: 2 | Y75: 2 | Z75: 2 | AA75: 1 | AB75: 2 | AC75: 6 | AD75: 4 | AE75: 1 | AF75: 1 | AG75: 1 | AH75: 2 | AI75: 2 | AJ75: 1 | AS75: 4 | AT75: 4 | AU75: 4 | AV75: 3 | AW75: 2 | AX75: 4 | AY75: 4 | AZ75: 4 | BA75: 4 | BB75: 2 | BC75: 2 | BD75: 2 | BE75: 3 | BF75: 2 | BG75: 2 | BH75: 3 | BI75: 3 | BJ75: 4 | BK75: 4 | BL75: 3 | BM75: 4 | BN75: 4 | BO75: 2 | BP75: 2 | BQ75: 2 | BR75: 2 | BS75: 3 | BT75: 4 | BU75: 4 | BV75: 3 | BW75: 3 | BX75: 2 | BY75: 4 | BZ75: 3 | CA75: 3 | CB75: 4 | CC75: 3 | CD75: 3 | CE75: 4 | CF75: 2 | CG75: 1 | CH75: 1 | CI75: 1 | CJ75: 1 | CK75: 5 | CM75: 3 | CN75: 4 | CO75: 2 | CP75: 1 | CQ75: 1 | CS75: 2 | CT75: 3 | CU75: 4 | CV75: 2 | CX75: 1 | CY75: 1 | CZ75: 4 | DB75: 10 | DC75: 11758 | DD75: nothing more to add | DE75: 5f0b7f45bd7f5a0e21a8b561 | DF75: 0
A76: 45718.471 | B76: 45718.474 | C76: 0 | D76: 38.27.143.253 | E76: 100 | F76: 278 | G76: 1 | H76: 45718.474 | I76: R_7dzsopgEr8fyP3i | N76: 42.3414 | O76: -77.3049 | P76: anonymous | Q76: EN | R76: 1 | S76: 63b35e76636a57e9ca3ee861 | T76: 2 | U76: 1 | W76: 2 | Y76: 1 | Z76: 1 | AA76: 1 | AB76: 2 | AC76: 1 | AD76: 3 | AE76: 1 | AF76: 2 | AG76: 2 | AH76: 2 | AI76: 2 | AJ76: 1 | AS76: 2 | AT76: 3 | AU76: 3 | AV76: 3 | AW76: 3 | AX76: 2 | AY76: 3 | AZ76: 2 | BA76: 2 | BB76: 2 | BC76: 4 | BD76: 3 | BE76: 1 | BF76: 1 | BG76: 1 | BH76: 2 | BI76: 2 | BJ76: 1 | BK76: 2 | BL76: 4 | BM76: 2 | BN76: 3 | BO76: 4 | BP76: 4 | BQ76: 4 | BR76: 4 | BS76: 3 | BT76: 2 | BU76: 2 | BV76: 3 | BW76: 2 | BX76: 2 | BY76: 4 | BZ76: 2 | CA76: 2 | CB76: 3 | CC76: 3 | CD76: 2 | CE76: 4 | CF76: 3 | CG76: 2 | CH76: 2 | CI76: 2 | CJ76: 3 | CK76: 1 | CM76: 1 | CN76: 3 | CO76: 2 | CP76: 4 | CQ76: 1 | CS76: 4 | CT76: 2 | CU76: 4 | CV76: 1 | CX76: 1 | CY76: 2 | CZ76: 3 | DB76: 7 | DC76: 14810 | DE76: 63b35e76636a57e9ca3ee861 | DF76: 0
A77: 45718.467 | B77: 45718.475 | C77: 0 | D77: 72.79.29.78 | E77: 100 | F77: 653 | G77: 1 | H77: 45718.475 | I77: R_3jjlN9yi17IaWQp | N77: 40.8185 | O77: -74.1589 | P77: anonymous | Q77: EN | R77: 1 | S77: 6554f7a941230b673902f7aa | T77: 1 | U77: 1 | W77: 1 | Y77: 1 | Z77: 2 | AA77: 1 | AB77: 1 | AC77: 5 | AD77: 3 | AE77: 1 | AF77: 2 | AG77: 1 | AH77: 1 | AI77: 1 | AJ77: 2 | AK77: 1 | AL77: 1 | AM77: 2024 | AN77: 3 | AO77: 2 | AP77: 5 | AR77: 1 | AS77: 4 | AT77: 4 | AU77: 4 | AV77: 4 | AW77: 3 | AX77: 3 | AY77: 2 | AZ77: 3 | BA77: 3 | BB77: 3 | BC77: 3 | BD77: 3 | BE77: 4 | BF77: 3 | BG77: 2 | BH77: 4 | BI77: 4 | BJ77: 2 | BK77: 4 | BL77: 3 | BM77: 4 | BN77: 4 | BO77: 2 | BP77: 2 | BQ77: 3 | BR77: 3 | BS77: 3 | BT77: 4 | BU77: 4 | BV77: 1 | BW77: 1 | BX77: 1 | BY77: 4 | BZ77: 2 | CA77: 2 | CB77: 3 | CC77: 1 | CD77: 2 | CE77: 4 | CF77: 1 | CG77: 1 | CL77: 1 | CQ77: 2 | CS77: 2 | CT77: 2 | CU77: 5 | CV77: 1 | CX77: 1 | CY77: 1 | CZ77: 1 | DB77: 10 | DC77: 07110 | DE77: 6554f7a941230b673902f7aa | DF77: 0
A78: 45718.471 | B78: 45718.475 | C78: 0 | D78: 67.247.229.17 | E78: 100 | F78: 308 | G78: 1 | H78: 45718.475 | I78: R_7nx7GlJWtSaWZ4t | N78: 42.986 | O78: -77.4139 | P78: anonymous | Q78: EN | R78: 1 | S78: 663ff63648ca32afb9acc9de | T78: 2 | U78: 1 | W78: 1 | Y78: 4 | Z78: 2 | AA78: 1 | AB78: 2 | AC78: 3 | AD78: 2 | AE78: 1 | AF78: 2 | AG78: 1 | AH78: 2 | AI78: 2 | AJ78: 1 | AS78: 5 | AT78: 3 | AU78: 4 | AV78: 4 | AW78: 3 | AX78: 4 | AY78: 3 | AZ78: 3 | BA78: 4 | BB78: 3 | BC78: 2 | BD78: 2 | BE78: 4 | BF78: 4 | BG78: 2 | BH78: 4 | BI78: 2 | BJ78: 2 | BK78: 3 | BL78: 4 | BM78: 3 | BN78: 3 | BO78: 4 | BP78: 2 | BQ78: 4 | BR78: 1 | BS78: 3 | BT78: 2 | BU78: 3 | BV78: 4 | BW78: 2 | BX78: 3 | BY78: 4 | BZ78: 4 | CA78: 4 | CB78: 4 | CC78: 2 | CD78: 3 | CE78: 4 | CF78: 4 | CG78: 2 | CL78: 4 | CQ78: 1 | CS78: 1 | CT78: 3 | CU78: 4 | CV78: 2 | CX78: 1 | CY78: 1 | CZ78: 3 | DB78: 5 | DC78: 14564 | DE78: 663ff63648ca32afb9acc9de | DF78: 0
A79: 45718.455 | B79: 45718.475 | C79: 0 | D79: 98.109.130.188 | E79: 100 | F79: 1705 | G79: 1 | H79: 45718.475 | I79: R_7dXMxv8vyVp4kcj | N79: 40.4131 | O79: -74.2372 | P79: anonymous | Q79: EN | R79: 1 | S79: 63d13e9a41e1c279a151bd4b | T79: 1 | U79: 1 | W79: 2 | Y79: 1 | Z79: 2 | AA79: 1 | AB79: 2 | AC79: 4 | AD79: 3 | AE79: 1 | AF79: 1 | AG79: 2 | AH79: 2 | AI79: 1 | AJ79: 2 | AK79: 3 | AL79: 2 | AN79: 2 | AO79: 1 | AP79: 1 | AR79: 1 | AS79: 4 | AT79: 5 | AU79: 5 | AV79: 5 | AW79: 4 | AX79: 4 | AY79: 4 | AZ79: 5 | BA79: 5 | BB79: 4 | BC79: 4 | BD79: 4 | BE79: 5 | BF79: 4 | BG79: 4 | BH79: 5 | BI79: 5 | BJ79: 4 | BK79: 5 | BL79: 4 | BM79: 4 | BN79: 4 | BO79: 4 | BP79: 5 | BQ79: 4 | BR79: 5 | BS79: 3 | BT79: 4 | BU79: 5 | BV79: 4 | BW79: 4 | BX79: 5 | BY79: 4 | BZ79: 5 | CA79: 4 | CB79: 5 | CC79: 5 | CD79: 4 | CE79: 1 | CF79: 1 | CG79: 3 | CH79: 5 | CI79: 3 | CJ79: 4 | CK79: 2 | CM79: 1 | CN79: 2 | CO79: 3 | CP79: 4 | CQ79: 2 | CS79: 2 | CT79: 3 | CU79: 4 | CV79: 1 | CX79: 1 | CY79: 1 | CZ79: 4 | DB79: 10 | DC79: 07730 | DE79: 63d13e9a41e1c279a151bd4b | DF79: 0
A80: 45718.471 | B80: 45718.475 | C80: 0 | D80: 73.195.125.238 | E80: 100 | F80: 344 | G80: 1 | H80: 45718.475 | I80: R_3KSznVXlIZEFZLz | N80: 40.5407 | O80: -74.314 | P80: anonymous | Q80: EN | R80: 1 | S80: 66f97191dcc6224cd452017a | T80: 1 | U80: 1 | W80: 4 | X80: Live with mom | Y80: 1 | Z80: 2 | AA80: 1 | AB80: 1 | AC80: 2 | AD80: 7 | AE80: 3 | AF80: 2 | AG80: 2 | AH80: 1 | AI80: 2 | AJ80: 1 | AS80: 1 | AT80: 1 | AU80: 2 | AV80: 2 | AW80: 1 | AX80: 3 | AY80: 1 | AZ80: 1 | BA80: 1 | BB80: 1 | BC80: 1 | BD80: 1 | BE80: 1 | BF80: 1 | BG80: 1 | BH80: 4 | BI80: 4 | BJ80: 1 | BK80: 4 | BL80: 2 | BM80: 3 | BN80: 3 | BO80: 1 | BP80: 5 | BQ80: 5 | BR80: 5 | BS80: 3 | BT80: 3 | BU80: 1 | BV80: 1 | BW80: 1 | BX80: 1 | BY80: 2 | BZ80: 1 | CA80: 1 | CB80: 4 | CC80: 1 | CD80: 1 | CE80: 1 | CF80: 3 | CG80: 2 | CQ80: 2 | CS80: 5 | CT80: 2 | CU80: 4 | CV80: 1 | CX80: 1 | CY80: 1 | CZ80: 8 | DB80: 4 | DC80: 07008 | DE80: 66f97191dcc6224cd452017a | DF80: 0
A81: 45718.471 | B81: 45718.475 | C81: 0 | D81: 206.171.36.102 | E81: 100 | F81: 381 | G81: 1 | H81: 45718.475 | I81: R_7kXFBZgFezLhE2I | N81: 40.7785 | O81: -73.9898 | P81: anonymous | Q81: EN | R81: 1 | S81: 6777ed538463a07760a8cae9 | T81: 2 | U81: 2 | W81: 1 | Y81: 7 | Z81: 2 | AA81: 1 | AB81: 2 | AC81: 2 | AD81: 2 | AE81: 1 | AF81: 2 | AG81: 2 | AH81: 2 | AI81: 2 | AJ81: 1 | AS81: 4 | AT81: 3 | AU81: 4 | AV81: 3 | AW81: 3 | AX81: 4 | AY81: 3 | AZ81: 4 | BA81: 3 | BB81: 3 | BC81: 3 | BD81: 4 | BE81: 4 | BF81: 4 | BG81: 3 | BH81: 4 | BI81: 2 | BJ81: 5 | BK81: 5 | BL81: 2 | BM81: 4 | BN81: 4 | BO81: 2 | BP81: 2 | BQ81: 2 | BR81: 2 | BS81: 3 | BT81: 2 | BU81: 3 | BV81: 4 | BW81: 2 | BX81: 3 | BY81: 4 | BZ81: 3 | CA81: 2 | CB81: 4 | CC81: 3 | CD81: 3 | CE81: 4 | CF81: 4 | CG81: 1 | CL81: 3 | CQ81: 2 | CS81: 1 | CT81: 4 | CU81: 4 | CV81: 1 | CX81: 1 | CY81: 2 | CZ81: 3 | DB81: 10 | DC81: 10980 | DE81: 6777ed538463a07760a8cae9 | DF81: 0
A82: 45718.47 | B82: 45718.477 | C82: 0 | D82: 68.195.128.254 | E82: 100 | F82: 658 | G82: 1 | H82: 45718.477 | I82: R_3pti1azchkCjQuE | N82: 40.793 | O82: -74.0247 | P82: anonymous | Q82: EN | R82: 1 | S82: 657f8d99678be2d216a85c3d | T82: 1 | U82: 3 | W82: 2 | Y82: 5 | Z82: 1 | AA82: 1 | AB82: 2 | AC82: 1 | AD82: 3 | AE82: 2 | AF82: 2 | AG82: 2 | AH82: 2 | AI82: 1 | AJ82: 2 | AK82: 2 | AL82: 2 | AN82: 3 | AO82: 2 | AP82: 5 | AR82: 1 | AS82: 4 | AT82: 4 | AU82: 4 | AV82: 4 | AW82: 2 | AX82: 2 | AY82: 2 | AZ82: 2 | BA82: 3 | BB82: 3 | BC82: 4 | BD82: 4 | BE82: 3 | BF82: 4 | BG82: 2 | BH82: 3 | BI82: 2 | BJ82: 4 | BK82: 4 | BL82: 4 | BM82: 4 | BN82: 4 | BO82: 2 | BP82: 2 | BQ82: 3 | BR82: 2 | BS82: 3 | BT82: 4 | BU82: 4 | BV82: 3 | BW82: 3 | BX82: 2 | BY82: 4 | BZ82: 3 | CA82: 3 | CB82: 4 | CC82: 3 | CD82: 1 | CE82: 1 | CF82: 3 | CG82: 1 | CH82: 2 | CI82: 1 | CJ82: 4 | CK82: 4 | CM82: 1 | CN82: 2 | CO82: 3 | CP82: 4 | CQ82: 1 | CS82: 3 | CT82: 3 | CU82: 4 | CV82: 1 | CX82: 1 | CY82: 1 | CZ82: 4 | DB82: 10 | DC82: 07030 | DD82: Some of the questions seemed specific to houses while I live in a condominium. However, I am in a flood zone and have had damage to my car as my city has flood numerous times while Ive lived here | DE82: 657f8d99678be2d216a85c3d | DF82: 0
A83: 45718.468 | B83: 45718.478 | C83: 0 | D83: 108.50.221.203 | E83: 100 | F83: 869 | G83: 1 | H83: 45718.478 | I83: R_6COxACO4zhxSDRw | N83: 40.798 | O83: -74.2416 | P83: anonymous | Q83: EN | R83: 1 | S83: 5c7e9e5384fc500017bee7ce | T83: 1 | U83: 1 | W83: 2 | Y83: 1 | Z83: 2 | AA83: 1 | AB83: 2 | AC83: 3 | AD83: 4 | AE83: 1 | AF83: 2 | AG83: 2 | AH83: 2 | AI83: 2 | AJ83: 1 | AS83: 4 | AT83: 4 | AU83: 4 | AV83: 4 | AW83: 5 | AX83: 4 | AY83: 3 | AZ83: 3 | BA83: 4 | BB83: 4 | BC83: 2 | BD83: 2 | BE83: 4 | BF83: 5 | BG83: 3 | BH83: 2 | BI83: 3 | BJ83: 2 | BK83: 2 | BL83: 2 | BM83: 1 | BN83: 1 | BO83: 2 | BP83: 2 | BQ83: 3 | BR83: 3 | BS83: 3 | BT83: 1 | BU83: 3 | BV83: 3 | BW83: 3 | BX83: 4 | BY83: 4 | BZ83: 3 | CA83: 3 | CB83: 4 | CC83: 3 | CD83: 4 | CE83: 4 | CF83: 1 | CG83: 1 | CH83: 3 | CI83: 1 | CJ83: 1 | CK83: 3 | CM83: 4 | CN83: 2 | CO83: 3 | CP83: 1 | CQ83: 1 | CS83: 1 | CT83: 3 | CU83: 2 | CV83: 5 | CW83: Student | CX83: 1 | CY83: 1 | CZ83: 8 | DA83: Student | DB83: 9 | DC83: 07052 | DE83: 5c7e9e5384fc500017bee7ce | DF83: 0
A84: 45718.474 | B84: 45718.478 | C84: 0 | D84: 73.160.76.120 | E84: 100 | F84: 379 | G84: 1 | H84: 45718.478 | I84: R_5f3Rwxj8VpfN9oT | N84: 39.7665 | O84: -75.1443 | P84: anonymous | Q84: EN | R84: 1 | S84: 5ced8f96a726ed0015d31452 | T84: 1 | U84: 1 | W84: 2 | Y84: 1 | Z84: 2 | AA84: 1 | AB84: 2 | AC84: 2 | AD84: 2 | AE84: 1 | AF84: 2 | AG84: 2 | AH84: 2 | AI84: 2 | AJ84: 1 | AS84: 4 | AT84: 4 | AU84: 4 | AV84: 4 | AW84: 2 | AX84: 4 | AY84: 2 | AZ84: 4 | BA84: 3 | BB84: 3 | BC84: 3 | BD84: 2 | BE84: 4 | BF84: 2 | BG84: 2 | BH84: 4 | BI84: 1 | BJ84: 1 | BK84: 2 | BL84: 1 | BM84: 1 | BN84: 1 | BO84: 1 | BP84: 1 | BQ84: 1 | BR84: 1 | BS84: 3 | BT84: 2 | BU84: 2 | BV84: 4 | BW84: 3 | BX84: 3 | BY84: 5 | BZ84: 2 | CA84: 2 | CB84: 5 | CC84: 1 | CD84: 1 | CE84: 4 | CF84: 4 | CG84: 1 | CH84: 2 | CI84: 1 | CJ84: 1 | CK84: 5 | CM84: 1 | CN84: 2 | CO84: 4 | CP84: 3 | CQ84: 2 | CS84: 2 | CT84: 4 | CU84: 4 | CV84: 1 | CX84: 1 | CY84: 1 | CZ84: 5 | DB84: 10 | DC84: 08012 | DE84: 5ced8f96a726ed0015d31452 | DF84: 0
A85: 45718.473 | B85: 45718.478 | C85: 0 | D85: 172.59.208.77 | E85: 100 | F85: 478 | G85: 1 | H85: 45718.478 | I85: R_3BniqxRNqthQfNZ | N85: 40.7463 | O85: -74.1553 | P85: anonymous | Q85: EN | R85: 1 | S85: 614f74c86e809d190daf00a4 | T85: 1 | U85: 1 | W85: 2 | Y85: 3 | Z85: 2 | AA85: 1 | AB85: 2 | AC85: 2 | AD85: 3 | AE85: 1 | AF85: 2 | AG85: 2 | AH85: 2 | AI85: 2 | AJ85: 1 | AS85: 3 | AT85: 2 | AU85: 2 | AV85: 2 | AW85: 3 | AX85: 2 | AY85: 1 | AZ85: 1 | BA85: 1 | BB85: 1 | BC85: 1 | BD85: 1 | BE85: 1 | BF85: 1 | BG85: 1 | BH85: 4 | BI85: 4 | BJ85: 2 | BK85: 2 | BL85: 2 | BM85: 2 | BN85: 2 | BO85: 3 | BP85: 4 | BQ85: 5 | BR85: 3 | BS85: 3 | BT85: 2 | BU85: 2 | BV85: 5 | BW85: 3 | BX85: 2 | BY85: 5 | BZ85: 3 | CA85: 2 | CB85: 3 | CC85: 3 | CD85: 3 | CE85: 4 | CF85: 3 | CG85: 1 | CH85: 2 | CI85: 1 | CJ85: 5 | CK85: 4 | CM85: 2 | CN85: 4 | CO85: 1 | CP85: 3 | CQ85: 1 | CS85: 4 | CT85: 2 | CU85: 4 | CV85: 3 | CX85: 1 | CY85: 2 | CZ85: 7 | DB85: 10 | DC85: 07874 | DD85: Good luck with your research! :-) | DE85: 614f74c86e809d190daf00a4 | DF85: 0
A86: 45718.474 | B86: 45718.48 | C86: 0 | D86: 67.251.139.200 | E86: 100 | F86: 482 | G86: 1 | H86: 45718.48 | I86: R_5rIGm66KyBbLNNP | N86: 41.5603 | O86: -74.1745 | P86: anonymous | Q86: EN | R86: 1 | S86: 66b6b9378cb7193d92ed359d | T86: 2 | U86: 1 | W86: 2 | Y86: 3 | Z86: 2 | AA86: 1 | AB86: 1 | AC86: 3 | AD86: 6 | AE86: 1 | AF86: 2 | AG86: 2 | AH86: 1 | AI86: 2 | AJ86: 1 | AS86: 4 | AT86: 4 | AU86: 4 | AV86: 4 | AW86: 4 | AX86: 4 | AY86: 4 | AZ86: 4 | BA86: 4 | BB86: 4 | BC86: 4 | BD86: 4 | BE86: 4 | BF86: 4 | BG86: 4 | BH86: 4 | BI86: 2 | BJ86: 3 | BK86: 2 | BL86: 2 | BM86: 2 | BN86: 2 | BO86: 4 | BP86: 4 | BQ86: 4 | BR86: 2 | BS86: 3 | BT86: 2 | BU86: 2 | BV86: 2 | BW86: 3 | BX86: 2 | BY86: 4 | BZ86: 3 | CA86: 2 | CB86: 4 | CC86: 3 | CD86: 2 | CE86: 4 | CF86: 3 | CG86: 1 | CH86: 3 | CI86: 1 | CJ86: 2 | CK86: 3 | CM86: 1 | CN86: 3 | CO86: 2 | CP86: 4 | CQ86: 1 | CS86: 5 | CT86: 2 | CU86: 4 | CV86: 1 | CX86: 1 | CY86: 2 | CZ86: 1 | DB86: 10 | DC86: 12566 | DE86: 66b6b9378cb7193d92ed359d | DF86: 0
A87: 45718.477 | B87: 45718.48 | C87: 0 | D87: 108.50.137.82 | E87: 100 | F87: 272 | G87: 1 | H87: 45718.48 | I87: R_1FDIrlxR1soSIrv | N87: 40.9817 | O87: -74.1101 | P87: anonymous | Q87: EN | R87: 1 | S87: 5a86357bae9a0b0001a9f14e | T87: 1 | U87: 1 | W87: 2 | Y87: 3 | Z87: 2 | AA87: 1 | AB87: 2 | AC87: 1 | AD87: 2 | AE87: 1 | AF87: 2 | AG87: 2 | AH87: 2 | AI87: 1 | AJ87: 2 | AK87: 2 | AL87: 1 | AM87: 2021 | AN87: 2 | AO87: 1 | AP87: 1 | AR87: 1 | AS87: 4 | AT87: 4 | AU87: 4 | AV87: 4 | AW87: 5 | AX87: 5 | AY87: 4 | AZ87: 4 | BA87: 4 | BB87: 5 | BC87: 5 | BD87: 4 | BE87: 5 | BF87: 4 | BG87: 4 | BH87: 2 | BI87: 2 | BJ87: 4 | BK87: 4 | BL87: 5 | BM87: 4 | BN87: 4 | BO87: 2 | BP87: 2 | BQ87: 2 | BR87: 2 | BS87: 3 | BT87: 4 | BU87: 4 | BV87: 2 | BW87: 2 | BX87: 4 | BY87: 4 | BZ87: 4 | CA87: 3 | CB87: 2 | CC87: 2 | CD87: 4 | CE87: 1 | CF87: 4 | CG87: 1 | CH87: 1 | CI87: 1 | CJ87: 2 | CK87: 4 | CM87: 1 | CN87: 4 | CO87: 2 | CP87: 3 | CQ87: 2 | CS87: 2 | CT87: 3 | CU87: 4 | CV87: 1 | CX87: 1 | CY87: 1 | CZ87: 4 | DB87: 10 | DC87: 07432 | DE87: 5a86357bae9a0b0001a9f14e | DF87: 0
A88: 45718.472 | B88: 45718.481 | C88: 0 | D88: 71.183.48.68 | E88: 100 | F88: 742 | G88: 1 | H88: 45718.481 | I88: R_3qCAKJSINBokzE8 | N88: 40.5739 | O88: -73.841 | P88: anonymous | Q88: EN | R88: 1 | S88: 63b6d3e17fd3063a57be2512 | T88: 2 | U88: 2 | W88: 1 | Y88: 7 | Z88: 1 | AA88: 1 | AB88: 2 | AC88: 6 | AD88: 3 | AE88: 1 | AF88: 1 | AG88: 1 | AH88: 2 | AI88: 2 | AJ88: 1 | AS88: 4 | AT88: 4 | AU88: 4 | AV88: 4 | AW88: 5 | AX88: 4 | AY88: 3 | AZ88: 4 | BA88: 4 | BB88: 5 | BC88: 3 | BD88: 3 | BE88: 3 | BF88: 2 | BG88: 3 | BH88: 4 | BI88: 4 | BJ88: 2 | BK88: 4 | BL88: 5 | BM88: 5 | BN88: 5 | BO88: 5 | BP88: 3 | BQ88: 3 | BR88: 3 | BS88: 3 | BT88: 4 | BU88: 4 | BV88: 2 | BW88: 5 | BX88: 1 | BY88: 3 | BZ88: 3 | CA88: 4 | CB88: 5 | CC88: 4 | CD88: 4 | CE88: 4 | CF88: 2 | CG88: 1 | CL88: 5 | CQ88: 1 | CS88: 2 | CT88: 2 | CU88: 4 | CV88: 1 | CX88: 1 | CY88: 1 | CZ88: 3 | DB88: 10 | DC88: 11694 | DD88: the page before you joined the study says 8 minutes. The consent page says 10. Do I sit on this screen for 10 minutes now? | DE88: 63b6d3e17fd3063a57be2512 | DF88: 0
A89: 45718.476 | B89: 45718.481 | C89: 0 | D89: 73.33.227.166 | E89: 100 | F89: 426 | G89: 1 | H89: 45718.481 | I89: R_7cCvVhrr72k4LxY | N89: 40.0726 | O89: -74.7207 | P89: anonymous | Q89: EN | R89: 1 | S89: 5842fc63bd63a400010f6ae7 | T89: 1 | U89: 1 | W89: 2 | Y89: 1 | Z89: 1 | AA89: 1 | AB89: 2 | AC89: 3 | AD89: 2 | AE89: 1 | AF89: 2 | AG89: 1 | AH89: 2 | AI89: 2 | AJ89: 1 | AS89: 3 | AT89: 3 | AU89: 4 | AV89: 4 | AW89: 3 | AX89: 4 | AY89: 2 | AZ89: 2 | BA89: 2 | BB89: 2 | BC89: 2 | BD89: 1 | BE89: 3 | BF89: 1 | BG89: 1 | BH89: 4 | BI89: 3 | BJ89: 3 | BK89: 3 | BL89: 3 | BM89: 4 | BN89: 2 | BO89: 5 | BP89: 4 | BQ89: 5 | BR89: 5 | BS89: 3 | BT89: 3 | BU89: 3 | BV89: 3 | BW89: 4 | BX89: 2 | BY89: 4 | BZ89: 4 | CA89: 2 | CB89: 4 | CC89: 4 | CD89: 4 | CE89: 1 | CF89: 3 | CG89: 1 | CH89: 4 | CI89: 2 | CJ89: 1 | CK89: 2 | CM89: 1 | CN89: 3 | CO89: 4 | CP89: 2 | CQ89: 1 | CS89: 4 | CT89: 4 | CU89: 4 | CV89: 1 | CX89: 1 | CY89: 1 | CZ89: 4 | DB89: 9 | DC89: 08068 | DE89: 5842fc63bd63a400010f6ae7 | DF89: 0
A90: 45718.469 | B90: 45718.481 | C90: 0 | D90: 162.83.137.220 | E90: 100 | F90: 1033 | G90: 1 | H90: 45718.481 | I90: R_5BRBH43pNPyJcjs | N90: 40.6117 | O90: -74.0851 | P90: anonymous | Q90: EN | R90: 1 | S90: 5c10a3702b16ba0001c8747a | T90: 2 | U90: 1 | W90: 2 | Y90: 3 | Z90: 1 | AA90: 1 | AB90: 2 | AC90: 2 | AD90: 2 | AE90: 1 | AF90: 2 | AG90: 2 | AH90: 2 | AI90: 2 | AJ90: 1 | AS90: 5 | AT90: 5 | AU90: 5 | AV90: 5 | AW90: 5 | AX90: 5 | AY90: 5 | AZ90: 5 | BA90: 5 | BB90: 5 | BC90: 5 | BD90: 5 | BE90: 5 | BF90: 5 | BG90: 1 | BH90: 1 | BI90: 1 | BJ90: 5 | BK90: 5 | BL90: 5 | BM90: 5 | BN90: 5 | BO90: 1 | BP90: 1 | BQ90: 5 | BR90: 5 | BS90: 3 | BT90: 5 | BU90: 5 | BV90: 5 | BW90: 3 | BX90: 1 | BY90: 5 | BZ90: 5 | CA90: 4 | CB90: 5 | CC90: 1 | CD90: 2 | CE90: 1 | CF90: 5 | CG90: 1 | CH90: 1 | CI90: 1 | CJ90: 1 | CK90: 4 | CM90: 1 | CN90: 4 | CO90: 2 | CP90: 3 | CQ90: 2 | CS90: 2 | CT90: 3 | CU90: 4 | CV90: 1 | CX90: 1 | CY90: 2 | CZ90: 5 | DB90: 10 | DC90: 10305 | DE90: 5c10a3702b16ba0001c8747a | DF90: 0
A91: 45718.476 | B91: 45718.482 | C91: 0 | D91: 174.206.231.157 | E91: 100 | F91: 547 | G91: 1 | H91: 45718.482 | I91: R_69m5l3Br0n78gvW | N91: 40.6947 | O91: -74.2688 | P91: anonymous | Q91: EN | R91: 1 | S91: 66d469950c5528673c92f3f4 | T91: 1 | U91: 1 | W91: 2 | Y91: 1 | Z91: 2 | AA91: 1 | AB91: 2 | AC91: 2 | AD91: 3 | AE91: 1 | AF91: 2 | AG91: 2 | AH91: 2 | AI91: 1 | AJ91: 2 | AK91: 2 | AL91: 2 | AN91: 1 | AO91: 2 | AP91: 5 | AR91: 1 | AS91: 4 | AT91: 4 | AU91: 4 | AV91: 4 | AW91: 3 | AX91: 3 | AY91: 4 | AZ91: 3 | BA91: 4 | BB91: 4 | BC91: 4 | BD91: 3 | BE91: 4 | BF91: 4 | BG91: 4 | BH91: 2 | BI91: 2 | BJ91: 2 | BK91: 4 | BL91: 2 | BM91: 3 | BN91: 2 | BO91: 2 | BP91: 2 | BQ91: 4 | BR91: 3 | BS91: 3 | BT91: 3 | BU91: 4 | BV91: 2 | BW91: 2 | BX91: 3 | BY91: 4 | BZ91: 4 | CA91: 3 | CB91: 4 | CC91: 3 | CD91: 3 | CE91: 1 | CF91: 4 | CG91: 1 | CH91: 2 | CI91: 1 | CJ91: 2 | CK91: 4 | CM91: 1 | CN91: 3 | CO91: 2 | CP91: 4 | CQ91: 1 | CS91: 3 | CT91: 3 | CU91: 4 | CV91: 1 | CX91: 1 | CY91: 2 | CZ91: 4 | DB91: 10 | DC91: 07401 | DD91: Very easy to understand! | DE91: 66d469950c5528673c92f3f4 | DF91: 0
A92: 45718.478 | B92: 45718.483 | C92: 0 | D92: 47.20.58.176 | E92: 100 | F92: 458 | G92: 1 | H92: 45718.483 | I92: R_53CjjMTdGW6rfOA | N92: 40.8549 | O92: -73.2157 | P92: anonymous | Q92: EN | R92: 1 | S92: 666601d2d09c8744714ca8a1 | T92: 2 | U92: 2 | W92: 1 | Y92: 7 | Z92: 1 | AA92: 1 | AB92: 2 | AC92: 2 | AD92: 2 | AE92: 1 | AF92: 2 | AG92: 2 | AH92: 2 | AI92: 2 | AJ92: 1 | AS92: 4 | AT92: 4 | AU92: 4 | AV92: 4 | AW92: 4 | AX92: 4 | AY92: 4 | AZ92: 4 | BA92: 4 | BB92: 4 | BC92: 4 | BD92: 4 | BE92: 4 | BF92: 5 | BG92: 4 | BH92: 2 | BI92: 1 | BJ92: 3 | BK92: 4 | BL92: 1 | BM92: 3 | BN92: 1 | BO92: 3 | BP92: 3 | BQ92: 2 | BR92: 1 | BS92: 3 | BT92: 3 | BU92: 3 | BV92: 4 | BW92: 4 | BX92: 4 | BY92: 4 | BZ92: 4 | CA92: 4 | CB92: 5 | CC92: 5 | CD92: 5 | CE92: 4 | CF92: 1 | CG92: 1 | CL92: 5 | CQ92: 1 | CS92: 5 | CT92: 2 | CU92: 4 | CV92: 5 | CW92: self employed | CX92: 1 | CY92: 1 | CZ92: 2 | DB92: 10 | DC92: 11788 | DE92: 666601d2d09c8744714ca8a1 | DF92: 0
A93: 45718.475 | B93: 45718.483 | C93: 0 | D93: 108.53.189.22 | E93: 100 | F93: 701 | G93: 1 | H93: 45718.483 | I93: R_6kttSK3ero7v8lz | N93: 40.3209 | O93: -74.4208 | P93: anonymous | Q93: EN | R93: 1 | S93: 6789ac8527bbce25fe21a7a4 | T93: 1 | U93: 1 | W93: 2 | Y93: 6 | Z93: 2 | AA93: 1 | AB93: 2 | AC93: 4 | AD93: 4 | AE93: 1 | AF93: 2 | AG93: 2 | AH93: 1 | AI93: 1 | AJ93: 2 | AK93: 2 | AL93: 1 | AM93: 2021 | AN93: 2 | AO93: 2 | AP93: 4 | AQ93: Install Ejector Pump | AR93: 1 | AS93: 3 | AT93: 4 | AU93: 3 | AV93: 3 | AW93: 3 | AX93: 3 | AY93: 2 | AZ93: 2 | BA93: 3 | BB93: 4 | BC93: 4 | BD93: 3 | BE93: 4 | BF93: 3 | BG93: 3 | BH93: 3 | BI93: 2 | BJ93: 4 | BK93: 4 | BL93: 2 | BM93: 3 | BN93: 2 | BO93: 2 | BP93: 3 | BQ93: 4 | BR93: 2 | BS93: 3 | BT93: 3 | BU93: 3 | BV93: 3 | BW93: 3 | BX93: 2 | BY93: 4 | BZ93: 4 | CA93: 2 | CB93: 3 | CC93: 2 | CD93: 3 | CE93: 1 | CF93: 4 | CG93: 1 | CH93: 3 | CI93: 1 | CJ93: 3 | CK93: 4 | CM93: 1 | CN93: 3 | CO93: 4 | CP93: 2 | CQ93: 2 | CS93: 1 | CT93: 3 | CU93: 5 | CV93: 2 | CX93: 1 | CY93: 2 | CZ93: 3 | DB93: 10 | DC93: 08831 | DD93: Thank you | DE93: 6789ac8527bbce25fe21a7a4 | DF93: 0
A94: 45718.475 | B94: 45718.484 | C94: 0 | D94: 174.197.129.36 | E94: 100 | F94: 756 | G94: 1 | H94: 45718.484 | I94: R_3GDamK1bFCb3mj7 | N94: 40.793 | O94: -74.0247 | P94: anonymous | Q94: EN | R94: 1 | S94: 60e9fd8a2f52070be49cf317 | T94: 1 | U94: 3 | W94: 1 | Y94: 6 | Z94: 1 | AA94: 1 | AB94: 2 | AC94: 2 | AD94: 2 | AE94: 1 | AF94: 2 | AG94: 2 | AH94: 2 | AI94: 2 | AJ94: 1 | AS94: 5 | AT94: 5 | AU94: 5 | AV94: 5 | AW94: 5 | AX94: 5 | AY94: 5 | AZ94: 5 | BA94: 5 | BB94: 5 | BC94: 3 | BD94: 5 | BE94: 5 | BF94: 4 | BG94: 3 | BH94: 4 | BI94: 3 | BJ94: 3 | BK94: 2 | BL94: 4 | BM94: 4 | BN94: 4 | BO94: 3 | BP94: 3 | BQ94: 3 | BR94: 2 | BS94: 3 | BT94: 4 | BU94: 3 | BV94: 5 | BW94: 5 | BX94: 4 | BY94: 4 | BZ94: 4 | CA94: 4 | CB94: 4 | CC94: 4 | CD94: 4 | CE94: 1 | CF94: 5 | CG94: 1 | CL94: 3 | CQ94: 2 | CS94: 1 | CT94: 3 | CU94: 4 | CV94: 1 | CX94: 1 | CY94: 1 | CZ94: 4 | DB94: 10 | DC94: 07950 | DD94: None thank you!! | DE94: 60e9fd8a2f52070be49cf317 | DF94: 0
A95: 45718.478 | B95: 45718.485 | C95: 0 | D95: 66.67.82.62 | E95: 100 | F95: 619 | G95: 1 | H95: 45718.485 | I95: R_5q8zxw7h1YaGQxP | N95: 44.0584 | O95: -75.7619 | P95: anonymous | Q95: EN | R95: 1 | S95: 6657ec86de21bffb2036473e | T95: 2 | U95: 2 | W95: 1 | Y95: 5 | Z95: 2 | AA95: 1 | AB95: 2 | AC95: 3 | AD95: 2 | AE95: 1 | AF95: 1 | AG95: 2 | AH95: 2 | AI95: 2 | AJ95: 1 | AS95: 4 | AT95: 4 | AU95: 2 | AV95: 4 | AW95: 3 | AX95: 3 | AY95: 2 | AZ95: 2 | BA95: 3 | BB95: 3 | BC95: 4 | BD95: 2 | BE95: 4 | BF95: 2 | BG95: 2 | BH95: 2 | BI95: 1 | BJ95: 2 | BK95: 2 | BL95: 1 | BM95: 2 | BN95: 1 | BO95: 2 | BP95: 2 | BQ95: 2 | BR95: 1 | BS95: 3 | BT95: 2 | BU95: 1 | BV95: 4 | BW95: 3 | BX95: 4 | BY95: 4 | BZ95: 3 | CA95: 2 | CB95: 4 | CC95: 2 | CD95: 3 | CE95: 4 | CF95: 4 | CG95: 1 | CL95: 2 | CQ95: 1 | CS95: 2 | CT95: 3 | CU95: 4 | CV95: 5 | CW95: Homemaker | CX95: 1 | CY95: 2 | CZ95: 8 | DA95: Homemaker | DB95: 10 | DC95: 13603 | DE95: 6657ec86de21bffb2036473e | DF95: 0
A96: 45718.478 | B96: 45718.485 | C96: 0 | D96: 174.208.45.208 | E96: 100 | F96: 617 | G96: 1 | H96: 45718.485 | I96: R_7mEqAFapQQm2e2Q | N96: 42.9685 | O96: -78.7492 | P96: anonymous | Q96: EN | R96: 1 | S96: 6743d00780033fc64a081696 | T96: 2 | U96: 2 | W96: 1 | Y96: 2 | Z96: 2 | AA96: 1 | AB96: 2 | AC96: 3 | AD96: 3 | AE96: 1 | AF96: 2 | AG96: 1 | AH96: 2 | AI96: 2 | AJ96: 1 | AS96: 3 | AT96: 4 | AU96: 3 | AV96: 4 | AW96: 4 | AX96: 2 | AY96: 2 | AZ96: 2 | BA96: 4 | BB96: 2 | BC96: 3 | BD96: 4 | BE96: 4 | BF96: 4 | BG96: 2 | BH96: 4 | BI96: 2 | BJ96: 4 | BK96: 4 | BL96: 2 | BM96: 4 | BN96: 4 | BO96: 5 | BP96: 4 | BQ96: 4 | BR96: 2 | BS96: 3 | BT96: 4 | BU96: 4 | BV96: 4 | BW96: 2 | BX96: 4 | BY96: 5 | BZ96: 3 | CA96: 4 | CB96: 5 | CC96: 2 | CD96: 4 | CE96: 2 | CF96: 4 | CG96: 1 | CL96: 4 | CQ96: 2 | CS96: 2 | CT96: 2 | CU96: 4 | CV96: 1 | CX96: 1 | CY96: 2 | CZ96: 7 | DB96: 9 | DC96: 14830 | DE96: 6743d00780033fc64a081696 | DF96: 0
A97: 45718.479 | B97: 45718.485 | C97: 0 | D97: 73.194.77.108 | E97: 100 | F97: 552 | G97: 1 | H97: 45718.485 | I97: R_61mArR3JZxqSMlH | N97: 39.8023 | O97: -75.0641 | P97: anonymous | Q97: EN | R97: 1 | S97: 66d77728aa95856ee65ecd73 | T97: 1 | U97: 1 | W97: 2 | Y97: 3 | Z97: 2 | AA97: 1 | AB97: 2 | AC97: 4 | AD97: 2 | AE97: 1 | AF97: 2 | AG97: 2 | AH97: 2 | AI97: 2 | AJ97: 1 | AS97: 3 | AT97: 2 | AU97: 3 | AV97: 4 | AW97: 4 | AX97: 4 | AY97: 2 | AZ97: 2 | BA97: 3 | BB97: 2 | BC97: 2 | BD97: 2 | BE97: 3 | BF97: 4 | BG97: 1 | BH97: 2 | BI97: 2 | BJ97: 2 | BK97: 2 | BL97: 1 | BM97: 2 | BN97: 1 | BO97: 4 | BP97: 4 | BQ97: 2 | BR97: 2 | BS97: 3 | BT97: 1 | BU97: 1 | BV97: 4 | BW97: 3 | BX97: 2 | BY97: 4 | BZ97: 3 | CA97: 2 | CB97: 4 | CC97: 3 | CD97: 2 | CE97: 4 | CF97: 4 | CG97: 1 | CH97: 2 | CI97: 1 | CJ97: 4 | CK97: 2 | CM97: 1 | CN97: 3 | CO97: 2 | CP97: 4 | CQ97: 1 | CS97: 4 | CT97: 3 | CU97: 4 | CV97: 1 | CX97: 1 | CY97: 2 | CZ97: 3 | DB97: 10 | DC97: 08081 | DE97: 66d77728aa95856ee65ecd73 | DF97: 0
A98: 45718.48 | B98: 45718.485 | C98: 0 | D98: 69.120.114.17 | E98: 100 | F98: 421 | G98: 1 | H98: 45718.485 | I98: R_76gcIT16S0b8Yhg | N98: 40.8905 | O98: -74.0504 | P98: anonymous | Q98: EN | R98: 1 | S98: 67533a13d3508a91e20c1807 | T98: 1 | U98: 2 | W98: 1 | Y98: 7 | Z98: 1 | AA98: 1 | AB98: 2 | AC98: 5 | AD98: 2 | AE98: 1 | AF98: 1 | AG98: 1 | AH98: 2 | AI98: 1 | AJ98: 2 | AK98: 2 | AL98: 2 | AN98: 3 | AO98: 2 | AP98: 5 | AR98: 1 | AS98: 4 | AT98: 4 | AU98: 4 | AV98: 3 | AW98: 4 | AX98: 4 | AY98: 4 | AZ98: 4 | BA98: 4 | BB98: 4 | BC98: 4 | BD98: 4 | BE98: 3 | BF98: 2 | BG98: 2 | BH98: 4 | BI98: 4 | BJ98: 4 | BK98: 4 | BL98: 5 | BM98: 4 | BN98: 4 | BO98: 4 | BP98: 3 | BQ98: 3 | BR98: 4 | BS98: 3 | BT98: 4 | BU98: 4 | BV98: 4 | BW98: 4 | BX98: 3 | BY98: 4 | BZ98: 4 | CA98: 3 | CB98: 4 | CC98: 4 | CD98: 4 | CE98: 4 | CF98: 2 | CG98: 3 | CL98: 4 | CQ98: 1 | CS98: 1 | CT98: 2 | CU98: 2 | CV98: 5 | CW98: student | CX98: 1 | CY98: 1 | CZ98: 8 | DA98: student | DB98: 9 | DC98: 07026 | DD98: thank you | DE98: 67533a13d3508a91e20c1807 | DF98: 0
A99: 45718.479 | B99: 45718.486 | C99: 0 | D99: 98.13.188.109 | E99: 100 | F99: 550 | G99: 1 | H99: 45718.486 | I99: R_7S5ZsNRgENgjr3Z | N99: 40.6375 | O99: -74.0216 | P99: anonymous | Q99: EN | R99: 1 | S99: 66318a453cf195962fd393ba | T99: 2 | U99: 2 | W99: 2 | Y99: 1 | Z99: 2 | AA99: 2 | AB99: 1 | AC99: 3 | AD99: 4 | AE99: 1 | AF99: 2 | AG99: 2 | AH99: 1 | AI99: 1 | AJ99: 2 | AK99: 2 | AL99: 1 | AM99: 2023 | AN99: 2 | AO99: 2 | AP99: 4 | AQ99: Did some renovations | AR99: 1 | AS99: 4 | AT99: 4 | AU99: 3 | AV99: 3 | AW99: 3 | AX99: 3 | AY99: 2 | AZ99: 3 | BA99: 3 | BB99: 2 | BC99: 2 | BD99: 3 | BE99: 3 | BF99: 4 | BG99: 4 | BH99: 4 | BI99: 4 | BJ99: 3 | BK99: 2 | BL99: 3 | BM99: 3 | BN99: 2 | BO99: 4 | BP99: 5 | BQ99: 5 | BR99: 5 | BS99: 3 | BT99: 2 | BU99: 2 | BV99: 4 | BW99: 3 | BX99: 2 | BY99: 4 | BZ99: 3 | CA99: 2 | CB99: 1 | CC99: 1 | CD99: 1 | CE99: 4 | CF99: 2 | CG99: 2 | CH99: 1 | CI99: 1 | CJ99: 3 | CK99: 2 | CM99: 1 | CN99: 4 | CO99: 3 | CP99: 2 | CQ99: 2 | CS99: 2 | CT99: 3 | CU99: 1 | CV99: 1 | CX99: 1 | CY99: 2 | CZ99: 6 | DB99: 10 | DC99: 11232 | DE99: 66318a453cf195962fd393ba | DF99: 0
A100: 45718.477 | B100: 45718.486 | C100: 0 | D100: 173.68.126.201 | E100: 100 | F100: 777 | G100: 1 | H100: 45718.486 | I100: R_1jZMGuV1JSnGE4B | N100: 41.2709 | O100: -73.7776 | P100: anonymous | Q100: EN | R100: 1 | S100: 67ad6ce838364b28dc8d22b1 | T100: 2 | U100: 1 | W100: 2 | Y100: 3 | Z100: 2 | AA100: 1 | AB100: 1 | AC100: 4 | AD100: 3 | AE100: 1 | AF100: 1 | AG100: 2 | AH100: 1 | AI100: 1 | AJ100: 2 | AK100: 2 | AL100: 1 | AM100: 2023 | AN100: 2 | AO100: 2 | AP100: 5 | AR100: 1 | AS100: 2 | AT100: 3 | AU100: 3 | AV100: 1 | AW100: 3 | AX100: 4 | AY100: 2 | AZ100: 2 | BA100: 3 | BB100: 3 | BC100: 4 | BD100: 2 | BE100: 3 | BF100: 2 | BG100: 2 | BH100: 4 | BI100: 4 | BJ100: 3 | BK100: 4 | BL100: 4 | BM100: 4 | BN100: 4 | BO100: 4 | BP100: 4 | BQ100: 4 | BR100: 4 | BS100: 3 | BT100: 3 | BU100: 2 | BV100: 3 | BW100: 2 | BX100: 3 | BY100: 4 | BZ100: 2 | CA100: 4 | CB100: 4 | CC100: 3 | CD100: 4 | CE100: 2 | CF100: 4 | CG100: 2 | CH100: 3 | CI100: 2 | CJ100: 3 | CK100: 5 | CM100: 1 | CN100: 2 | CO100: 3 | CP100: 4 | CQ100: 1 | CS100: 2 | CT100: 2 | CU100: 4 | CV100: 3 | CX100: 1 | CY100: 1 | CZ100: 3 | DB100: 9 | DC100: 10547 | DD100: No suggestions | DE100: 67ad6ce838364b28dc8d22b1 | DF100: 0
...

Sheet MG
A1: StartDate | B1: EndDate | C1: Status | D1: IPAddress | E1: Progress | F1: Duration (in seconds) | G1: Finished | H1: RecordedDate | I1: ResponseId | J1: RecipientLastName | K1: RecipientFirstName | L1: RecipientEmail | M1: ExternalReference | N1: LocationLatitude | O1: LocationLongitude | P1: DistributionChannel | Q1: UserLanguage | R1: Q1 | S1: Q2 | T1: Q3 | U1: Q4 | V1: Q4_5_TEXT | W1: Q5 | X1: Q5_4_TEXT | Y1: Q6 | Z1: Q7 | AA1: Q8 | AB1: Q9 | AC1: Q10 | AD1: Q11 | AE1: Q12 | AF1: Q13_1 | AG1: Q13_2 | AH1: Q13_3 | AI1: Q14_0 | AJ1: Q14 | AK1: Q15 | AL1: Q16 | AM1: Q16_1_TEXT | AN1: Q17 | AO1: Q18 | AP1: Q19 | AQ1: Q19_4_TEXT | AR1: Q20 | AS1: Q21_1 | AT1: Q21_2 | AU1: Q21_3 | AV1: Q21_4 | AW1: Q21_5 | AX1: Q21_6 | AY1: Q21_7 | AZ1: Q21_8 | BA1: Q21_9 | BB1: Q21_10 | BC1: Q21_11 | BD1: Q21_12 | BE1: Q21_13 | BF1: Q21_14 | BG1: Q21_15 | BH1: Q22_1 | BI1: Q22_2 | BJ1: Q22_3 | BK1: Q22_4 | BL1: Q22_5 | BM1: Q22_6 | BN1: Q22_7 | BO1: Q22_8 | BP1: Q22_9 | BQ1: Q22_10 | BR1: Q22_11 | BS1: Q23 | BT1: Q24_1 | BU1: Q24_2 | BV1: Q25_1 | BW1: Q25_2 | BX1: Q25_3 | BY1: Q25_4 | BZ1: Q25_5 | CA1: Q25_6 | CB1: Q25_7 | CC1: Q25_8 | CD1: Q25_9 | CE1: Q26 | CF1: Q27 | CG1: Q28 | CH1: Q29 | CI1: Q30 | CJ1: Q31 | CK1: Q32 | CL1: Q33 | CM1: Q34_1 | CN1: Q34_2 | CO1: Q34_3 | CP1: Q34_4 | CQ1: Q35 | CR1: Q35_5_TEXT | CS1: Q36 | CT1: Q37 | CU1: Q38 | CV1: Q39 | CW1: Q39_5_TEXT | CX1: Q40 | CY1: Q41 | CZ1: Q42 | DA1: Q42_8_TEXT | DB1: Q43 | DC1: Q44 | DD1: Q45 | DE1: PROLIFIC_PID | DF1: Indicators_Satisfied
A2: 45718.431 | B2: 45718.437 | C2: 0 | D2: 73.248.109.70 | E2: 100 | F2: 524 | G2: 1 | H2: 45718.437 | I2: R_7j7fGoUx2urCdLI | N2: 39.7889 | O2: -74.1982 | P2: anonymous | Q2: EN | R2: 1 | S2: 676c3f1a779ded5787343064 | T2: 1 | U2: 1 | W2: 4 | X2: I live with my parents who own their home. | Y2: 6 | Z2: 2 | AA2: 1 | AB2: 2 | AC2: 3 | AD2: 3 | AE2: 1 | AF2: 2 | AG2: 2 | AH2: 2 | AI2: 2 | AJ2: 1 | AS2: 3 | AT2: 3 | AU2: 3 | AV2: 3 | AW2: 4 | AX2: 3 | AY2: 2 | AZ2: 2 | BA2: 3 | BB2: 3 | BC2: 4 | BD2: 2 | BE2: 4 | BF2: 4 | BG2: 2 | BH2: 4 | BI2: 3 | BJ2: 2 | BK2: 2 | BL2: 2 | BM2: 2 | BN2: 2 | BO2: 4 | BP2: 4 | BQ2: 4 | BR2: 2 | BS2: 3 | BT2: 1 | BU2: 4 | BV2: 2 | BW2: 3 | BX2: 2 | BY2: 4 | BZ2: 4 | CA2: 3 | CB2: 4 | CC2: 3 | CD2: 3 | CE2: 4 | CF2: 2 | CG2: 2 | CQ2: 1 | CS2: 2 | CT2: 2 | CU2: 4 | CV2: 1 | CX2: 1 | CY2: 1 | CZ2: 8 | DA2: veterinarian receptionist | DB2: 4 | DC2: 08758 | DE2: 676c3f1a779ded5787343064 | DF2: 1
A3: 45718.448 | B3: 45718.452 | C3: 0 | D3: 129.21.147.16 | E3: 100 | F3: 310 | G3: 1 | H3: 45718.452 | I3: R_5EXB9X0in8EJLH8 | N3: 43.0801 | O3: -77.6342 | P3: anonymous | Q3: EN | R3: 1 | S3: 656cf11e8c036a31a22e0ccc | T3: 1 | U3: 5 | V3: Apartment | W3: 1 | Y3: 7 | Z3: 2 | AA3: 1 | AB3: 2 | AC3: 4 | AD3: 2 | AE3: 1 | AF3: 2 | AG3: 1 | AH3: 2 | AI3: 2 | AJ3: 1 | AS3: 4 | AT3: 4 | AU3: 4 | AV3: 4 | AW3: 4 | AX3: 3 | AY3: 2 | AZ3: 4 | BA3: 3 | BB3: 4 | BC3: 4 | BD3: 4 | BE3: 4 | BF3: 4 | BG3: 3 | BH3: 2 | BI3: 2 | BJ3: 2 | BK3: 2 | BL3: 2 | BM3: 2 | BN3: 1 | BO3: 2 | BP3: 2 | BQ3: 2 | BR3: 2 | BS3: 3 | BT3: 2 | BU3: 2 | BV3: 4 | BW3: 4 | BX3: 4 | BY3: 4 | BZ3: 4 | CA3: 4 | CB3: 4 | CC3: 4 | CD3: 4 | CE3: 4 | CF3: 2 | CG3: 1 | CL3: 2 | CQ3: 1 | CS3: 1 | CT3: 2 | CU3: 4 | CV3: 3 | CX3: 1 | CY3: 1 | CZ3: 8 | DA3: student | DB3: 2 | DC3: 07920 | DE3: 656cf11e8c036a31a22e0ccc | DF3: 1
A4: 45718.449 | B4: 45718.453 | C4: 0 | D4: 172.59.214.22 | E4: 100 | F4: 333 | G4: 1 | H4: 45718.453 | I4: R_5VqD7RdQwGIfA7U | N4: 40.7597 | O4: -74.1836 | P4: anonymous | Q4: EN | R4: 1 | S4: 6663c5eb2243733847460c5c | T4: 1 | U4: 2 | W4: 1 | Y4: 1 | Z4: 2 | AA4: 2 | AB4: 2 | AC4: 1 | AD4: 7 | AE4: 5 | AF4: 2 | AG4: 2 | AH4: 2 | AI4: 1 | AJ4: 2 | AK4: 2 | AL4: 1 | AM4: Nont | AN4: 4 | AO4: 2 | AP4: 4 | AQ4: Sandbags | AR4: 1 | AS4: 3 | AT4: 4 | AU4: 4 | AV4: 4 | AW4: 4 | AX4: 4 | AY4: 4 | AZ4: 3 | BA4: 4 | BB4: 3 | BC4: 4 | BD4: 3 | BE4: 4 | BF4: 4 | BG4: 3 | BH4: 4 | BI4: 3 | BJ4: 5 | BK4: 5 | BL4: 4 | BM4: 5 | BN4: 5 | BO4: 4 | BP4: 4 | BQ4: 4 | BR4: 2 | BS4: 3 | BT4: 5 | BU4: 5 | BV4: 2 | BW4: 4 | BX4: 4 | BY4: 3 | BZ4: 2 | CA4: 3 | CB4: 2 | CC4: 1 | CD4: 3 | CE4: 4 | CF4: 2 | CG4: 2 | CL4: 4 | CQ4: 2 | CS4: 4 | CT4: 3 | CU4: 2 | CV4: 2 | CX4: 2 | CY4: 1 | CZ4: 6 | DB4: 6 | DC4: 07305 | DE4: 6663c5eb2243733847460c5c | DF4: 1
A5: 45718.438 | B5: 45718.453 | C5: 0 | D5: 172.59.209.180 | E5: 100 | F5: 1322 | G5: 1 | H5: 45718.453 | I5: R_6N4q8RQ3tJfFmH7 | N5: 40.7463 | O5: -74.1553 | P5: anonymous | Q5: EN | R5: 1 | S5: 6766d6be81561a325b3802c9 | T5: 2 | U5: 1 | W5: 3 | Y5: 5 | Z5: 2 | AA5: 1 | AB5: 2 | AC5: 3 | AD5: 4 | AE5: 3 | AF5: 2 | AG5: 1 | AH5: 1 | AI5: 1 | AJ5: 2 | AK5: 7 | AL5: 2 | AN5: 1 | AO5: 2 | AP5: 5 | AR5: 1 | AS5: 4 | AT5: 3 | AU5: 2 | AV5: 3 | AW5: 3 | AX5: 3 | AY5: 3 | AZ5: 3 | BA5: 4 | BB5: 3 | BC5: 3 | BD5: 3 | BE5: 3 | BF5: 4 | BG5: 3 | BH5: 3 | BI5: 4 | BJ5: 3 | BK5: 4 | BL5: 3 | BM5: 4 | BN5: 3 | BO5: 4 | BP5: 3 | BQ5: 4 | BR5: 3 | BS5: 3 | BT5: 3 | BU5: 4 | BV5: 3 | BW5: 4 | BX5: 3 | BY5: 4 | BZ5: 3 | CA5: 4 | CB5: 3 | CC5: 4 | CD5: 3 | CE5: 1 | CF5: 3 | CG5: 4 | CH5: 3 | CI5: 4 | CJ5: 3 | CK5: 3 | CM5: 2 | CN5: 1 | CO5: 3 | CP5: 4 | CQ5: 1 | CS5: 1 | CT5: 3 | CU5: 2 | CV5: 2 | CX5: 1 | CY5: 1 | CZ5: 4 | DB5: 2 | DC5: 10081 | DD5: This survey is good | DE5: 6766d6be81561a325b3802c9 | DF5: 1
A6: 45718.447 | B6: 45718.454 | C6: 0 | D6: 69.207.213.205 | E6: 100 | F6: 642 | G6: 1 | H6: 45718.454 | I6: R_5z8Ywn2drTMmoj1 | N6: 42.4617 | O6: -75.0534 | P6: anonymous | Q6: EN | R6: 1 | S6: 5be0fb420d5adc0001d6d5b7 | T6: 2 | U6: 1 | W6: 2 | Y6: 1 | Z6: 1 | AA6: 1 | AB6: 1 | AC6: 4 | AD6: 3 | AE6: 1 | AF6: 2 | AG6: 1 | AH6: 2 | AI6: 2 | AJ6: 1 | AS6: 5 | AT6: 4 | AU6: 5 | AV6: 5 | AW6: 5 | AX6: 4 | AY6: 5 | AZ6: 5 | BA6: 5 | BB6: 4 | BC6: 4 | BD6: 3 | BE6: 4 | BF6: 5 | BG6: 3 | BH6: 4 | BI6: 3 | BJ6: 4 | BK6: 5 | BL6: 4 | BM6: 4 | BN6: 4 | BO6: 4 | BP6: 5 | BQ6: 5 | BR6: 3 | BS6: 3 | BT6: 3 | BU6: 4 | BV6: 4 | BW6: 3 | BX6: 4 | BY6: 5 | BZ6: 4 | CA6: 4 | CB6: 5 | CC6: 4 | CD6: 5 | CE6: 1 | CF6: 2 | CG6: 2 | CH6: 4 | CI6: 4 | CJ6: 2 | CK6: 2 | CM6: 2 | CN6: 3 | CO6: 4 | CP6: 1 | CQ6: 2 | CS6: 3 | CT6: 2 | CU6: 4 | CV6: 3 | CX6: 1 | CY6: 1 | CZ6: 1 | DB6: 3 | DC6: 12197 | DD6: very easy to understand | DE6: 5be0fb420d5adc0001d6d5b7 | DF6: 1
A7: 45718.455 | B7: 45718.457 | C7: 0 | D7: 74.101.36.175 | E7: 100 | F7: 195 | G7: 1 | H7: 45718.457 | I7: R_3FY1mlyTOLzDbdD | N7: 40.6002 | O7: -74.1469 | P7: anonymous | Q7: EN | R7: 1 | S7: 667c247b3a2743051fdc0f5d | T7: 2 | U7: 1 | W7: 2 | Y7: 4 | Z7: 2 | AA7: 1 | AB7: 2 | AC7: 4 | AD7: 5 | AE7: 1 | AF7: 2 | AG7: 2 | AH7: 1 | AI7: 1 | AJ7: 2 | AK7: 3 | AL7: 2 | AN7: 2 | AO7: 2 | AP7: 5 | AR7: 1 | AS7: 5 | AT7: 4 | AU7: 4 | AV7: 4 | AW7: 4 | AX7: 4 | AY7: 4 | AZ7: 4 | BA7: 3 | BB7: 4 | BC7: 4 | BD7: 3 | BE7: 4 | BF7: 5 | BG7: 4 | BH7: 5 | BI7: 5 | BJ7: 3 | BK7: 2 | BL7: 4 | BM7: 3 | BN7: 4 | BO7: 5 | BP7: 4 | BQ7: 4 | BR7: 5 | BS7: 3 | BT7: 5 | BU7: 4 | BV7: 4 | BW7: 5 | BX7: 4 | BY7: 4 | BZ7: 4 | CA7: 5 | CB7: 5 | CC7: 4 | CD7: 4 | CE7: 1 | CF7: 4 | CG7: 3 | CH7: 4 | CI7: 3 | CJ7: 4 | CK7: 2 | CM7: 1 | CN7: 3 | CO7: 2 | CP7: 4 | CQ7: 1 | CS7: 1 | CT7: 3 | CU7: 1 | CV7: 3 | CX7: 1 | CY7: 1 | CZ7: 2 | DB7: 1 | DC7: 10314 | DE7: 667c247b3a2743051fdc0f5d | DF7: 1
A8: 45718.455 | B8: 45718.458 | C8: 0 | D8: 75.214.77.135 | E8: 100 | F8: 264 | G8: 1 | H8: 45718.458 | I8: R_3MmVu0NevCrAFYo | N8: 40.674 | O8: -73.9701 | P8: anonymous | Q8: EN | R8: 1 | S8: 5e724373a7892a1749fd479d | T8: 2 | U8: 2 | W8: 1 | Y8: 3 | Z8: 2 | AA8: 2 | AB8: 2 | AC8: 2 | AD8: 3 | AE8: 1 | AF8: 2 | AG8: 2 | AH8: 2 | AI8: 2 | AJ8: 1 | AS8: 3 | AT8: 3 | AU8: 3 | AV8: 2 | AW8: 2 | AX8: 2 | AY8: 3 | AZ8: 3 | BA8: 4 | BB8: 3 | BC8: 3 | BD8: 3 | BE8: 3 | BF8: 4 | BG8: 3 | BH8: 3 | BI8: 2 | BJ8: 2 | BK8: 2 | BL8: 2 | BM8: 2 | BN8: 1 | BO8: 4 | BP8: 4 | BQ8: 4 | BR8: 3 | BS8: 3 | BT8: 2 | BU8: 3 | BV8: 3 | BW8: 2 | BX8: 2 | BY8: 3 | BZ8: 2 | CA8: 1 | CB8: 4 | CC8: 3 | CD8: 2 | CE8: 4 | CF8: 3 | CG8: 1 | CL8: 4 | CQ8: 1 | CS8: 2 | CT8: 3 | CU8: 4 | CV8: 2 | CX8: 1 | CY8: 1 | CZ8: 2 | DB8: 5 | DC8: 11216 | DE8: 5e724373a7892a1749fd479d | DF8: 1
A9: 45718.45 | B9: 45718.46 | C9: 0 | D9: 72.45.243.58 | E9: 100 | F9: 930 | G9: 1 | H9: 45718.46 | I9: R_3Veny5RdReBXzr3 | N9: 42.781 | O9: -73.9115 | P9: anonymous | Q9: EN | R9: 1 | S9: 6750718c7d08a1b658702c22 | T9: 2 | U9: 5 | W9: 4 | Y9: 1 | Z9: 2 | AA9: 2 | AB9: 1 | AC9: 1 | AD9: 1 | AE9: 1 | AF9: 2 | AG9: 2 | AH9: 2 | AI9: 2 | AJ9: 1 | AS9: 1 | AT9: 3 | AU9: 1 | AV9: 1 | AW9: 3 | AX9: 5 | AY9: 2 | AZ9: 3 | BA9: 2 | BB9: 4 | BC9: 3 | BD9: 5 | BE9: 3 | BF9: 5 | BG9: 5 | BH9: 2 | BI9: 2 | BJ9: 3 | BK9: 5 | BL9: 3 | BM9: 2 | BN9: 2 | BO9: 2 | BP9: 2 | BQ9: 2 | BR9: 2 | BS9: 3 | BT9: 3 | BU9: 3 | BV9: 2 | BW9: 3 | BX9: 1 | BY9: 4 | BZ9: 4 | CA9: 1 | CB9: 4 | CC9: 4 | CD9: 1 | CE9: 4 | CF9: 3 | CG9: 3 | CQ9: 2 | CS9: 3 | CT9: 5 | CU9: 2 | CV9: 3 | CX9: 1 | CY9: 2 | CZ9: 7 | DB9: 1 | DC9: 12206 | DD9: I dont think every home owner in the world is concerned about having to replace material things | DE9: 6750718c7d08a1b658702c22 | DF9: 1
A10: 45718.451 | B10: 45718.462 | C10: 0 | D10: 172.56.165.131 | E10: 100 | F10: 927 | G10: 1 | H10: 45718.462 | I10: R_3jvL8MBDrZgUtWN | N10: 40.7035 | O10: -73.9235 | P10: anonymous | Q10: EN | R10: 1 | S10: 672c5b912fcc16cf421581e7 | T10: 1 | U10: 1 | W10: 1 | Y10: 1 | Z10: 1 | AA10: 2 | AB10: 1 | AC10: 2 | AD10: 7 | AE10: 4 | AF10: 2 | AG10: 2 | AH10: 1 | AI10: 2 | AJ10: 1 | AS10: 3 | AT10: 4 | AU10: 4 | AV10: 3 | AW10: 3 | AX10: 3 | AY10: 3 | AZ10: 3 | BA10: 3 | BB10: 3 | BC10: 2 | BD10: 2 | BE10: 2 | BF10: 2 | BG10: 2 | BH10: 2 | BI10: 2 | BJ10: 3 | BK10: 4 | BL10: 4 | BM10: 3 | BN10: 4 | BO10: 2 | BP10: 2 | BQ10: 2 | BR10: 2 | BS10: 3 | BT10: 2 | BU10: 3 | BV10: 3 | BW10: 3 | BX10: 3 | BY10: 3 | BZ10: 2 | CA10: 3 | CB10: 3 | CC10: 2 | CD10: 4 | CE10: 4 | CF10: 1 | CG10: 1 | CL10: 3 | CQ10: 2 | CS10: 6 | CT10: 3 | CU10: 5 | CV10: 4 | CX10: 2 | CY10: 2 | CZ10: 8 | DA10: retiree | DB10: 2 | DC10: 08872 | DE10: 672c5b912fcc16cf421581e7 | DF10: 1
A11: 45718.461 | B11: 45718.464 | C11: 0 | D11: 68.198.185.57 | E11: 100 | F11: 249 | G11: 1 | H11: 45718.464 | I11: R_6NywJQEaGDUvvz9 | N11: 40.5828 | O11: -73.9532 | P11: anonymous | Q11: EN | R11: 1 | S11: 66d71dbb91a283b5a18fb170 | T11: 2 | U11: 3 | W11: 1 | Y11: 2 | Z11: 1 | AA11: 1 | AB11: 2 | AC11: 4 | AD11: 6 | AE11: 4 | AF11: 1 | AG11: 2 | AH11: 2 | AI11: 1 | AJ11: 2 | AK11: 1 | AL11: 2 | AN11: 5 | AO11: 2 | AP11: 3 | AR11: 1 | AS11: 5 | AT11: 5 | AU11: 5 | AV11: 5 | AW11: 5 | AX11: 5 | AY11: 5 | AZ11: 5 | BA11: 5 | BB11: 5 | BC11: 5 | BD11: 5 | BE11: 5 | BF11: 5 | BG11: 5 | BH11: 5 | BI11: 5 | BJ11: 2 | BK11: 5 | BL11: 5 | BM11: 3 | BN11: 3 | BO11: 4 | BP11: 3 | BQ11: 5 | BR11: 4 | BS11: 3 | BT11: 4 | BU11: 4 | BV11: 2 | BW11: 2 | BX11: 5 | BY11: 5 | BZ11: 5 | CA11: 5 | CB11: 3 | CC11: 2 | CD11: 4 | CE11: 3 | CF11: 2 | CG11: 4 | CL11: 4 | CQ11: 2 | CS11: 2 | CT11: 3 | CU11: 5 | CV11: 1 | CX11: 1 | CY11: 1 | CZ11: 3 | DB11: 2 | DC11: 11224 | DE11: 66d71dbb91a283b5a18fb170 | DF11: 1
A12: 45718.457 | B12: 45718.465 | C12: 0 | D12: 24.228.254.242 | E12: 100 | F12: 653 | G12: 1 | H12: 45718.465 | I12: R_3XgiyptlALxsBln | N12: 40.4551 | O12: -74.4871 | P12: anonymous | Q12: EN | R12: 1 | S12: 66bf519b34c66d259e5554d1 | T12: 1 | U12: 1 | W12: 1 | Y12: 4 | Z12: 1 | AA12: 1 | AB12: 1 | AC12: 6 | AD12: 2 | AE12: 1 | AF12: 2 | AG12: 1 | AH12: 2 | AI12: 1 | AJ12: 2 | AK12: 2 | AL12: 2 | AN12: 1 | AO12: 2 | AP12: 5 | AR12: 1 | AS12: 4 | AT12: 4 | AU12: 5 | AV12: 4 | AW12: 4 | AX12: 4 | AY12: 4 | AZ12: 4 | BA12: 4 | BB12: 4 | BC12: 4 | BD12: 2 | BE12: 4 | BF12: 4 | BG12: 4 | BH12: 5 | BI12: 4 | BJ12: 3 | BK12: 2 | BL12: 2 | BM12: 4 | BN12: 2 | BO12: 4 | BP12: 4 | BQ12: 4 | BR12: 4 | BS12: 3 | BT12: 2 | BU12: 2 | BV12: 2 | BW12: 4 | BX12: 2 | BY12: 2 | BZ12: 2 | CA12: 2 | CB12: 4 | CC12: 2 | CD12: 2 | CE12: 1 | CF12: 4 | CG12: 1 | CL12: 2 | CQ12: 1 | CS12: 2 | CT12: 3 | CU12: 4 | CV12: 2 | CX12: 1 | CY12: 1 | CZ12: 4 | DB12: 7 | DC12: 07011 | DE12: 66bf519b34c66d259e5554d1 | DF12: 1
A13: 45718.452 | B13: 45718.465 | C13: 0 | D13: 172.56.167.236 | E13: 100 | F13: 1127 | G13: 1 | H13: 45718.465 | I13: R_13ma7vh4uCMKM6d | N13: 40.7035 | O13: -73.9235 | P13: anonymous | Q13: EN | R13: 1 | S13: 66cf6453d66a848ab8d9f3d2 | T13: 2 | U13: 5 | V13: Coop | W13: 2 | Y13: 1 | Z13: 2 | AA13: 2 | AB13: 2 | AC13: 3 | AD13: 2 | AE13: 1 | AF13: 1 | AG13: 2 | AH13: 2 | AI13: 2 | AJ13: 1 | AS13: 4 | AT13: 4 | AU13: 4 | AV13: 4 | AW13: 4 | AX13: 4 | AY13: 4 | AZ13: 4 | BA13: 4 | BB13: 4 | BC13: 3 | BD13: 4 | BE13: 4 | BF13: 3 | BG13: 3 | BH13: 3 | BI13: 3 | BJ13: 3 | BK13: 3 | BL13: 4 | BM13: 4 | BN13: 3 | BO13: 3 | BP13: 3 | BQ13: 3 | BR13: 3 | BS13: 3 | BT13: 2 | BU13: 3 | BV13: 3 | BW13: 3 | BX13: 3 | BY13: 4 | BZ13: 3 | CA13: 3 | CB13: 4 | CC13: 3 | CD13: 3 | CE13: 4 | CF13: 2 | CG13: 1 | CH13: 2 | CI13: 1 | CJ13: 2 | CK13: 3 | CM13: 3 | CN13: 2 | CO13: 4 | CP13: 1 | CQ13: 2 | CS13: 2 | CT13: 2 | CU13: 1 | CV13: 1 | CX13: 1 | CY13: 1 | CZ13: 8 | DA13: Technician | DB13: 3 | DC13: 11220 | DE13: 66cf6453d66a848ab8d9f3d2 | DF13: 1
A14: 45718.462 | B14: 45718.465 | C14: 0 | D14: 151.205.179.101 | E14: 100 | F14: 254 | G14: 1 | H14: 45718.465 | I14: R_3pPvkj1ZuGVGPPX | N14: 40.674 | O14: -73.9701 | P14: anonymous | Q14: EN | R14: 1 | S14: 5e7142237bcd6e05c4128129 | T14: 2 | U14: 2 | W14: 1 | Y14: 1 | Z14: 2 | AA14: 2 | AB14: 2 | AC14: 2 | AD14: 2 | AE14: 1 | AF14: 2 | AG14: 2 | AH14: 2 | AI14: 2 | AJ14: 1 | AS14: 5 | AT14: 4 | AU14: 4 | AV14: 4 | AW14: 2 | AX14: 4 | AY14: 4 | AZ14: 4 | BA14: 5 | BB14: 4 | BC14: 5 | BD14: 3 | BE14: 4 | BF14: 5 | BG14: 3 | BH14: 2 | BI14: 4 | BJ14: 1 | BK14: 2 | BL14: 4 | BM14: 2 | BN14: 1 | BO14: 4 | BP14: 4 | BQ14: 4 | BR14: 2 | BS14: 3 | BT14: 1 | BU14: 4 | BV14: 4 | BW14: 4 | BX14: 2 | BY14: 5 | BZ14: 3 | CA14: 1 | CB14: 4 | CC14: 3 | CD14: 4 | CE14: 4 | CF14: 2 | CG14: 2 | CL14: 4 | CQ14: 1 | CS14: 1 | CT14: 3 | CU14: 1 | CV14: 1 | CX14: 1 | CY14: 1 | CZ14: 2 | DB14: 9 | DC14: 11216 | DE14: 5e7142237bcd6e05c4128129 | DF14: 1
A15: 45718.46 | B15: 45718.465 | C15: 0 | D15: 184.152.224.222 | E15: 100 | F15: 480 | G15: 1 | H15: 45718.465 | I15: R_7cP84dvQgyI2E6d | N15: 40.738 | O15: -73.9858 | P15: anonymous | Q15: EN | R15: 1 | S15: 675793fcd759b993d59985c9 | T15: 2 | U15: 2 | W15: 1 | Y15: 7 | Z15: 2 | AA15: 2 | AB15: 1 | AC15: 2 | AD15: 1 | AE15: 1 | AF15: 2 | AG15: 2 | AH15: 2 | AI15: 2 | AJ15: 1 | AS15: 2 | AT15: 3 | AU15: 4 | AV15: 4 | AW15: 2 | AX15: 4 | AY15: 3 | AZ15: 2 | BA15: 4 | BB15: 3 | BC15: 4 | BD15: 4 | BE15: 3 | BF15: 5 | BG15: 4 | BH15: 1 | BI15: 2 | BJ15: 2 | BK15: 3 | BL15: 2 | BM15: 2 | BN15: 1 | BO15: 1 | BP15: 2 | BQ15: 1 | BR15: 1 | BS15: 3 | BT15: 2 | BU15: 2 | BV15: 4 | BW15: 1 | BX15: 2 | BY15: 4 | BZ15: 3 | CA15: 2 | CB15: 4 | CC15: 4 | CD15: 3 | CE15: 4 | CF15: 3 | CG15: 1 | CL15: 2 | CQ15: 1 | CS15: 1 | CT15: 3 | CU15: 4 | CV15: 2 | CX15: 1 | CY15: 1 | CZ15: 2 | DB15: 4 | DC15: 10009 | DE15: 675793fcd759b993d59985c9 | DF15: 1
A16: 45718.461 | B16: 45718.466 | C16: 0 | D16: 73.193.217.73 | E16: 100 | F16: 389 | G16: 1 | H16: 45718.466 | I16: R_6P2b9DNMuTsK9ON | N16: 40.3162 | O16: -74.5138 | P16: anonymous | Q16: EN | R16: 1 | S16: 67158fc2d3dcb39fb10908dc | T16: 1 | U16: 1 | W16: 4 | X16: Living with family | Y16: 2 | Z16: 2 | AA16: 1 | AB16: 1 | AC16: 5 | AD16: 2 | AE16: 1 | AF16: 2 | AG16: 2 | AH16: 1 | AI16: 1 | AJ16: 2 | AK16: 2 | AL16: 2 | AN16: 2 | AO16: 2 | AP16: 4 | AQ16: Renovations | AR16: 1 | AS16: 3 | AT16: 3 | AU16: 3 | AV16: 3 | AW16: 3 | AX16: 3 | AY16: 1 | AZ16: 3 | BA16: 3 | BB16: 3 | BC16: 3 | BD16: 3 | BE16: 3 | BF16: 1 | BG16: 1 | BH16: 5 | BI16: 5 | BJ16: 5 | BK16: 2 | BL16: 2 | BM16: 5 | BN16: 1 | BO16: 4 | BP16: 5 | BQ16: 5 | BR16: 5 | BS16: 3 | BT16: 3 | BU16: 5 | BV16: 3 | BW16: 3 | BX16: 2 | BY16: 4 | BZ16: 3 | CA16: 2 | CB16: 5 | CC16: 1 | CD16: 1 | CE16: 4 | CF16: 2 | CG16: 1 | CQ16: 2 | CS16: 1 | CT16: 3 | CU16: 1 | CV16: 3 | CX16: 1 | CY16: 1 | CZ16: 2 | DB16: 1 | DC16: 08882 | DD16: You should include questions pertaining to if you live with family and don't own a home yourself but living with family. | DE16: 67158fc2d3dcb39fb10908dc | DF16: 1
A17: 45718.466 | B17: 45718.469 | C17: 0 | D17: 24.89.148.138 | E17: 100 | F17: 257 | G17: 1 | H17: 45718.469 | I17: R_6DU7Ik8ecmUAFlw | N17: 40.6368 | O17: -74.0005 | P17: anonymous | Q17: EN | R17: 1 | S17: 601992d4a11f4e0e0a60ee8a | T17: 2 | U17: 2 | W17: 1 | Y17: 2 | Z17: 2 | AA17: 2 | AB17: 1 | AC17: 2 | AD17: 2 | AE17: 1 | AF17: 2 | AG17: 2 | AH17: 2 | AI17: 2 | AJ17: 1 | AS17: 4 | AT17: 4 | AU17: 4 | AV17: 4 | AW17: 4 | AX17: 4 | AY17: 4 | AZ17: 4 | BA17: 4 | BB17: 4 | BC17: 4 | BD17: 4 | BE17: 4 | BF17: 4 | BG17: 4 | BH17: 2 | BI17: 2 | BJ17: 1 | BK17: 1 | BL17: 1 | BM17: 1 | BN17: 1 | BO17: 1 | BP17: 1 | BQ17: 1 | BR17: 1 | BS17: 3 | BT17: 1 | BU17: 1 | BV17: 3 | BW17: 3 | BX17: 3 | BY17: 3 | BZ17: 3 | CA17: 3 | CB17: 1 | CC17: 1 | CD17: 1 | CE17: 4 | CF17: 3 | CG17: 1 | CL17: 3 | CQ17: 1 | CS17: 2 | CT17: 3 | CU17: 1 | CV17: 1 | CX17: 1 | CY17: 1 | CZ17: 2 | DB17: 9 | DC17: 11221 | DE17: 601992d4a11f4e0e0a60ee8a | DF17: 1
A18: 45718.455 | B18: 45718.469 | C18: 0 | D18: 139.171.134.138 | E18: 100 | F18: 1242 | G18: 1 | H18: 45718.469 | I18: R_3MMOTIVeq9PkM5M | N18: 37.751 | O18: -97.822 | P18: anonymous | Q18: EN | R18: 1 | S18: 6789798be54df25793eaeb00 | T18: 1 | U18: 2 | W18: 1 | Y18: 4 | Z18: 1 | AA18: 1 | AB18: 1 | AC18: 6 | AD18: 3 | AE18: 3 | AF18: 1 | AG18: 1 | AH18: 1 | AI18: 1 | AJ18: 2 | AK18: 2 | AL18: 1 | AN18: 3 | AO18: 1 | AP18: 3 | AR18: 2 | AS18: 3 | AT18: 3 | AU18: 4 | AV18: 3 | AW18: 4 | AX18: 4 | AY18: 4 | AZ18: 4 | BA18: 4 | BB18: 4 | BC18: 4 | BD18: 3 | BE18: 3 | BF18: 3 | BG18: 3 | BH18: 5 | BI18: 4 | BJ18: 4 | BK18: 4 | BL18: 4 | BM18: 4 | BN18: 4 | BO18: 4 | BP18: 4 | BQ18: 4 | BR18: 4 | BS18: 3 | BT18: 4 | BU18: 4 | BV18: 4 | BW18: 3 | BX18: 4 | BY18: 3 | BZ18: 3 | CA18: 3 | CB18: 4 | CC18: 3 | CD18: 3 | CE18: 2 | CF18: 4 | CG18: 2 | CL18: 4 | CQ18: 2 | CS18: 1 | CT18: 3 | CU18: 4 | CV18: 2 | CX18: 1 | CY18: 1 | CZ18: 4 | DB18: 6 | DC18: 44907 | DE18: 6789798be54df25793eaeb00 | DF18: 1
A19: 45718.465 | B19: 45718.469 | C19: 0 | D19: 100.8.77.196 | E19: 100 | F19: 403 | G19: 1 | H19: 45718.469 | I19: R_7g0cInK09cRDHpx | N19: 40.793 | O19: -74.0247 | P19: anonymous | Q19: EN | R19: 1 | S19: 5f84743db0bcc50c63cdb55c | T19: 1 | U19: 1 | W19: 1 | Y19: 1 | Z19: 1 | AA19: 1 | AB19: 1 | AC19: 2 | AD19: 2 | AE19: 1 | AF19: 2 | AG19: 2 | AH19: 2 | AI19: 2 | AJ19: 1 | AS19: 3 | AT19: 2 | AU19: 1 | AV19: 4 | AW19: 3 | AX19: 5 | AY19: 5 | AZ19: 4 | BA19: 2 | BB19: 3 | BC19: 1 | BD19: 2 | BE19: 5 | BF19: 4 | BG19: 4 | BH19: 4 | BI19: 3 | BJ19: 5 | BK19: 1 | BL19: 2 | BM19: 3 | BN19: 2 | BO19: 4 | BP19: 5 | BQ19: 4 | BR19: 5 | BS19: 3 | BT19: 4 | BU19: 4 | BV19: 5 | BW19: 2 | BX19: 3 | BY19: 1 | BZ19: 2 | CA19: 5 | CB19: 3 | CC19: 3 | CD19: 4 | CE19: 3 | CF19: 3 | CG19: 4 | CL19: 5 | CQ19: 2 | CS19: 3 | CT19: 2 | CU19: 3 | CV19: 4 | CX19: 1 | CY19: 1 | CZ19: 6 | DB19: 2 | DC19: 07087 | DE19: 5f84743db0bcc50c63cdb55c | DF19: 1
A20: 45718.461 | B20: 45718.471 | C20: 0 | D20: 38.162.176.234 | E20: 100 | F20: 835 | G20: 1 | H20: 45718.471 | I20: R_6DP4RM82Gh9hPW8 | N20: 42.0943 | O20: -76.8078 | P20: anonymous | Q20: EN | R20: 1 | S20: 6696da58096c2ea4a7fa072d | T20: 2 | U20: 1 | W20: 1 | Y20: 7 | Z20: 2 | AA20: 1 | AB20: 1 | AC20: 3 | AD20: 2 | AE20: 1 | AF20: 2 | AG20: 2 | AH20: 2 | AI20: 2 | AJ20: 1 | AS20: 2 | AT20: 3 | AU20: 2 | AV20: 3 | AW20: 5 | AX20: 5 | AY20: 1 | AZ20: 1 | BA20: 1 | BB20: 1 | BC20: 1 | BD20: 1 | BE20: 1 | BF20: 1 | BG20: 1 | BH20: 2 | BI20: 1 | BJ20: 1 | BK20: 3 | BL20: 5 | BM20: 3 | BN20: 1 | BO20: 2 | BP20: 2 | BQ20: 2 | BR20: 1 | BS20: 3 | BT20: 1 | BU20: 5 | BV20: 5 | BW20: 3 | BX20: 1 | BY20: 5 | BZ20: 3 | CA20: 1 | CB20: 3 | CC20: 3 | CD20: 5 | CE20: 4 | CF20: 1 | CG20: 1 | CL20: 1 | CQ20: 2 | CS20: 1 | CT20: 2 | CU20: 5 | CV20: 3 | CX20: 1 | CY20: 1 | CZ20: 8 | DB20: 4 | DC20: 14845 | DE20: 6696da58096c2ea4a7fa072d | DF20: 1
A21: 45718.465 | B21: 45718.471 | C21: 0 | D21: 68.224.111.189 | E21: 100 | F21: 545 | G21: 1 | H21: 45718.471 | I21: R_71KojA7FhrUeECB | N21: 36.0586 | O21: -115.0803 | P21: anonymous | Q21: EN | R21: 1 | S21: 5e16bce18dffa0c6f76cda9b | T21: 2 | U21: 1 | W21: 2 | Y21: 5 | Z21: 1 | AA21: 1 | AB21: 2 | AC21: 5 | AD21: 3 | AE21: 1 | AF21: 1 | AG21: 1 | AH21: 2 | AI21: 2 | AJ21: 1 | AS21: 4 | AT21: 4 | AU21: 4 | AV21: 4 | AW21: 5 | AX21: 4 | AY21: 5 | AZ21: 5 | BA21: 5 | BB21: 5 | BC21: 4 | BD21: 3 | BE21: 5 | BF21: 5 | BG21: 4 | BH21: 5 | BI21: 3 | BJ21: 4 | BK21: 5 | BL21: 5 | BM21: 5 | BN21: 4 | BO21: 5 | BP21: 5 | BQ21: 5 | BR21: 5 | BS21: 3 | BT21: 4 | BU21: 4 | BV21: 4 | BW21: 4 | BX21: 2 | BY21: 4 | BZ21: 5 | CA21: 2 | CB21: 4 | CC21: 1 | CD21: 1 | CE21: 1 | CF21: 5 | CG21: 2 | CH21: 4 | CI21: 2 | CJ21: 2 | CK21: 4 | CM21: 2 | CN21: 1 | CO21: 3 | CP21: 4 | CQ21: 1 | CS21: 2 | CT21: 3 | CU21: 4 | CV21: 1 | CX21: 1 | CY21: 1 | CZ21: 8 | DA21: management | DB21: 7 | DC21: 14618 | DE21: 5e16bce18dffa0c6f76cda9b | DF21: 1
A22: 45718.466 | B22: 45718.471 | C22: 0 | D22: 73.196.56.216 | E22: 100 | F22: 496 | G22: 1 | H22: 45718.471 | I22: R_6on9aR5nmDgDNkd | N22: 40.8022 | O22: -74.1914 | P22: anonymous | Q22: EN | R22: 1 | S22: 66a919ed216b817cbfd778f2 | T22: 1 | U22: 1 | W22: 1 | Y22: 1 | Z22: 2 | AA22: 2 | AB22: 2 | AC22: 1 | AD22: 2 | AE22: 1 | AF22: 2 | AG22: 2 | AH22: 1 | AI22: 2 | AJ22: 1 | AS22: 4 | AT22: 3 | AU22: 3 | AV22: 3 | AW22: 4 | AX22: 3 | AY22: 2 | AZ22: 2 | BA22: 3 | BB22: 2 | BC22: 4 | BD22: 2 | BE22: 4 | BF22: 1 | BG22: 1 | BH22: 2 | BI22: 3 | BJ22: 2 | BK22: 5 | BL22: 4 | BM22: 4 | BN22: 2 | BO22: 5 | BP22: 5 | BQ22: 3 | BR22: 4 | BS22: 3 | BT22: 4 | BU22: 3 | BV22: 3 | BW22: 2 | BX22: 4 | BY22: 3 | BZ22: 2 | CA22: 2 | CB22: 4 | CC22: 2 | CD22: 3 | CE22: 4 | CF22: 2 | CG22: 1 | CL22: 5 | CQ22: 1 | CS22: 6 | CT22: 2 | CU22: 4 | CV22: 4 | CX22: 1 | CY22: 1 | CZ22: 6 | DB22: 1 | DC22: 07004 | DD22: I'm fortunate (I think) in that while a lot of the surrounding towns flood pretty regularly, where I live specifically is high enough for that not to happen. Occasionally, a little bit of water comes in through the basement floor, but not much. | DE22: 66a919ed216b817cbfd778f2 | DF22: 1
A23: 45718.471 | B23: 45718.477 | C23: 0 | D23: 96.248.57.77 | E23: 100 | F23: 585 | G23: 1 | H23: 45718.477 | I23: R_7nq2DRu7fiymkFC | N23: 41.5404 | O23: -73.8979 | P23: anonymous | Q23: EN | R23: 1 | S23: 67813733b9f7bd24cb2745b4 | T23: 2 | U23: 1 | W23: 1 | Y23: 3 | Z23: 1 | AA23: 1 | AB23: 1 | AC23: 5 | AD23: 5 | AE23: 3 | AF23: 1 | AG23: 2 | AH23: 2 | AI23: 2 | AJ23: 1 | AS23: 2 | AT23: 2 | AU23: 2 | AV23: 2 | AW23: 2 | AX23: 4 | AY23: 2 | AZ23: 2 | BA23: 3 | BB23: 1 | BC23: 1 | BD23: 1 | BE23: 1 | BF23: 1 | BG23: 1 | BH23: 4 | BI23: 2 | BJ23: 2 | BK23: 4 | BL23: 2 | BM23: 2 | BN23: 2 | BO23: 5 | BP23: 5 | BQ23: 2 | BR23: 4 | BS23: 3 | BT23: 4 | BU23: 2 | BV23: 4 | BW23: 2 | BX23: 4 | BY23: 5 | BZ23: 4 | CA23: 5 | CB23: 2 | CC23: 2 | CD23: 3 | CE23: 4 | CF23: 1 | CG23: 2 | CL23: 4 | CQ23: 1 | CS23: 1 | CT23: 2 | CU23: 3 | CV23: 3 | CX23: 1 | CY23: 1 | CZ23: 8 | DA23: home-maker | DB23: 7 | DC23: 12524 | DE23: 67813733b9f7bd24cb2745b4 | DF23: 1
A24: 45718.474 | B24: 45718.479 | C24: 0 | D24: 72.231.237.10 | E24: 100 | F24: 413 | G24: 1 | H24: 45718.479 | I24: R_3QY5GbQPezaOAhP | N24: 42.9685 | O24: -78.7492 | P24: anonymous | Q24: EN | R24: 1 | S24: 666a6f06044ce149fe6523f6 | T24: 2 | U24: 2 | W24: 1 | Y24: 2 | Z24: 2 | AA24: 1 | AB24: 1 | AC24: 1 | AD24: 5 | AE24: 1 | AF24: 2 | AG24: 2 | AH24: 2 | AI24: 2 | AJ24: 1 | AS24: 2 | AT24: 3 | AU24: 3 | AV24: 2 | AW24: 4 | AX24: 4 | AY24: 2 | AZ24: 3 | BA24: 3 | BB24: 4 | BC24: 2 | BD24: 1 | BE24: 3 | BF24: 3 | BG24: 1 | BH24: 4 | BI24: 2 | BJ24: 3 | BK24: 4 | BL24: 2 | BM24: 3 | BN24: 2 | BO24: 4 | BP24: 4 | BQ24: 2 | BR24: 1 | BS24: 3 | BT24: 2 | BU24: 2 | BV24: 4 | BW24: 2 | BX24: 2 | BY24: 4 | BZ24: 2 | CA24: 1 | CB24: 4 | CC24: 2 | CD24: 3 | CE24: 4 | CF24: 4 | CG24: 2 | CL24: 4 | CQ24: 1 | CS24: 4 | CT24: 3 | CU24: 4 | CV24: 1 | CX24: 1 | CY24: 1 | CZ24: 8 | DA24: Personal services | DB24: 1 | DC24: 14221 | DE24: 666a6f06044ce149fe6523f6 | DF24: 1
A25: 45718.476 | B25: 45718.479 | C25: 0 | D25: 204.14.59.48 | E25: 100 | F25: 318 | G25: 1 | H25: 45718.479 | I25: R_6rwHU7X8uxGCBJv | N25: 42.2781 | O25: -74.916 | P25: anonymous | Q25: EN | R25: 1 | S25: 67aca380c880844977f461ef | T25: 2 | U25: 1 | W25: 1 | Y25: 2 | Z25: 2 | AA25: 2 | AB25: 2 | AC25: 3 | AD25: 2 | AE25: 1 | AF25: 1 | AG25: 2 | AH25: 2 | AI25: 2 | AJ25: 1 | AS25: 3 | AT25: 3 | AU25: 4 | AV25: 2 | AW25: 3 | AX25: 2 | AY25: 2 | AZ25: 2 | BA25: 3 | BB25: 2 | BC25: 4 | BD25: 2 | BE25: 3 | BF25: 4 | BG25: 2 | BH25: 2 | BI25: 2 | BJ25: 4 | BK25: 4 | BL25: 4 | BM25: 2 | BN25: 2 | BO25: 2 | BP25: 2 | BQ25: 2 | BR25: 2 | BS25: 3 | BT25: 2 | BU25: 3 | BV25: 4 | BW25: 3 | BX25: 2 | BY25: 4 | BZ25: 2 | CA25: 3 | CB25: 4 | CC25: 2 | CD25: 4 | CE25: 4 | CF25: 1 | CG25: 1 | CL25: 2 | CQ25: 1 | CS25: 1 | CT25: 2 | CU25: 4 | CV25: 1 | CX25: 1 | CY25: 1 | CZ25: 3 | DB25: 1 | DC25: 13838 | DE25: 67aca380c880844977f461ef | DF25: 1
A26: 45718.473 | B26: 45718.48 | C26: 0 | D26: 172.56.226.231 | E26: 100 | F26: 617 | G26: 1 | H26: 45718.48 | I26: R_3YPxnBnw5mKSI1S | N26: 33.4849 | O26: -86.8596 | P26: anonymous | Q26: EN | R26: 1 | S26: 676851db119ea20af1678219 | T26: 2 | U26: 2 | W26: 3 | Y26: 5 | Z26: 2 | AA26: 1 | AB26: 2 | AC26: 5 | AD26: 5 | AE26: 3 | AF26: 1 | AG26: 1 | AH26: 2 | AI26: 2 | AJ26: 1 | AS26: 4 | AT26: 5 | AU26: 4 | AV26: 4 | AW26: 4 | AX26: 4 | AY26: 5 | AZ26: 4 | BA26: 4 | BB26: 5 | BC26: 4 | BD26: 4 | BE26: 4 | BF26: 5 | BG26: 4 | BH26: 4 | BI26: 4 | BJ26: 5 | BK26: 4 | BL26: 4 | BM26: 5 | BN26: 4 | BO26: 4 | BP26: 4 | BQ26: 5 | BR26: 4 | BS26: 3 | BT26: 4 | BU26: 4 | BV26: 4 | BW26: 4 | BX26: 5 | BY26: 4 | BZ26: 4 | CA26: 5 | CB26: 4 | CC26: 4 | CD26: 5 | CE26: 2 | CF26: 4 | CG26: 1 | CH26: 2 | CI26: 1 | CJ26: 4 | CK26: 1 | CM26: 2 | CN26: 3 | CO26: 1 | CP26: 4 | CQ26: 1 | CS26: 3 | CT26: 4 | CU26: 2 | CV26: 2 | CX26: 2 | CY26: 1 | CZ26: 4 | DB26: 7 | DC26: 35249 | DD26: good | DE26: 676851db119ea20af1678219 | DF26: 1
A27: 45718.475 | B27: 45718.48 | C27: 0 | D27: 172.56.167.209 | E27: 100 | F27: 423 | G27: 1 | H27: 45718.48 | I27: R_3uVXn9mwQHPw277 | N27: 40.7035 | O27: -73.9235 | P27: anonymous | Q27: EN | R27: 1 | S27: 664aa32c6cf60f70afed78ea | T27: 2 | U27: 2 | W27: 1 | Y27: 1 | Z27: 2 | AA27: 2 | AB27: 2 | AC27: 1 | AD27: 2 | AE27: 1 | AF27: 2 | AG27: 2 | AH27: 2 | AI27: 2 | AJ27: 1 | AS27: 4 | AT27: 4 | AU27: 4 | AV27: 4 | AW27: 4 | AX27: 4 | AY27: 5 | AZ27: 5 | BA27: 5 | BB27: 5 | BC27: 3 | BD27: 4 | BE27: 4 | BF27: 5 | BG27: 4 | BH27: 4 | BI27: 3 | BJ27: 3 | BK27: 4 | BL27: 2 | BM27: 3 | BN27: 3 | BO27: 3 | BP27: 3 | BQ27: 4 | BR27: 3 | BS27: 3 | BT27: 2 | BU27: 2 | BV27: 3 | BW27: 3 | BX27: 2 | BY27: 3 | BZ27: 2 | CA27: 2 | CB27: 3 | CC27: 3 | CD27: 2 | CE27: 4 | CF27: 2 | CG27: 1 | CL27: 2 | CQ27: 1 | CS27: 3 | CT27: 3 | CU27: 4 | CV27: 1 | CX27: 1 | CY27: 1 | CZ27: 3 | DB27: 10 | DC27: 10024 | DE27: 664aa32c6cf60f70afed78ea | DF27: 1
A28: 45718.474 | B28: 45718.481 | C28: 0 | D28: 68.195.177.206 | E28: 100 | F28: 551 | G28: 1 | H28: 45718.481 | I28: R_755UsLn2waedKj7 | N28: 40.8622 | O28: -73.8902 | P28: anonymous | Q28: EN | R28: 1 | S28: 6711248dbac785b25397ceca | T28: 2 | U28: 2 | W28: 1 | Y28: 7 | Z28: 2 | AA28: 2 | AB28: 1 | AC28: 4 | AD28: 3 | AE28: 3 | AF28: 2 | AG28: 1 | AH28: 2 | AI28: 2 | AJ28: 1 | AS28: 4 | AT28: 4 | AU28: 4 | AV28: 4 | AW28: 3 | AX28: 1 | AY28: 3 | AZ28: 4 | BA28: 4 | BB28: 4 | BC28: 5 | BD28: 4 | BE28: 3 | BF28: 5 | BG28: 4 | BH28: 4 | BI28: 1 | BJ28: 1 | BK28: 1 | BL28: 1 | BM28: 1 | BN28: 1 | BO28: 5 | BP28: 5 | BQ28: 5 | BR28: 5 | BS28: 3 | BT28: 1 | BU28: 5 | BV28: 3 | BW28: 5 | BX28: 1 | BY28: 5 | BZ28: 5 | CA28: 3 | CB28: 3 | CC28: 5 | CD28: 3 | CE28: 4 | CF28: 1 | CG28: 2 | CL28: 5 | CQ28: 1 | CS28: 3 | CT28: 2 | CU28: 2 | CV28: 3 | CX28: 1 | CY28: 1 | CZ28: 8 | DA28: disabled | DB28: 1 | DC28: 10453 | DE28: 6711248dbac785b25397ceca | DF28: 1
A29: 45718.473 | B29: 45718.481 | C29: 0 | D29: 69.142.92.124 | E29: 100 | F29: 690 | G29: 1 | H29: 45718.481 | I29: R_6EvjEiWJWBE2eoK | N29: 39.363 | O29: -74.4324 | P29: anonymous | Q29: EN | R29: 1 | S29: 6737baa242fb816259c039ab | T29: 1 | U29: 2 | W29: 1 | Y29: 1 | Z29: 2 | AA29: 2 | AB29: 2 | AC29: 3 | AD29: 4 | AE29: 1 | AF29: 2 | AG29: 2 | AH29: 2 | AI29: 1 | AJ29: 2 | AK29: 4 | AL29: 1 | AM29: 2012 | AN29: 1 | AO29: 2 | AP29: 5 | AR29: 1 | AS29: 2 | AT29: 3 | AU29: 3 | AV29: 2 | AW29: 2 | AX29: 4 | AY29: 1 | AZ29: 2 | BA29: 3 | BB29: 2 | BC29: 2 | BD29: 2 | BE29: 1 | BF29: 1 | BG29: 1 | BH29: 5 | BI29: 1 | BJ29: 4 | BK29: 5 | BL29: 5 | BM29: 5 | BN29: 3 | BO29: 4 | BP29: 4 | BQ29: 4 | BR29: 2 | BS29: 3 | BT29: 3 | BU29: 3 | BV29: 4 | BW29: 3 | BX29: 4 | BY29: 3 | BZ29: 3 | CA29: 4 | CB29: 4 | CC29: 3 | CD29: 3 | CE29: 4 | CF29: 3 | CG29: 4 | CL29: 4 | CQ29: 1 | CS29: 1 | CT29: 2 | CU29: 3 | CV29: 2 | CX29: 1 | CY29: 1 | CZ29: 8 | DA29: commission | DB29: 3 | DC29: 08401 | DD29: all was good | DE29: 6737baa242fb816259c039ab | DF29: 1
A30: 45718.474 | B30: 45718.482 | C30: 0 | D30: 96.249.220.11 | E30: 100 | F30: 744 | G30: 1 | H30: 45718.482 | I30: R_7JOPBEIUkEaUrM9 | N30: 41.6919 | O30: -73.8642 | P30: anonymous | Q30: EN | R30: 1 | S30: 62b5dbad8247bb91a8ba272a | T30: 2 | U30: 3 | W30: 1 | Y30: 7 | Z30: 1 | AA30: 2 | AB30: 2 | AC30: 1 | AD30: 1 | AE30: 1 | AF30: 2 | AG30: 2 | AH30: 2 | AI30: 1 | AJ30: 2 | AK30: 2 | AL30: 1 | AN30: 3 | AO30: 2 | AP30: 4 | AQ30: The landlord had to replace flooring | AR30: 2 | AS30: 4 | AT30: 4 | AU30: 4 | AV30: 4 | AW30: 4 | AX30: 5 | AY30: 4 | AZ30: 4 | BA30: 4 | BB30: 4 | BC30: 4 | BD30: 4 | BE30: 3 | BF30: 4 | BG30: 3 | BH30: 4 | BI30: 4 | BJ30: 2 | BK30: 2 | BL30: 2 | BM30: 2 | BN30: 2 | BO30: 4 | BP30: 4 | BQ30: 4 | BR30: 4 | BS30: 3 | BT30: 2 | BU30: 3 | BV30: 5 | BW30: 5 | BX30: 3 | BY30: 5 | BZ30: 2 | CA30: 2 | CB30: 5 | CC30: 1 | CD30: 2 | CE30: 4 | CF30: 5 | CG30: 2 | CL30: 5 | CQ30: 1 | CS30: 3 | CT30: 3 | CU30: 4 | CV30: 5 | CW30: mental health disability | CX30: 1 | CY30: 1 | CZ30: 6 | DB30: 1 | DC30: 12601 | DD30: Thank you for allowing me to participate in this study. It was eye opening and has me putting in motion a plan in case of flooding. | DE30: 62b5dbad8247bb91a8ba272a | DF30: 1
A31: 45718.478 | B31: 45718.482 | C31: 0 | D31: 74.78.249.126 | E31: 100 | F31: 334 | G31: 1 | H31: 45718.482 | I31: R_3rOfBtdvOMA2XKg | N31: 43.9813 | O31: -75.6059 | P31: anonymous | Q31: EN | R31: 1 | S31: 570c083272a70300085135fd | T31: 2 | U31: 1 | W31: 1 | Y31: 7 | Z31: 2 | AA31: 1 | AB31: 2 | AC31: 3 | AD31: 3 | AE31: 1 | AF31: 1 | AG31: 2 | AH31: 2 | AI31: 2 | AJ31: 1 | AS31: 5 | AT31: 4 | AU31: 4 | AV31: 5 | AW31: 5 | AX31: 5 | AY31: 3 | AZ31: 2 | BA31: 2 | BB31: 2 | BC31: 3 | BD31: 1 | BE31: 1 | BF31: 3 | BG31: 1 | BH31: 2 | BI31: 1 | BJ31: 1 | BK31: 1 | BL31: 1 | BM31: 1 | BN31: 1 | BO31: 1 | BP31: 1 | BQ31: 1 | BR31: 1 | BS31: 3 | BT31: 1 | BU31: 1 | BV31: 3 | BW31: 1 | BX31: 3 | BY31: 3 | BZ31: 2 | CA31: 3 | CB31: 3 | CC31: 3 | CD31: 3 | CE31: 4 | CF31: 3 | CG31: 1 | CL31: 4 | CQ31: 2 | CS31: 2 | CT31: 2 | CU31: 4 | CV31: 1 | CX31: 1 | CY31: 1 | CZ31: 6 | DB31: 2 | DC31: 13620 | DE31: 570c083272a70300085135fd | DF31: 1
A32: 45718.476 | B32: 45718.483 | C32: 0 | D32: 69.141.19.54 | E32: 100 | F32: 624 | G32: 1 | H32: 45718.483 | I32: R_3bVQpbxDU7tAi4b | N32: 39.7325 | O32: -75.2209 | P32: anonymous | Q32: EN | R32: 1 | S32: 5dea7a7df87f5519e686ff7b | T32: 1 | U32: 1 | W32: 2 | Y32: 1 | Z32: 1 | AA32: 1 | AB32: 2 | AC32: 1 | AD32: 5 | AE32: 1 | AF32: 2 | AG32: 2 | AH32: 1 | AI32: 2 | AJ32: 1 | AS32: 4 | AT32: 4 | AU32: 4 | AV32: 4 | AW32: 4 | AX32: 4 | AY32: 2 | AZ32: 3 | BA32: 4 | BB32: 3 | BC32: 3 | BD32: 3 | BE32: 2 | BF32: 4 | BG32: 2 | BH32: 2 | BI32: 1 | BJ32: 2 | BK32: 4 | BL32: 3 | BM32: 2 | BN32: 2 | BO32: 2 | BP32: 3 | BQ32: 3 | BR32: 2 | BS32: 3 | BT32: 2 | BU32: 2 | BV32: 2 | BW32: 2 | BX32: 3 | BY32: 3 | BZ32: 2 | CA32: 2 | CB32: 2 | CC32: 2 | CD32: 2 | CE32: 4 | CF32: 2 | CG32: 1 | CH32: 2 | CI32: 1 | CJ32: 1 | CK32: 3 | CM32: 2 | CN32: 3 | CO32: 4 | CP32: 1 | CQ32: 1 | CS32: 2 | CT32: 2 | CU32: 4 | CV32: 2 | CX32: 1 | CY32: 1 | CZ32: 2 | DB32: 1 | DC32: 08028 | DE32: 5dea7a7df87f5519e686ff7b | DF32: 1
A33: 45718.471 | B33: 45718.484 | C33: 0 | D33: 72.228.86.33 | E33: 100 | F33: 1157 | G33: 1 | H33: 45718.484 | I33: R_6QJWyNOqVgKoXbN | N33: 43.01 | O33: -76.1496 | P33: anonymous | Q33: EN | R33: 1 | S33: 641397a5ea8f5954ad10fceb | T33: 2 | U33: 5 | V33: Public Housing, townhome type home/connected to others | W33: 1 | Y33: 1 | Z33: 2 | AA33: 2 | AB33: 1 | AC33: 2 | AD33: 5 | AE33: 1 | AF33: 2 | AG33: 2 | AH33: 2 | AI33: 1 | AJ33: 2 | AK33: 4 | AL33: 2 | AN33: 1 | AO33: 2 | AP33: 5 | AR33: 1 | AS33: 2 | AT33: 2 | AU33: 4 | AV33: 4 | AW33: 4 | AX33: 4 | AY33: 2 | AZ33: 2 | BA33: 2 | BB33: 2 | BC33: 2 | BD33: 4 | BE33: 2 | BF33: 4 | BG33: 2 | BH33: 3 | BI33: 4 | BJ33: 2 | BK33: 4 | BL33: 1 | BM33: 2 | BN33: 1 | BO33: 3 | BP33: 2 | BQ33: 4 | BR33: 1 | BS33: 3 | BT33: 2 | BU33: 2 | BV33: 1 | BW33: 1 | BX33: 3 | BY33: 3 | BZ33: 1 | CA33: 3 | CB33: 4 | CC33: 1 | CD33: 3 | CE33: 4 | CF33: 2 | CG33: 1 | CL33: 2 | CQ33: 1 | CS33: 4 | CT33: 3 | CU33: 2 | CV33: 2 | CX33: 1 | CY33: 2 | CZ33: 4 | DB33: 1 | DC33: 13206 | DD33: I experienced a flood in my area approximately 12 years ago. The water level was so high I was worried it would enter my home. Haven't had a bad flood like this since but still experience a small amount of flooding in the complex in which I live, although not high enough to enter my home. | DE33: 641397a5ea8f5954ad10fceb | DF33: 1
A34: 45718.478 | B34: 45718.484 | C34: 0 | D34: 108.41.40.249 | E34: 100 | F34: 552 | G34: 1 | H34: 45718.484 | I34: R_17Btrmfv7tUEZqE | N34: 40.598 | O34: -73.9467 | P34: anonymous | Q34: EN | R34: 1 | S34: 671bdd06525adeea062a1d73 | T34: 2 | U34: 1 | W34: 2 | Y34: 7 | Z34: 2 | AA34: 1 | AB34: 2 | AC34: 4 | AD34: 5 | AE34: 1 | AF34: 1 | AG34: 1 | AH34: 1 | AI34: 1 | AJ34: 2 | AK34: 4 | AL34: 2 | AN34: 2 | AO34: 2 | AP34: 5 | AR34: 1 | AS34: 4 | AT34: 3 | AU34: 3 | AV34: 3 | AW34: 2 | AX34: 5 | AY34: 3 | AZ34: 3 | BA34: 4 | BB34: 4 | BC34: 4 | BD34: 3 | BE34: 2 | BF34: 3 | BG34: 4 | BH34: 4 | BI34: 4 | BJ34: 3 | BK34: 3 | BL34: 5 | BM34: 3 | BN34: 4 | BO34: 4 | BP34: 2 | BQ34: 2 | BR34: 3 | BS34: 3 | BT34: 4 | BU34: 4 | BV34: 3 | BW34: 4 | BX34: 2 | BY34: 3 | BZ34: 3 | CA34: 2 | CB34: 2 | CC34: 3 | CD34: 4 | CE34: 4 | CF34: 2 | CG34: 1 | CH34: 2 | CI34: 1 | CJ34: 3 | CK34: 1 | CM34: 1 | CN34: 2 | CO34: 3 | CP34: 4 | CQ34: 2 | CS34: 1 | CT34: 2 | CU34: 1 | CV34: 2 | CX34: 1 | CY34: 1 | CZ34: 6 | DB34: 1 | DC34: 11235 | DE34: 671bdd06525adeea062a1d73 | DF34: 1
A35: 45718.461 | B35: 45718.485 | C35: 0 | D35: 174.216.243.35 | E35: 100 | F35: 2075 | G35: 1 | H35: 45718.485 | I35: R_3sjN29Bw1Vtk4y7 | N35: 40.8019 | O35: -73.9285 | P35: anonymous | Q35: EN | R35: 1 | S35: 66ada3c630ff8dd4f7d3aeb0 | T35: 2 | U35: 1 | W35: 1 | Y35: 1 | Z35: 2 | AA35: 2 | AB35: 2 | AC35: 1 | AD35: 2 | AE35: 1 | AF35: 2 | AG35: 2 | AH35: 2 | AI35: 2 | AJ35: 1 | AS35: 3 | AT35: 3 | AU35: 3 | AV35: 4 | AW35: 3 | AX35: 3 | AY35: 2 | AZ35: 3 | BA35: 3 | BB35: 4 | BC35: 2 | BD35: 4 | BE35: 4 | BF35: 3 | BG35: 4 | BH35: 2 | BI35: 2 | BJ35: 3 | BK35: 4 | BL35: 3 | BM35: 4 | BN35: 4 | BO35: 2 | BP35: 2 | BQ35: 2 | BR35: 2 | BS35: 3 | BT35: 4 | BU35: 4 | BV35: 3 | BW35: 3 | BX35: 2 | BY35: 3 | BZ35: 2 | CA35: 2 | CB35: 3 | CC35: 2 | CD35: 3 | CE35: 4 | CF35: 2 | CG35: 1 | CL35: 4 | CQ35: 2 | CS35: 1 | CT35: 2 | CU35: 2 | CV35: 1 | CX35: 1 | CY35: 1 | CZ35: 4 | DB35: 5 | DC35: 10018 | DE35: 66ada3c630ff8dd4f7d3aeb0 | DF35: 1
A36: 45718.481 | B36: 45718.485 | C36: 0 | D36: 71.246.106.22 | E36: 100 | F36: 337 | G36: 1 | H36: 45718.485 | I36: R_3zaTegUe1BuBMit | N36: 40.694 | O36: -73.9901 | P36: anonymous | Q36: EN | R36: 1 | S36: 6595826f3295eff742fead3b | T36: 2 | U36: 3 | W36: 2 | Y36: 7 | Z36: 2 | AA36: 2 | AB36: 2 | AC36: 1 | AD36: 2 | AE36: 1 | AF36: 2 | AG36: 2 | AH36: 2 | AI36: 2 | AJ36: 1 | AS36: 4 | AT36: 4 | AU36: 4 | AV36: 4 | AW36: 4 | AX36: 2 | AY36: 4 | AZ36: 3 | BA36: 4 | BB36: 4 | BC36: 3 | BD36: 4 | BE36: 2 | BF36: 5 | BG36: 4 | BH36: 2 | BI36: 2 | BJ36: 2 | BK36: 2 | BL36: 2 | BM36: 2 | BN36: 2 | BO36: 2 | BP36: 3 | BQ36: 2 | BR36: 3 | BS36: 3 | BT36: 2 | BU36: 2 | BV36: 3 | BW36: 2 | BX36: 1 | BY36: 2 | BZ36: 2 | CA36: 1 | CB36: 4 | CC36: 2 | CD36: 1 | CE36: 4 | CF36: 4 | CG36: 1 | CH36: 3 | CI36: 1 | CJ36: 4 | CK36: 3 | CM36: 1 | CN36: 2 | CO36: 3 | CP36: 4 | CQ36: 1 | CS36: 2 | CT36: 4 | CU36: 1 | CV36: 1 | CX36: 1 | CY36: 1 | CZ36: 8 | DA36: technology | DB36: 10 | DC36: 11201 | DE36: 6595826f3295eff742fead3b | DF36: 1
A37: 45718.471 | B37: 45718.485 | C37: 0 | D37: 149.31.161.156 | E37: 100 | F37: 1229 | G37: 1 | H37: 45718.485 | I37: R_7YYPTYiVoTTnwA1 | N37: 40.7359 | O37: -73.9904 | P37: anonymous | Q37: EN | R37: 1 | S37: 61080d1c39e080da7841eade | T37: 2 | U37: 3 | W37: 1 | Y37: 1 | Z37: 2 | AA37: 2 | AB37: 1 | AC37: 2 | AD37: 2 | AE37: 1 | AF37: 2 | AG37: 2 | AH37: 2 | AI37: 2 | AJ37: 1 | AS37: 3 | AT37: 4 | AU37: 3 | AV37: 4 | AW37: 2 | AX37: 2 | AY37: 3 | AZ37: 4 | BA37: 4 | BB37: 4 | BC37: 3 | BD37: 4 | BE37: 4 | BF37: 4 | BG37: 4 | BH37: 3 | BI37: 2 | BJ37: 2 | BK37: 3 | BL37: 4 | BM37: 3 | BN37: 2 | BO37: 3 | BP37: 2 | BQ37: 2 | BR37: 1 | BS37: 3 | BT37: 2 | BU37: 3 | BV37: 4 | BW37: 4 | BX37: 3 | BY37: 4 | BZ37: 3 | CA37: 2 | CB37: 2 | CC37: 2 | CD37: 3 | CE37: 4 | CF37: 3 | CG37: 1 | CL37: 4 | CQ37: 1 | CS37: 1 | CT37: 3 | CU37: 4 | CV37: 5 | CW37: Masters student | CX37: 1 | CY37: 1 | CZ37: 2 | DB37: 10 | DC37: 10005 | DD37: The types of insurance things could be split apart with more clarity. | DE37: 61080d1c39e080da7841eade | DF37: 1
A38: 45718.48 | B38: 45718.486 | C38: 0 | D38: 50.48.153.206 | E38: 100 | F38: 516 | G38: 1 | H38: 45718.486 | I38: R_7qTJpS6nKKFv9w8 | N38: 43.1661 | O38: -77.5555 | P38: anonymous | Q38: EN | R38: 1 | S38: 670d2af9c00f086b201e9f70 | T38: 2 | U38: 1 | W38: 3 | Y38: 1 | Z38: 2 | AA38: 1 | AB38: 1 | AC38: 3 | AD38: 6 | AE38: 3 | AF38: 2 | AG38: 2 | AH38: 2 | AI38: 2 | AJ38: 1 | AS38: 3 | AT38: 3 | AU38: 3 | AV38: 3 | AW38: 3 | AX38: 4 | AY38: 3 | AZ38: 3 | BA38: 3 | BB38: 2 | BC38: 3 | BD38: 3 | BE38: 3 | BF38: 4 | BG38: 4 | BH38: 4 | BI38: 3 | BJ38: 3 | BK38: 3 | BL38: 4 | BM38: 4 | BN38: 3 | BO38: 4 | BP38: 4 | BQ38: 4 | BR38: 4 | BS38: 3 | BT38: 4 | BU38: 4 | BV38: 3 | BW38: 4 | BX38: 3 | BY38: 4 | BZ38: 4 | CA38: 3 | CB38: 4 | CC38: 4 | CD38: 4 | CE38: 4 | CF38: 3 | CG38: 1 | CH38: 4 | CI38: 1 | CJ38: 3 | CK38: 3 | CM38: 2 | CN38: 3 | CO38: 4 | CP38: 1 | CQ38: 1 | CS38: 5 | CT38: 2 | CU38: 4 | CV38: 2 | CX38: 1 | CY38: 1 | CZ38: 6 | DB38: 3 | DC38: 14626 | DE38: 670d2af9c00f086b201e9f70 | DF38: 1
A39: 45718.488 | B39: 45718.491 | C39: 0 | D39: 70.107.93.196 | E39: 100 | F39: 230 | G39: 1 | H39: 45718.491 | I39: R_3LvAO1DtKHvpSS8 | N39: 40.6739 | O39: -73.9358 | P39: anonymous | Q39: EN | R39: 1 | S39: 605363bb60479c6e682fa925 | T39: 2 | U39: 3 | W39: 1 | Y39: 6 | Z39: 1 | AA39: 2 | AB39: 2 | AC39: 2 | AD39: 1 | AE39: 1 | AF39: 2 | AG39: 2 | AH39: 2 | AI39: 2 | AJ39: 1 | AS39: 3 | AT39: 4 | AU39: 2 | AV39: 3 | AW39: 2 | AX39: 3 | AY39: 3 | AZ39: 3 | BA39: 4 | BB39: 3 | BC39: 4 | BD39: 3 | BE39: 3 | BF39: 5 | BG39: 4 | BH39: 2 | BI39: 3 | BJ39: 2 | BK39: 4 | BL39: 4 | BM39: 5 | BN39: 2 | BO39: 2 | BP39: 2 | BQ39: 2 | BR39: 3 | BS39: 3 | BT39: 3 | BU39: 4 | BV39: 2 | BW39: 2 | BX39: 3 | BY39: 4 | BZ39: 3 | CA39: 3 | CB39: 4 | CC39: 3 | CD39: 4 | CE39: 4 | CF39: 2 | CG39: 1 | CL39: 2 | CQ39: 1 | CS39: 1 | CT39: 4 | CU39: 4 | CV39: 1 | CX39: 1 | CY39: 1 | CZ39: 5 | DB39: 10 | DC39: 11225 | DD39: N/a | DE39: 605363bb60479c6e682fa925 | DF39: 1
A40: 45718.485 | B40: 45718.492 | C40: 0 | D40: 24.164.158.70 | E40: 100 | F40: 582 | G40: 1 | H40: 45718.492 | I40: R_6OP7OmWMHTpr5P8 | N40: 40.5468 | O40: -74.1804 | P40: anonymous | Q40: EN | R40: 1 | S40: 63d588deae210f070cd02269 | T40: 2 | U40: 2 | W40: 1 | Y40: 7 | Z40: 1 | AA40: 2 | AB40: 1 | AC40: 1 | AD40: 4 | AE40: 1 | AF40: 2 | AG40: 2 | AH40: 2 | AI40: 2 | AJ40: 1 | AS40: 4 | AT40: 4 | AU40: 5 | AV40: 4 | AW40: 4 | AX40: 3 | AY40: 4 | AZ40: 5 | BA40: 4 | BB40: 4 | BC40: 4 | BD40: 3 | BE40: 4 | BF40: 5 | BG40: 4 | BH40: 2 | BI40: 1 | BJ40: 2 | BK40: 2 | BL40: 2 | BM40: 2 | BN40: 2 | BO40: 1 | BP40: 1 | BQ40: 2 | BR40: 1 | BS40: 3 | BT40: 2 | BU40: 2 | BV40: 3 | BW40: 2 | BX40: 3 | BY40: 3 | BZ40: 3 | CA40: 3 | CB40: 4 | CC40: 4 | CD40: 4 | CE40: 4 | CF40: 2 | CG40: 1 | CL40: 4 | CQ40: 1 | CS40: 2 | CT40: 2 | CU40: 4 | CV40: 3 | CX40: 1 | CY40: 1 | CZ40: 8 | DA40: Disabled | DB40: 1 | DC40: 10306 | DE40: 63d588deae210f070cd02269 | DF40: 1
A41: 45718.489 | B41: 45718.493 | C41: 0 | D41: 70.23.171.147 | E41: 100 | F41: 306 | G41: 1 | H41: 45718.493 | I41: R_50pirYpUDMa35Qi | N41: 40.726 | O41: -73.848 | P41: anonymous | Q41: EN | R41: 1 | S41: 5e48d3d8b26b05361ff522f2 | T41: 2 | U41: 2 | W41: 1 | Y41: 1 | Z41: 2 | AA41: 1 | AB41: 2 | AC41: 4 | AD41: 1 | AE41: 1 | AF41: 2 | AG41: 2 | AH41: 1 | AI41: 2 | AJ41: 1 | AS41: 2 | AT41: 4 | AU41: 4 | AV41: 4 | AW41: 2 | AX41: 2 | AY41: 1 | AZ41: 2 | BA41: 2 | BB41: 3 | BC41: 4 | BD41: 2 | BE41: 2 | BF41: 2 | BG41: 2 | BH41: 4 | BI41: 1 | BJ41: 4 | BK41: 2 | BL41: 2 | BM41: 4 | BN41: 2 | BO41: 5 | BP41: 5 | BQ41: 5 | BR41: 1 | BS41: 3 | BT41: 2 | BU41: 4 | BV41: 5 | BW41: 5 | BX41: 5 | BY41: 5 | BZ41: 5 | CA41: 5 | CB41: 5 | CC41: 2 | CD41: 3 | CE41: 4 | CF41: 2 | CG41: 1 | CL41: 2 | CQ41: 1 | CS41: 2 | CT41: 3 | CU41: 1 | CV41: 2 | CX41: 1 | CY41: 1 | CZ41: 8 | DA41: Data | DB41: 1 | DC41: 11375 | DE41: 5e48d3d8b26b05361ff522f2 | DF41: 1
A42: 45718.484 | B42: 45718.493 | C42: 0 | D42: 69.206.20.45 | E42: 100 | F42: 791 | G42: 1 | H42: 45718.493 | I42: R_7t0rW0XwJZR2yd3 | N42: 41.534 | O42: -74.0492 | P42: anonymous | Q42: EN | R42: 1 | S42: 65c16db75badf1513aea44fd | T42: 2 | U42: 5 | V42: Apartment complex | W42: 1 | Y42: 2 | Z42: 2 | AA42: 2 | AB42: 1 | AC42: 3 | AD42: 2 | AE42: 1 | AF42: 2 | AG42: 2 | AH42: 1 | AI42: 2 | AJ42: 1 | AS42: 3 | AT42: 3 | AU42: 4 | AV42: 3 | AW42: 3 | AX42: 5 | AY42: 2 | AZ42: 2 | BA42: 3 | BB42: 3 | BC42: 3 | BD42: 2 | BE42: 2 | BF42: 2 | BG42: 2 | BH42: 5 | BI42: 3 | BJ42: 1 | BK42: 2 | BL42: 3 | BM42: 3 | BN42: 2 | BO42: 3 | BP42: 4 | BQ42: 5 | BR42: 3 | BS42: 3 | BT42: 2 | BU42: 2 | BV42: 3 | BW42: 3 | BX42: 2 | BY42: 4 | BZ42: 2 | CA42: 3 | CB42: 4 | CC42: 3 | CD42: 2 | CE42: 4 | CF42: 2 | CG42: 1 | CL42: 3 | CQ42: 1 | CS42: 1 | CT42: 1 | CU42: 2 | CV42: 3 | CX42: 2 | CY42: 1 | CZ42: 8 | DB42: 1 | DC42: 12550 | DE42: 65c16db75badf1513aea44fd | DF42: 1
A43: 45718.481 | B43: 45718.493 | C43: 0 | D43: 100.1.247.137 | E43: 100 | F43: 1105 | G43: 1 | H43: 45718.493 | I43: R_63dSvmWVtJ2028V | N43: 40.4441 | O43: -74.13 | P43: anonymous | Q43: EN | R43: 1 | S43: 67a6cbe357e1acaf3c860247 | T43: 1 | U43: 1 | W43: 1 | Y43: 7 | Z43: 1 | AA43: 1 | AB43: 1 | AC43: 1 | AD43: 3 | AE43: 1 | AF43: 2 | AG43: 2 | AH43: 2 | AI43: 1 | AJ43: 2 | AK43: 4 | AL43: 2 | AN43: 1 | AO43: 2 | AP43: 5 | AR43: 1 | AS43: 4 | AT43: 4 | AU43: 4 | AV43: 3 | AW43: 3 | AX43: 4 | AY43: 5 | AZ43: 3 | BA43: 2 | BB43: 3 | BC43: 4 | BD43: 2 | BE43: 2 | BF43: 2 | BG43: 3 | BH43: 2 | BI43: 4 | BJ43: 4 | BK43: 5 | BL43: 5 | BM43: 5 | BN43: 5 | BO43: 2 | BP43: 2 | BQ43: 2 | BR43: 1 | BS43: 3 | BT43: 5 | BU43: 5 | BV43: 1 | BW43: 2 | BX43: 1 | BY43: 1 | BZ43: 1 | CA43: 1 | CB43: 5 | CC43: 1 | CD43: 4 | CE43: 4 | CF43: 3 | CG43: 1 | CL43: 1 | CQ43: 2 | CS43: 3 | CT43: 3 | CU43: 4 | CV43: 2 | CX43: 1 | CY43: 1 | CZ43: 8 | DA43: Waterproofing & mold removal | DB43: 1 | DC43: 07748 | DD43: I have no suggestions for the survey which was very clear. But I've been working in the waterproofing industry for 12 yrs. So I have very rigid opinions on most these quesitons. Ok thanks! | DE43: 67a6cbe357e1acaf3c860247 | DF43: 1
A44: 45718.49 | B44: 45718.494 | C44: 0 | D44: 96.239.106.137 | E44: 100 | F44: 359 | G44: 1 | H44: 45718.494 | I44: R_5j99Vu0T8TcKTy6 | N44: 40.8777 | O44: -73.908 | P44: anonymous | Q44: EN | R44: 1 | S44: 653fb726d2b45b03e76d0c42 | T44: 2 | U44: 3 | W44: 2 | Y44: 2 | Z44: 2 | AA44: 2 | AB44: 2 | AC44: 2 | AD44: 3 | AE44: 1 | AF44: 2 | AG44: 2 | AH44: 2 | AI44: 1 | AJ44: 2 | AK44: 2 | AL44: 1 | AM44: 2022 | AN44: 2 | AO44: 2 | AP44: 4 | AQ44: Additional infrastructure to protect the building | AR44: 2 | AS44: 4 | AT44: 4 | AU44: 4 | AV44: 4 | AW44: 4 | AX44: 3 | AY44: 4 | AZ44: 4 | BA44: 4 | BB44: 4 | BC44: 4 | BD44: 3 | BE44: 4 | BF44: 4 | BG44: 4 | BH44: 4 | BI44: 4 | BJ44: 4 | BK44: 4 | BL44: 3 | BM44: 3 | BN44: 3 | BO44: 3 | BP44: 3 | BQ44: 4 | BR44: 4 | BS44: 3 | BT44: 3 | BU44: 2 | BV44: 3 | BW44: 3 | BX44: 2 | BY44: 3 | BZ44: 3 | CA44: 2 | CB44: 3 | CC44: 2 | CD44: 2 | CE44: 1 | CF44: 4 | CG44: 2 | CH44: 4 | CI44: 2 | CJ44: 3 | CK44: 4 | CM44: 1 | CN44: 2 | CO44: 3 | CP44: 4 | CQ44: 1 | CS44: 2 | CT44: 4 | CU44: 4 | CV44: 1 | CX44: 1 | CY44: 1 | CZ44: 3 | DB44: 10 | DC44: 10463 | DE44: 653fb726d2b45b03e76d0c42 | DF44: 1
A45: 45718.491 | B45: 45718.495 | C45: 0 | D45: 75.203.24.224 | E45: 100 | F45: 380 | G45: 1 | H45: 45718.495 | I45: R_8QooqeWkdeKLik6 | N45: 40.7053 | O45: -74.0866 | P45: anonymous | Q45: EN | R45: 1 | S45: 5fe354a2e44df4fb4634bbc3 | T45: 1 | U45: 3 | W45: 1 | Y45: 7 | Z45: 1 | AA45: 2 | AB45: 2 | AC45: 5 | AD45: 3 | AE45: 1 | AF45: 2 | AG45: 1 | AH45: 2 | AI45: 1 | AJ45: 2 | AK45: 2 | AL45: 2 | AN45: 1 | AO45: 2 | AP45: 5 | AR45: 3 | AS45: 3 | AT45: 4 | AU45: 4 | AV45: 3 | AW45: 3 | AX45: 4 | AY45: 4 | AZ45: 3 | BA45: 4 | BB45: 3 | BC45: 2 | BD45: 2 | BE45: 2 | BF45: 2 | BG45: 2 | BH45: 4 | BI45: 3 | BJ45: 2 | BK45: 4 | BL45: 2 | BM45: 3 | BN45: 2 | BO45: 4 | BP45: 4 | BQ45: 4 | BR45: 4 | BS45: 3 | BT45: 3 | BU45: 3 | BV45: 3 | BW45: 2 | BX45: 2 | BY45: 3 | BZ45: 2 | CA45: 2 | CB45: 4 | CC45: 2 | CD45: 2 | CE45: 4 | CF45: 4 | CG45: 1 | CL45: 4 | CQ45: 1 | CS45: 3 | CT45: 2 | CU45: 5 | CV45: 3 | CX45: 1 | CY45: 2 | CZ45: 8 | DA45: administrative | DB45: 1 | DC45: 07631 | DD45: Thank you for allowing me to participate! | DE45: 5fe354a2e44df4fb4634bbc3 | DF45: 1
A46: 45718.464 | B46: 45718.496 | C46: 0 | D46: 172.59.177.122 | E46: 100 | F46: 2711 | G46: 1 | H46: 45718.496 | I46: R_7iMZLOyxKlpCNRT | N46: 42.7805 | O46: -73.7012 | P46: anonymous | Q46: EN | R46: 1 | S46: 67631dd5e441a4ca93b917f0 | T46: 2 | U46: 1 | W46: 1 | Y46: 7 | Z46: 2 | AA46: 2 | AB46: 2 | AC46: 5 | AD46: 2 | AE46: 4 | AF46: 1 | AG46: 2 | AH46: 1 | AI46: 2 | AJ46: 1 | AS46: 4 | AT46: 4 | AU46: 4 | AV46: 3 | AW46: 4 | AX46: 4 | AY46: 3 | AZ46: 4 | BA46: 4 | BB46: 4 | BC46: 4 | BD46: 3 | BE46: 4 | BF46: 3 | BG46: 2 | BH46: 4 | BI46: 3 | BJ46: 4 | BK46: 4 | BL46: 3 | BM46: 4 | BN46: 4 | BO46: 4 | BP46: 4 | BQ46: 3 | BR46: 2 | BS46: 3 | BT46: 4 | BU46: 4 | BV46: 4 | BW46: 4 | BX46: 4 | BY46: 4 | BZ46: 4 | CA46: 4 | CB46: 3 | CC46: 4 | CD46: 4 | CE46: 1 | CF46: 4 | CG46: 1 | CL46: 4 | CQ46: 1 | CS46: 2 | CT46: 4 | CU46: 2 | CV46: 1 | CX46: 1 | CY46: 1 | CZ46: 3 | DB46: 6 | DC46: 13290 | DD46: The survey effectively addresses key aspects of flood risk and adaptation options, but some questions could benefit from clearer phrasing to ensure respondents fully understand the options. Additionally, the survey could be slightly shortened to make it more concise without sacrificing important details | DE46: 67631dd5e441a4ca93b917f0 | DF46: 1
A47: 45718.493 | B47: 45718.496 | C47: 0 | D47: 174.197.130.240 | E47: 100 | F47: 254 | G47: 1 | H47: 45718.496 | I47: R_3P80Q7wR3YbRZpj | N47: 40.6739 | O47: -73.9358 | P47: anonymous | Q47: EN | R47: 1 | S47: 60dd555e4efdf63bf31106af | T47: 2 | U47: 3 | W47: 1 | Y47: 4 | Z47: 2 | AA47: 2 | AB47: 2 | AC47: 2 | AD47: 1 | AE47: 1 | AF47: 2 | AG47: 2 | AH47: 2 | AI47: 2 | AJ47: 1 | AS47: 3 | AT47: 3 | AU47: 3 | AV47: 2 | AW47: 3 | AX47: 2 | AY47: 1 | AZ47: 1 | BA47: 3 | BB47: 3 | BC47: 3 | BD47: 4 | BE47: 3 | BF47: 4 | BG47: 3 | BH47: 2 | BI47: 3 | BJ47: 2 | BK47: 3 | BL47: 3 | BM47: 2 | BN47: 1 | BO47: 2 | BP47: 2 | BQ47: 2 | BR47: 2 | BS47: 3 | BT47: 2 | BU47: 2 | BV47: 2 | BW47: 1 | BX47: 1 | BY47: 2 | BZ47: 1 | CA47: 1 | CB47: 1 | CC47: 1 | CD47: 1 | CE47: 4 | CF47: 4 | CG47: 1 | CL47: 1 | CQ47: 2 | CS47: 1 | CT47: 4 | CU47: 1 | CV47: 3 | CX47: 1 | CY47: 1 | CZ47: 8 | DA47: Science | DB47: 10 | DC47: 10280 | DE47: 60dd555e4efdf63bf31106af | DF47: 1
A48: 45718.49 | B48: 45718.497 | C48: 0 | D48: 47.17.13.192 | E48: 100 | F48: 577 | G48: 1 | H48: 45718.497 | I48: R_53PXj6clHf60xu9 | N48: 40.8518 | O48: -73.8705 | P48: anonymous | Q48: EN | R48: 1 | S48: 652eba945043ab2f1243b9ca | T48: 2 | U48: 1 | W48: 2 | Y48: 1 | Z48: 2 | AA48: 1 | AB48: 2 | AC48: 6 | AD48: 2 | AE48: 1 | AF48: 2 | AG48: 2 | AH48: 1 | AI48: 2 | AJ48: 1 | AS48: 3 | AT48: 3 | AU48: 3 | AV48: 3 | AW48: 3 | AX48: 3 | AY48: 3 | AZ48: 3 | BA48: 3 | BB48: 3 | BC48: 3 | BD48: 3 | BE48: 3 | BF48: 3 | BG48: 3 | BH48: 1 | BI48: 1 | BJ48: 1 | BK48: 1 | BL48: 2 | BM48: 1 | BN48: 1 | BO48: 2 | BP48: 2 | BQ48: 1 | BR48: 1 | BS48: 3 | BT48: 1 | BU48: 1 | BV48: 3 | BW48: 3 | BX48: 3 | BY48: 2 | BZ48: 3 | CA48: 3 | CB48: 4 | CC48: 3 | CD48: 3 | CE48: 4 | CF48: 3 | CG48: 1 | CH48: 3 | CI48: 1 | CJ48: 3 | CK48: 4 | CM48: 1 | CN48: 2 | CO48: 3 | CP48: 4 | CQ48: 2 | CS48: 1 | CT48: 2 | CU48: 1 | CV48: 3 | CX48: 1 | CY48: 1 | CZ48: 8 | DA48: Unemployed but most recently did retail | DB48: 6 | DC48: 10013 | DD48: I was asked "What is your current employment status?" I put unemployed but also asked what occupation I was in but there was no unemployed option. | DE48: 652eba945043ab2f1243b9ca | DF48: 1
A49: 45718.495 | B49: 45718.499 | C49: 0 | D49: 98.10.77.79 | E49: 100 | F49: 343 | G49: 1 | H49: 45718.499 | I49: R_5c7Mhoiuma4jdsy | N49: 42.7159 | O49: -78.8295 | P49: anonymous | Q49: EN | R49: 1 | S49: 5c0e69d2fb91250001e89f82 | T49: 2 | U49: 2 | W49: 1 | Y49: 1 | Z49: 1 | AA49: 1 | AB49: 1 | AC49: 2 | AD49: 1 | AE49: 1 | AF49: 2 | AG49: 2 | AH49: 2 | AI49: 2 | AJ49: 1 | AS49: 4 | AT49: 4 | AU49: 3 | AV49: 3 | AW49: 2 | AX49: 2 | AY49: 2 | AZ49: 3 | BA49: 3 | BB49: 4 | BC49: 4 | BD49: 4 | BE49: 4 | BF49: 4 | BG49: 4 | BH49: 4 | BI49: 3 | BJ49: 2 | BK49: 2 | BL49: 2 | BM49: 2 | BN49: 4 | BO49: 2 | BP49: 2 | BQ49: 2 | BR49: 2 | BS49: 3 | BT49: 2 | BU49: 4 | BV49: 4 | BW49: 2 | BX49: 2 | BY49: 4 | BZ49: 2 | CA49: 2 | CB49: 4 | CC49: 1 | CD49: 1 | CE49: 4 | CF49: 1 | CG49: 2 | CL49: 2 | CQ49: 2 | CS49: 2 | CT49: 2 | CU49: 4 | CV49: 3 | CX49: 1 | CY49: 1 | CZ49: 8 | DB49: 2 | DC49: 14075 | DE49: 5c0e69d2fb91250001e89f82 | DF49: 1
A50: 45718.495 | B50: 45718.499 | C50: 0 | D50: 174.244.148.203 | E50: 100 | F50: 376 | G50: 1 | H50: 45718.499 | I50: R_8h3aGdIun6YzZvO | N50: 40.5828 | O50: -73.9532 | P50: anonymous | Q50: EN | R50: 1 | S50: 63d7b776a9923fe2a69d36bd | T50: 2 | U50: 1 | W50: 3 | Y50: 1 | Z50: 2 | AA50: 2 | AB50: 2 | AC50: 1 | AD50: 6 | AE50: 4 | AF50: 2 | AG50: 2 | AH50: 2 | AI50: 2 | AJ50: 1 | AS50: 3 | AT50: 3 | AU50: 3 | AV50: 3 | AW50: 3 | AX50: 4 | AY50: 2 | AZ50: 2 | BA50: 2 | BB50: 2 | BC50: 2 | BD50: 3 | BE50: 2 | BF50: 1 | BG50: 1 | BH50: 5 | BI50: 2 | BJ50: 4 | BK50: 4 | BL50: 2 | BM50: 2 | BN50: 2 | BO50: 1 | BP50: 1 | BQ50: 2 | BR50: 1 | BS50: 3 | BT50: 2 | BU50: 2 | BV50: 4 | BW50: 4 | BX50: 4 | BY50: 4 | BZ50: 4 | CA50: 4 | CB50: 4 | CC50: 2 | CD50: 4 | CE50: 4 | CF50: 3 | CG50: 3 | CH50: 2 | CI50: 4 | CJ50: 4 | CK50: 5 | CM50: 1 | CN50: 2 | CO50: 3 | CP50: 4 | CQ50: 2 | CS50: 2 | CT50: 2 | CU50: 2 | CV50: 3 | CX50: 1 | CY50: 2 | CZ50: 8 | DB50: 1 | DC50: 11221 | DE50: 63d7b776a9923fe2a69d36bd | DF50: 1
A51: 45718.491 | B51: 45718.499 | C51: 0 | D51: 70.18.8.227 | E51: 100 | F51: 704 | G51: 1 | H51: 45718.499 | I51: R_32fLxotvaWgjJFH | N51: 40.8231 | O51: -73.9513 | P51: anonymous | Q51: EN | R51: 1 | S51: 664783f1b5de4a3b523d090f | T51: 2 | U51: 2 | W51: 1 | Y51: 1 | Z51: 2 | AA51: 2 | AB51: 2 | AC51: 1 | AD51: 5 | AE51: 2 | AF51: 2 | AG51: 2 | AH51: 2 | AI51: 2 | AJ51: 1 | AS51: 4 | AT51: 4 | AU51: 4 | AV51: 4 | AW51: 4 | AX51: 4 | AY51: 4 | AZ51: 3 | BA51: 4 | BB51: 4 | BC51: 4 | BD51: 2 | BE51: 4 | BF51: 4 | BG51: 2 | BH51: 4 | BI51: 2 | BJ51: 4 | BK51: 4 | BL51: 2 | BM51: 2 | BN51: 2 | BO51: 4 | BP51: 4 | BQ51: 4 | BR51: 2 | BS51: 3 | BT51: 2 | BU51: 2 | BV51: 2 | BW51: 2 | BX51: 2 | BY51: 2 | BZ51: 2 | CA51: 1 | CB51: 2 | CC51: 2 | CD51: 1 | CE51: 4 | CF51: 3 | CG51: 1 | CL51: 4 | CQ51: 2 | CS51: 4 | CT51: 2 | CU51: 4 | CV51: 2 | CX51: 1 | CY51: 1 | CZ51: 2 | DB51: 1 | DC51: 10031 | DD51: regarding trusting the government, I can't being that our President is a CRIminal. Thankfully my area is not considered a flood zone because to rely on him to help is a farce unfortunately. | DE51: 664783f1b5de4a3b523d090f | DF51: 1
A52: 45718.496 | B52: 45718.499 | C52: 0 | D52: 47.230.34.33 | E52: 100 | F52: 253 | G52: 1 | H52: 45718.499 | I52: R_61i0LuSet9yaixq | N52: 40.8691 | O52: -73.9191 | P52: anonymous | Q52: EN | R52: 1 | S52: 5ec403bb09d0e02a060bd5e6 | T52: 2 | U52: 3 | W52: 1 | Y52: 7 | Z52: 2 | AA52: 2 | AB52: 2 | AC52: 2 | AD52: 2 | AE52: 1 | AF52: 2 | AG52: 1 | AH52: 2 | AI52: 2 | AJ52: 1 | AS52: 4 | AT52: 4 | AU52: 3 | AV52: 3 | AW52: 4 | AX52: 4 | AY52: 3 | AZ52: 2 | BA52: 3 | BB52: 3 | BC52: 5 | BD52: 2 | BE52: 3 | BF52: 4 | BG52: 1 | BH52: 4 | BI52: 2 | BJ52: 1 | BK52: 2 | BL52: 4 | BM52: 3 | BN52: 2 | BO52: 4 | BP52: 2 | BQ52: 4 | BR52: 1 | BS52: 3 | BT52: 2 | BU52: 2 | BV52: 3 | BW52: 3 | BX52: 3 | BY52: 4 | BZ52: 2 | CA52: 2 | CB52: 4 | CC52: 1 | CD52: 4 | CE52: 4 | CF52: 4 | CG52: 1 | CL52: 3 | CQ52: 3 | CS52: 1 | CT52: 3 | CU52: 4 | CV52: 1 | CX52: 1 | CY52: 1 | CZ52: 8 | DA52: Nonprofit | DB52: 9 | DC52: 10463 | DE52: 5ec403bb09d0e02a060bd5e6 | DF52: 1
A53: 45718.494 | B53: 45718.5 | C53: 0 | D53: 47.230.67.141 | E53: 100 | F53: 550 | G53: 1 | H53: 45718.5 | I53: R_7x8SaTkJnUeTzUd | N53: 40.8123 | O53: -73.9682 | P53: anonymous | Q53: EN | R53: 1 | S53: 6100b9d86fce4f88e29b5475 | T53: 2 | U53: 2 | W53: 1 | Y53: 7 | Z53: 2 | AA53: 2 | AB53: 2 | AC53: 1 | AD53: 2 | AE53: 1 | AF53: 2 | AG53: 2 | AH53: 2 | AI53: 2 | AJ53: 1 | AS53: 4 | AT53: 4 | AU53: 4 | AV53: 4 | AW53: 2 | AX53: 4 | AY53: 4 | AZ53: 4 | BA53: 4 | BB53: 5 | BC53: 4 | BD53: 4 | BE53: 4 | BF53: 5 | BG53: 4 | BH53: 4 | BI53: 3 | BJ53: 1 | BK53: 2 | BL53: 2 | BM53: 1 | BN53: 1 | BO53: 3 | BP53: 4 | BQ53: 4 | BR53: 2 | BS53: 3 | BT53: 2 | BU53: 2 | BV53: 3 | BW53: 2 | BX53: 2 | BY53: 3 | BZ53: 2 | CA53: 1 | CB53: 3 | CC53: 3 | CD53: 1 | CE53: 4 | CF53: 2 | CG53: 1 | CL53: 3 | CQ53: 1 | CS53: 1 | CT53: 2 | CU53: 4 | CV53: 2 | CX53: 1 | CY53: 1 | CZ53: 6 | DB53: 7 | DC53: 10024 | DE53: 6100b9d86fce4f88e29b5475 | DF53: 1
A54: 45718.493 | B54: 45718.501 | C54: 0 | D54: 172.101.207.201 | E54: 100 | F54: 701 | G54: 1 | H54: 45718.501 | I54: R_31nw2nyL6Jya5GP | N54: 42.9523 | O54: -77.5903 | P54: anonymous | Q54: EN | R54: 1 | S54: 5a973b8235237b0001127686 | T54: 2 | U54: 3 | W54: 1 | Y54: 4 | Z54: 2 | AA54: 2 | AB54: 1 | AC54: 2 | AD54: 1 | AE54: 1 | AF54: 2 | AG54: 1 | AH54: 2 | AI54: 2 | AJ54: 1 | AS54: 2 | AT54: 4 | AU54: 3 | AV54: 4 | AW54: 2 | AX54: 2 | AY54: 2 | AZ54: 2 | BA54: 2 | BB54: 2 | BC54: 4 | BD54: 2 | BE54: 4 | BF54: 4 | BG54: 2 | BH54: 2 | BI54: 2 | BJ54: 2 | BK54: 4 | BL54: 4 | BM54: 4 | BN54: 2 | BO54: 2 | BP54: 2 | BQ54: 2 | BR54: 2 | BS54: 3 | BT54: 2 | BU54: 4 | BV54: 4 | BW54: 3 | BX54: 2 | BY54: 2 | BZ54: 2 | CA54: 2 | CB54: 3 | CC54: 2 | CD54: 2 | CE54: 4 | CF54: 2 | CG54: 1 | CL54: 4 | CQ54: 1 | CS54: 3 | CT54: 2 | CU54: 4 | CV54: 2 | CX54: 1 | CY54: 1 | CZ54: 6 | DB54: 1 | DC54: 14487 | DE54: 5a973b8235237b0001127686 | DF54: 1
A55: 45718.478 | B55: 45718.503 | C55: 0 | D55: 24.228.166.6 | E55: 100 | F55: 2141 | G55: 1 | H55: 45718.503 | I55: R_694Vyyl4lnGaTrO | N55: 40.598 | O55: -73.9467 | P55: anonymous | Q55: EN | R55: 1 | S55: 6755e9121e8abe4946b2c8f6 | T55: 2 | U55: 1 | W55: 1 | Y55: 7 | Z55: 1 | AA55: 2 | AB55: 2 | AC55: 2 | AD55: 4 | AE55: 1 | AF55: 2 | AG55: 2 | AH55: 2 | AI55: 1 | AJ55: 2 | AK55: 1 | AL55: 1 | AM55: 2024 | AN55: 4 | AO55: 1 | AP55: 5 | AR55: 1 | AS55: 4 | AT55: 4 | AU55: 4 | AV55: 3 | AW55: 4 | AX55: 4 | AY55: 3 | AZ55: 4 | BA55: 4 | BB55: 3 | BC55: 4 | BD55: 3 | BE55: 3 | BF55: 4 | BG55: 3 | BH55: 4 | BI55: 4 | BJ55: 4 | BK55: 4 | BL55: 4 | BM55: 4 | BN55: 4 | BO55: 3 | BP55: 4 | BQ55: 4 | BR55: 4 | BS55: 3 | BT55: 4 | BU55: 4 | BV55: 4 | BW55: 4 | BX55: 3 | BY55: 4 | BZ55: 3 | CA55: 3 | CB55: 4 | CC55: 3 | CD55: 4 | CE55: 1 | CF55: 4 | CG55: 4 | CL55: 4 | CQ55: 2 | CS55: 3 | CT55: 2 | CU55: 3 | CV55: 1 | CX55: 1 | CY55: 1 | CZ55: 2 | DB55: 4 | DC55: 11224 | DE55: 6755e9121e8abe4946b2c8f6 | DF55: 1
A56: 45718.498 | B56: 45718.503 | C56: 0 | D56: 104.162.165.132 | E56: 100 | F56: 447 | G56: 1 | H56: 45718.503 | I56: R_1XhuFEROzh1UpAj | N56: 40.726 | O56: -73.848 | P56: anonymous | Q56: EN | R56: 1 | S56: 6110888158573651261c3100 | T56: 2 | U56: 3 | W56: 1 | Y56: 1 | Z56: 2 | AA56: 2 | AB56: 2 | AC56: 3 | AD56: 4 | AE56: 1 | AF56: 2 | AG56: 1 | AH56: 2 | AI56: 1 | AJ56: 2 | AK56: 3 | AL56: 2 | AN56: 2 | AO56: 2 | AP56: 5 | AR56: 1 | AS56: 3 | AT56: 4 | AU56: 4 | AV56: 4 | AW56: 4 | AX56: 4 | AY56: 4 | AZ56: 4 | BA56: 4 | BB56: 3 | BC56: 4 | BD56: 3 | BE56: 4 | BF56: 4 | BG56: 3 | BH56: 4 | BI56: 4 | BJ56: 4 | BK56: 4 | BL56: 3 | BM56: 3 | BN56: 3 | BO56: 4 | BP56: 4 | BQ56: 4 | BR56: 4 | BS56: 3 | BT56: 3 | BU56: 3 | BV56: 4 | BW56: 4 | BX56: 3 | BY56: 4 | BZ56: 4 | CA56: 3 | CB56: 4 | CC56: 4 | CD56: 3 | CE56: 4 | CF56: 4 | CG56: 2 | CL56: 3 | CQ56: 1 | CS56: 4 | CT56: 2 | CU56: 4 | CV56: 2 | CX56: 1 | CY56: 1 | CZ56: 3 | DB56: 9 | DC56: 11374 | DE56: 6110888158573651261c3100 | DF56: 1
A57: 45718.499 | B57: 45718.503 | C57: 0 | D57: 72.69.128.86 | E57: 100 | F57: 346 | G57: 1 | H57: 45718.503 | I57: R_1iEz8zQG7u8eJuM | N57: 40.7252 | O57: -73.944 | P57: anonymous | Q57: EN | R57: 1 | S57: 65614c86be0b8460a11d0b64 | T57: 2 | U57: 1 | W57: 1 | Y57: 1 | Z57: 2 | AA57: 2 | AB57: 2 | AC57: 6 | AD57: 3 | AE57: 1 | AF57: 2 | AG57: 2 | AH57: 2 | AI57: 2 | AJ57: 1 | AS57: 3 | AT57: 3 | AU57: 2 | AV57: 2 | AW57: 2 | AX57: 2 | AY57: 3 | AZ57: 5 | BA57: 4 | BB57: 4 | BC57: 3 | BD57: 1 | BE57: 3 | BF57: 4 | BG57: 2 | BH57: 1 | BI57: 1 | BJ57: 1 | BK57: 1 | BL57: 1 | BM57: 2 | BN57: 1 | BO57: 1 | BP57: 1 | BQ57: 1 | BR57: 1 | BS57: 3 | BT57: 2 | BU57: 2 | BV57: 1 | BW57: 3 | BX57: 2 | BY57: 2 | BZ57: 2 | CA57: 4 | CB57: 3 | CC57: 1 | CD57: 2 | CE57: 4 | CF57: 2 | CG57: 1 | CL57: 3 | CQ57: 2 | CS57: 2 | CT57: 3 | CU57: 4 | CV57: 2 | CX57: 1 | CY57: 1 | CZ57: 2 | DB57: 1 | DC57: 11222 | DE57: 65614c86be0b8460a11d0b64 | DF57: 1
A58: 45718.5 | B58: 45718.503 | C58: 0 | D58: 172.56.167.14 | E58: 100 | F58: 297 | G58: 1 | H58: 45718.503 | I58: R_6OlbgPzgaOVdIMZ | N58: 40.7035 | O58: -73.9235 | P58: anonymous | Q58: EN | R58: 1 | S58: 674f50d07a3595827b1e2ed7 | T58: 2 | U58: 3 | W58: 1 | Y58: 1 | Z58: 2 | AA58: 2 | AB58: 2 | AC58: 1 | AD58: 1 | AE58: 1 | AF58: 2 | AG58: 2 | AH58: 2 | AI58: 2 | AJ58: 1 | AS58: 2 | AT58: 2 | AU58: 2 | AV58: 2 | AW58: 2 | AX58: 2 | AY58: 1 | AZ58: 3 | BA58: 2 | BB58: 2 | BC58: 2 | BD58: 2 | BE58: 2 | BF58: 3 | BG58: 2 | BH58: 3 | BI58: 4 | BJ58: 2 | BK58: 3 | BL58: 2 | BM58: 3 | BN58: 1 | BO58: 4 | BP58: 4 | BQ58: 3 | BR58: 1 | BS58: 3 | BT58: 2 | BU58: 2 | BV58: 4 | BW58: 3 | BX58: 3 | BY58: 4 | BZ58: 2 | CA58: 2 | CB58: 3 | CC58: 3 | CD58: 3 | CE58: 4 | CF58: 2 | CG58: 5 | CL58: 4 | CQ58: 2 | CS58: 3 | CT58: 5 | CU58: 4 | CV58: 3 | CX58: 1 | CY58: 1 | CZ58: 3 | DB58: 9 | DC58: 10036 | DE58: 674f50d07a3595827b1e2ed7 | DF58: 1
A59: 45718.501 | B59: 45718.504 | C59: 0 | D59: 173.71.124.182 | E59: 100 | F59: 290 | G59: 1 | H59: 45718.504 | I59: R_1787vCC90hPdkbm | N59: 40.3173 | O59: -74.6199 | P59: anonymous | Q59: EN | R59: 1 | S59: 60fd6d5cdc912471a22c5eba | T59: 1 | U59: 3 | W59: 1 | Y59: 7 | Z59: 1 | AA59: 1 | AB59: 2 | AC59: 2 | AD59: 1 | AE59: 1 | AF59: 2 | AG59: 2 | AH59: 2 | AI59: 2 | AJ59: 1 | AS59: 3 | AT59: 3 | AU59: 4 | AV59: 3 | AW59: 3 | AX59: 3 | AY59: 2 | AZ59: 2 | BA59: 3 | BB59: 2 | BC59: 2 | BD59: 3 | BE59: 2 | BF59: 2 | BG59: 2 | BH59: 2 | BI59: 2 | BJ59: 2 | BK59: 2 | BL59: 2 | BM59: 3 | BN59: 2 | BO59: 2 | BP59: 2 | BQ59: 2 | BR59: 2 | BS59: 3 | BT59: 2 | BU59: 2 | BV59: 3 | BW59: 2 | BX59: 2 | BY59: 4 | BZ59: 2 | CA59: 2 | CB59: 4 | CC59: 2 | CD59: 2 | CE59: 4 | CF59: 3 | CG59: 1 | CL59: 3 | CQ59: 1 | CS59: 1 | CT59: 3 | CU59: 4 | CV59: 3 | CX59: 1 | CY59: 1 | CZ59: 2 | DB59: 1 | DC59: 08536 | DE59: 60fd6d5cdc912471a22c5eba | DF59: 1
A60: 45718.501 | B60: 45718.506 | C60: 0 | D60: 72.89.245.93 | E60: 100 | F60: 393 | G60: 1 | H60: 45718.506 | I60: R_39HgTwpthzUDdzX | N60: 40.8271 | O60: -73.9359 | P60: anonymous | Q60: EN | R60: 1 | S60: 67671599195d8599d85de189 | T60: 2 | U60: 4 | W60: 1 | Y60: 7 | Z60: 2 | AA60: 1 | AB60: 2 | AC60: 5 | AD60: 4 | AE60: 1 | AF60: 2 | AG60: 1 | AH60: 2 | AI60: 2 | AJ60: 1 | AS60: 4 | AT60: 4 | AU60: 4 | AV60: 4 | AW60: 4 | AX60: 4 | AY60: 4 | AZ60: 4 | BA60: 4 | BB60: 4 | BC60: 4 | BD60: 4 | BE60: 4 | BF60: 4 | BG60: 4 | BH60: 4 | BI60: 4 | BJ60: 4 | BK60: 2 | BL60: 2 | BM60: 2 | BN60: 2 | BO60: 2 | BP60: 2 | BQ60: 3 | BR60: 2 | BS60: 3 | BT60: 4 | BU60: 4 | BV60: 4 | BW60: 4 | BX60: 4 | BY60: 4 | BZ60: 4 | CA60: 4 | CB60: 4 | CC60: 4 | CD60: 4 | CE60: 2 | CF60: 4 | CG60: 1 | CL60: 4 | CQ60: 1 | CS60: 4 | CT60: 4 | CU60: 4 | CV60: 1 | CX60: 1 | CY60: 1 | CZ60: 3 | DB60: 6 | DC60: 10003 | DE60: 67671599195d8599d85de189 | DF60: 1
A61: 45718.487 | B61: 45718.508 | C61: 0 | D61: 66.108.16.191 | E61: 100 | F61: 1812 | G61: 1 | H61: 45718.508 | I61: R_7wTnBhbxNg3i98t | N61: 40.8527 | O61: -73.9383 | P61: anonymous | Q61: EN | R61: 1 | S61: 63026053812fe400f2929701 | T61: 2 | U61: 3 | W61: 1 | Y61: 1 | Z61: 1 | AA61: 2 | AB61: 2 | AC61: 1 | AD61: 4 | AE61: 1 | AF61: 2 | AG61: 2 | AH61: 2 | AI61: 2 | AJ61: 1 | AS61: 3 | AT61: 2 | AU61: 2 | AV61: 2 | AW61: 1 | AX61: 4 | AY61: 2 | AZ61: 2 | BA61: 3 | BB61: 2 | BC61: 2 | BD61: 1 | BE61: 1 | BF61: 4 | BG61: 1 | BH61: 2 | BI61: 1 | BJ61: 1 | BK61: 2 | BL61: 1 | BM61: 1 | BN61: 1 | BO61: 4 | BP61: 3 | BQ61: 4 | BR61: 3 | BS61: 3 | BT61: 1 | BU61: 1 | BV61: 5 | BW61: 5 | BX61: 3 | BY61: 5 | BZ61: 5 | CA61: 4 | CB61: 5 | CC61: 5 | CD61: 3 | CE61: 4 | CF61: 3 | CG61: 1 | CL61: 2 | CQ61: 2 | CS61: 2 | CT61: 2 | CU61: 3 | CV61: 3 | CX61: 1 | CY61: 1 | CZ61: 8 | DB61: 1 | DC61: 10034 | DE61: 63026053812fe400f2929701 | DF61: 1
A62: 45718.504 | B62: 45718.509 | C62: 0 | D62: 24.188.225.149 | E62: 100 | F62: 462 | G62: 1 | H62: 45718.509 | I62: R_3EVWr752VPSwGad | N62: 40.6877 | O62: -73.9267 | P62: anonymous | Q62: EN | R62: 1 | S62: 5b21259ce5cd900001125a0b | T62: 2 | U62: 2 | W62: 1 | Y62: 6 | Z62: 1 | AA62: 2 | AB62: 1 | AC62: 2 | AD62: 2 | AE62: 1 | AF62: 2 | AG62: 2 | AH62: 2 | AI62: 2 | AJ62: 1 | AS62: 4 | AT62: 4 | AU62: 4 | AV62: 4 | AW62: 4 | AX62: 5 | AY62: 2 | AZ62: 3 | BA62: 3 | BB62: 3 | BC62: 1 | BD62: 1 | BE62: 3 | BF62: 5 | BG62: 2 | BH62: 2 | BI62: 3 | BJ62: 1 | BK62: 2 | BL62: 2 | BM62: 2 | BN62: 1 | BO62: 1 | BP62: 1 | BQ62: 1 | BR62: 1 | BS62: 3 | BT62: 1 | BU62: 3 | BV62: 2 | BW62: 3 | BX62: 2 | BY62: 2 | BZ62: 2 | CA62: 2 | CB62: 1 | CC62: 1 | CD62: 1 | CE62: 4 | CF62: 1 | CG62: 1 | CL62: 1 | CQ62: 2 | CS62: 1 | CT62: 4 | CU62: 4 | CV62: 1 | CX62: 1 | CY62: 1 | CZ62: 3 | DB62: 10 | DC62: 11221 | DE62: 5b21259ce5cd900001125a0b | DF62: 1
A63: 45718.504 | B63: 45718.509 | C63: 0 | D63: 142.105.168.153 | E63: 100 | F63: 508 | G63: 1 | H63: 45718.509 | I63: R_5LmlQcTOw8YQIUN | N63: 43.0449 | O63: -78.8762 | P63: anonymous | Q63: EN | R63: 1 | S63: 6332274d72eff2df47171a78 | T63: 2 | U63: 1 | W63: 1 | Y63: 1 | Z63: 1 | AA63: 1 | AB63: 2 | AC63: 1 | AD63: 2 | AE63: 1 | AF63: 2 | AG63: 2 | AH63: 2 | AI63: 2 | AJ63: 1 | AS63: 4 | AT63: 4 | AU63: 4 | AV63: 4 | AW63: 4 | AX63: 3 | AY63: 3 | AZ63: 4 | BA63: 4 | BB63: 5 | BC63: 5 | BD63: 3 | BE63: 5 | BF63: 2 | BG63: 3 | BH63: 1 | BI63: 1 | BJ63: 2 | BK63: 4 | BL63: 4 | BM63: 4 | BN63: 3 | BO63: 1 | BP63: 1 | BQ63: 1 | BR63: 1 | BS63: 3 | BT63: 4 | BU63: 4 | BV63: 2 | BW63: 2 | BX63: 3 | BY63: 2 | BZ63: 2 | CA63: 1 | CB63: 3 | CC63: 3 | CD63: 2 | CE63: 4 | CF63: 1 | CG63: 1 | CL63: 2 | CQ63: 2 | CS63: 4 | CT63: 2 | CU63: 4 | CV63: 2 | CX63: 1 | CY63: 1 | CZ63: 2 | DB63: 1 | DC63: 14304 | DD63: The question about if I knew how to find info on flooding was worded oddly. | DE63: 6332274d72eff2df47171a78 | DF63: 1
A64: 45718.507 | B64: 45718.51 | C64: 0 | D64: 24.190.223.137 | E64: 100 | F64: 343 | G64: 1 | H64: 45718.511 | I64: R_3CJndy6xRz2FXDt | N64: 40.6221 | O64: -73.981 | P64: anonymous | Q64: EN | R64: 1 | S64: 5c07023eb70ffa00014873c7 | T64: 2 | U64: 2 | W64: 2 | Y64: 1 | Z64: 2 | AA64: 2 | AB64: 2 | AC64: 4 | AD64: 5 | AE64: 3 | AF64: 2 | AG64: 2 | AH64: 1 | AI64: 2 | AJ64: 1 | AS64: 3 | AT64: 3 | AU64: 3 | AV64: 3 | AW64: 4 | AX64: 2 | AY64: 3 | AZ64: 4 | BA64: 4 | BB64: 3 | BC64: 4 | BD64: 1 | BE64: 3 | BF64: 5 | BG64: 2 | BH64: 2 | BI64: 1 | BJ64: 1 | BK64: 1 | BL64: 1 | BM64: 1 | BN64: 1 | BO64: 1 | BP64: 1 | BQ64: 1 | BR64: 1 | BS64: 3 | BT64: 1 | BU64: 1 | BV64: 4 | BW64: 4 | BX64: 4 | BY64: 2 | BZ64: 2 | CA64: 3 | CB64: 4 | CC64: 3 | CD64: 4 | CE64: 4 | CF64: 1 | CG64: 1 | CH64: 1 | CI64: 1 | CJ64: 4 | CK64: 2 | CM64: 4 | CN64: 3 | CO64: 1 | CP64: 2 | CQ64: 2 | CS64: 2 | CT64: 3 | CU64: 1 | CV64: 1 | CX64: 1 | CY64: 2 | CZ64: 3 | DB64: 2 | DC64: 11214 | DE64: 5c07023eb70ffa00014873c7 | DF64: 1
A65: 45718.509 | B65: 45718.512 | C65: 0 | D65: 108.46.24.210 | E65: 100 | F65: 232 | G65: 1 | H65: 45718.512 | I65: R_5YUSG9SLXgMG0j7 | N65: 40.8 | O65: -73.9763 | P65: anonymous | Q65: EN | R65: 1 | S65: 668ebf594982c57c983cd910 | T65: 2 | U65: 2 | W65: 1 | Y65: 1 | Z65: 2 | AA65: 2 | AB65: 2 | AC65: 2 | AD65: 4 | AE65: 1 | AF65: 2 | AG65: 2 | AH65: 1 | AI65: 2 | AJ65: 1 | AS65: 4 | AT65: 4 | AU65: 4 | AV65: 4 | AW65: 4 | AX65: 4 | AY65: 3 | AZ65: 4 | BA65: 4 | BB65: 4 | BC65: 4 | BD65: 3 | BE65: 4 | BF65: 2 | BG65: 2 | BH65: 1 | BI65: 1 | BJ65: 1 | BK65: 1 | BL65: 5 | BM65: 3 | BN65: 1 | BO65: 1 | BP65: 1 | BQ65: 1 | BR65: 1 | BS65: 3 | BT65: 1 | BU65: 1 | BV65: 1 | BW65: 1 | BX65: 1 | BY65: 2 | BZ65: 2 | CA65: 1 | CB65: 1 | CC65: 1 | CD65: 1 | CE65: 4 | CF65: 4 | CG65: 1 | CL65: 1 | CQ65: 1 | CS65: 6 | CT65: 3 | CU65: 4 | CV65: 1 | CX65: 1 | CY65: 1 | CZ65: 4 | DB65: 10 | DC65: 10026 | DE65: 668ebf594982c57c983cd910 | DF65: 1
A66: 45718.496 | B66: 45718.512 | C66: 0 | D66: 92.112.62.188 | E66: 100 | F66: 1396 | G66: 1 | H66: 45718.512 | I66: R_5BwWRApbmuRjI7n | N66: 40.7126 | O66: -74.0066 | P66: anonymous | Q66: EN | R66: 1 | S66: 6792348d1f58f1ced4a5f962 | T66: 2 | U66: 3 | W66: 1 | Y66: 7 | Z66: 1 | AA66: 2 | AB66: 2 | AC66: 3 | AD66: 3 | AE66: 2 | AF66: 2 | AG66: 1 | AH66: 2 | AI66: 2 | AJ66: 1 | AS66: 3 | AT66: 4 | AU66: 2 | AV66: 3 | AW66: 4 | AX66: 2 | AY66: 3 | AZ66: 3 | BA66: 3 | BB66: 4 | BC66: 4 | BD66: 4 | BE66: 3 | BF66: 4 | BG66: 3 | BH66: 4 | BI66: 3 | BJ66: 4 | BK66: 3 | BL66: 4 | BM66: 3 | BN66: 3 | BO66: 4 | BP66: 4 | BQ66: 3 | BR66: 4 | BS66: 3 | BT66: 4 | BU66: 3 | BV66: 4 | BW66: 4 | BX66: 3 | BY66: 2 | BZ66: 4 | CA66: 2 | CB66: 4 | CC66: 3 | CD66: 4 | CE66: 4 | CF66: 4 | CG66: 2 | CL66: 4 | CQ66: 1 | CS66: 2 | CT66: 4 | CU66: 4 | CV66: 1 | CX66: 1 | CY66: 1 | CZ66: 8 | DA66: Software engineering | DB66: 10 | DC66: 10305 | DD66: It was a great survey helped understand more about floods and to be able to make decisions. | DE66: 6792348d1f58f1ced4a5f962 | DF66: 1
A67: 45718.508 | B67: 45718.512 | C67: 0 | D67: 71.187.241.230 | E67: 100 | F67: 426 | G67: 1 | H67: 45718.513 | I67: R_5lAkwLcAWaxxAbW | N67: 40.9129 | O67: -74.1627 | P67: anonymous | Q67: EN | R67: 1 | S67: 5ac5260dfa3b4e0001736dd3 | T67: 1 | U67: 2 | W67: 1 | Y67: 7 | Z67: 2 | AA67: 1 | AB67: 2 | AC67: 3 | AD67: 4 | AE67: 1 | AF67: 2 | AG67: 2 | AH67: 2 | AI67: 2 | AJ67: 1 | AS67: 2 | AT67: 3 | AU67: 3 | AV67: 3 | AW67: 2 | AX67: 4 | AY67: 1 | AZ67: 2 | BA67: 3 | BB67: 1 | BC67: 2 | BD67: 1 | BE67: 2 | BF67: 3 | BG67: 1 | BH67: 3 | BI67: 2 | BJ67: 2 | BK67: 4 | BL67: 4 | BM67: 4 | BN67: 3 | BO67: 4 | BP67: 3 | BQ67: 3 | BR67: 2 | BS67: 3 | BT67: 3 | BU67: 3 | BV67: 3 | BW67: 3 | BX67: 3 | BY67: 4 | BZ67: 3 | CA67: 2 | CB67: 4 | CC67: 3 | CD67: 4 | CE67: 4 | CF67: 3 | CG67: 1 | CL67: 3 | CQ67: 2 | CS67: 2 | CT67: 2 | CU67: 3 | CV67: 2 | CX67: 1 | CY67: 1 | CZ67: 8 | DA67: automotive | DB67: 2 | DC67: 07013 | DE67: 5ac5260dfa3b4e0001736dd3 | DF67: 1
A68: 45718.501 | B68: 45718.513 | C68: 0 | D68: 172.101.241.154 | E68: 100 | F68: 1051 | G68: 1 | H68: 45718.513 | I68: R_2RQzPDfzBBFqLQR | N68: 43.2318 | O68: -77.6607 | P68: anonymous | Q68: EN | R68: 1 | S68: 565b2be310593c000bff9695 | T68: 2 | U68: 1 | W68: 4 | X68: Live with family | Y68: 1 | Z68: 2 | AA68: 2 | AB68: 1 | AC68: 1 | AD68: 6 | AE68: 1 | AF68: 2 | AG68: 2 | AH68: 2 | AI68: 2 | AJ68: 1 | AS68: 2 | AT68: 2 | AU68: 3 | AV68: 2 | AW68: 1 | AX68: 1 | AY68: 1 | AZ68: 1 | BA68: 2 | BB68: 1 | BC68: 4 | BD68: 1 | BE68: 2 | BF68: 3 | BG68: 1 | BH68: 1 | BI68: 1 | BJ68: 1 | BK68: 1 | BL68: 1 | BM68: 1 | BN68: 1 | BO68: 2 | BP68: 2 | BQ68: 1 | BR68: 1 | BS68: 3 | BT68: 1 | BU68: 1 | BV68: 2 | BW68: 2 | BX68: 1 | BY68: 2 | BZ68: 2 | CA68: 1 | CB68: 1 | CC68: 1 | CD68: 3 | CE68: 4 | CF68: 4 | CG68: 1 | CQ68: 2 | CS68: 2 | CT68: 2 | CU68: 4 | CV68: 3 | CX68: 1 | CY68: 2 | CZ68: 8 | DA68: N/A - Unemployed | DB68: 1 | DC68: 14616 | DE68: 565b2be310593c000bff9695 | DF68: 1
A69: 45718.508 | B69: 45718.513 | C69: 0 | D69: 172.56.161.230 | E69: 100 | F69: 468 | G69: 1 | H69: 45718.513 | I69: R_5e9QBw54fgCg2ne | N69: 40.6643 | O69: -73.9763 | P69: anonymous | Q69: EN | R69: 1 | S69: 66fb3cda7fd78d0d38e1440f | T69: 2 | U69: 2 | W69: 1 | Y69: 2 | Z69: 2 | AA69: 2 | AB69: 2 | AC69: 1 | AD69: 3 | AE69: 2 | AF69: 2 | AG69: 2 | AH69: 2 | AI69: 2 | AJ69: 1 | AS69: 3 | AT69: 3 | AU69: 2 | AV69: 2 | AW69: 2 | AX69: 3 | AY69: 2 | AZ69: 2 | BA69: 3 | BB69: 3 | BC69: 2 | BD69: 2 | BE69: 2 | BF69: 3 | BG69: 3 | BH69: 3 | BI69: 3 | BJ69: 2 | BK69: 3 | BL69: 3 | BM69: 2 | BN69: 2 | BO69: 3 | BP69: 3 | BQ69: 3 | BR69: 3 | BS69: 3 | BT69: 3 | BU69: 2 | BV69: 3 | BW69: 2 | BX69: 3 | BY69: 3 | BZ69: 3 | CA69: 3 | CB69: 3 | CC69: 3 | CD69: 3 | CE69: 4 | CF69: 3 | CG69: 1 | CL69: 2 | CQ69: 2 | CS69: 3 | CT69: 2 | CU69: 2 | CV69: 2 | CX69: 1 | CY69: 1 | CZ69: 6 | DB69: 2 | DC69: 11226 | DE69: 66fb3cda7fd78d0d38e1440f | DF69: 1
A70: 45718.509 | B70: 45718.514 | C70: 0 | D70: 108.29.13.127 | E70: 100 | F70: 426 | G70: 1 | H70: 45718.514 | I70: R_2fv3OgtARcBVM72 | N70: 40.7547 | O70: -73.9614 | P70: anonymous | Q70: EN | R70: 1 | S70: 674e450b1a4a8e2d4e8d7e7c | T70: 2 | U70: 2 | W70: 1 | Y70: 6 | Z70: 2 | AA70: 2 | AB70: 2 | AC70: 1 | AD70: 2 | AE70: 1 | AF70: 2 | AG70: 2 | AH70: 1 | AI70: 2 | AJ70: 1 | AS70: 4 | AT70: 4 | AU70: 4 | AV70: 4 | AW70: 4 | AX70: 3 | AY70: 3 | AZ70: 3 | BA70: 3 | BB70: 4 | BC70: 3 | BD70: 3 | BE70: 4 | BF70: 5 | BG70: 3 | BH70: 2 | BI70: 3 | BJ70: 1 | BK70: 2 | BL70: 3 | BM70: 2 | BN70: 3 | BO70: 3 | BP70: 2 | BQ70: 2 | BR70: 4 | BS70: 3 | BT70: 2 | BU70: 3 | BV70: 4 | BW70: 3 | BX70: 3 | BY70: 3 | BZ70: 3 | CA70: 2 | CB70: 4 | CC70: 3 | CD70: 4 | CE70: 4 | CF70: 4 | CG70: 1 | CL70: 4 | CQ70: 2 | CS70: 3 | CT70: 3 | CU70: 1 | CV70: 1 | CX70: 1 | CY70: 1 | CZ70: 5 | DB70: 10 | DC70: 10044 | DE70: 674e450b1a4a8e2d4e8d7e7c | DF70: 1
A71: 45718.506 | B71: 45718.515 | C71: 0 | D71: 35.33.209.127 | E71: 100 | F71: 750 | G71: 1 | H71: 45718.515 | I71: R_5YQGAL2mctP9OiB | N71: 39.7503 | O71: -75.5453 | P71: anonymous | Q71: EN | R71: 1 | S71: 6731d6e3c0f5542c912b8c25@email.prolific.com | T71: 1 | U71: 1 | W71: 2 | Y71: 7 | Z71: 1 | AA71: 1 | AB71: 1 | AC71: 7 | AD71: 1 | AE71: 1 | AF71: 2 | AG71: 1 | AH71: 2 | AI71: 1 | AJ71: 2 | AK71: 1 | AL71: 2 | AN71: 3 | AO71: 1 | AP71: 1 | AR71: 1 | AS71: 3 | AT71: 3 | AU71: 3 | AV71: 3 | AW71: 3 | AX71: 4 | AY71: 3 | AZ71: 4 | BA71: 4 | BB71: 5 | BC71: 5 | BD71: 3 | BE71: 4 | BF71: 3 | BG71: 3 | BH71: 5 | BI71: 5 | BJ71: 5 | BK71: 3 | BL71: 2 | BM71: 4 | BN71: 3 | BO71: 3 | BP71: 4 | BQ71: 5 | BR71: 4 | BS71: 3 | BT71: 3 | BU71: 3 | BV71: 5 | BW71: 3 | BX71: 2 | BY71: 5 | BZ71: 3 | CA71: 4 | CB71: 5 | CC71: 3 | CD71: 3 | CE71: 2 | CF71: 5 | CG71: 4 | CH71: 4 | CI71: 4 | CJ71: 4 | CK71: 1 | CM71: 1 | CN71: 2 | CO71: 3 | CP71: 4 | CQ71: 1 | CS71: 1 | CT71: 2 | CU71: 5 | CV71: 3 | CX71: 1 | CY71: 1 | CZ71: 8 | DA71: Disability | DB71: 1 | DC71: 08010 | DE71: 6731d6e3c0f5542c912b8c25 | DF71: 1
A72: 45718.51 | B72: 45718.516 | C72: 0 | D72: 69.123.131.165 | E72: 100 | F72: 562 | G72: 1 | H72: 45718.516 | I72: R_5a6PP0LA2W3WsHn | N72: 40.8731 | O72: -73.8726 | P72: anonymous | Q72: EN | R72: 1 | S72: 674cc0fa6aed04bd02adeb49 | T72: 2 | U72: 2 | W72: 1 | Y72: 4 | Z72: 2 | AA72: 1 | AB72: 2 | AC72: 8 | AD72: 4 | AE72: 2 | AF72: 2 | AG72: 1 | AH72: 2 | AI72: 2 | AJ72: 1 | AS72: 4 | AT72: 5 | AU72: 5 | AV72: 4 | AW72: 3 | AX72: 4 | AY72: 5 | AZ72: 5 | BA72: 4 | BB72: 4 | BC72: 5 | BD72: 4 | BE72: 3 | BF72: 3 | BG72: 5 | BH72: 3 | BI72: 2 | BJ72: 4 | BK72: 4 | BL72: 5 | BM72: 5 | BN72: 4 | BO72: 3 | BP72: 4 | BQ72: 4 | BR72: 3 | BS72: 3 | BT72: 4 | BU72: 3 | BV72: 3 | BW72: 2 | BX72: 4 | BY72: 5 | BZ72: 5 | CA72: 4 | CB72: 3 | CC72: 4 | CD72: 5 | CE72: 4 | CF72: 3 | CG72: 2 | CL72: 3 | CQ72: 2 | CS72: 1 | CT72: 3 | CU72: 2 | CV72: 3 | CX72: 1 | CY72: 1 | CZ72: 4 | DB72: 9 | DC72: 10467 | DE72: 674cc0fa6aed04bd02adeb49 | DF72: 1
A73: 45718.512 | B73: 45718.518 | C73: 0 | D73: 72.89.41.31 | E73: 100 | F73: 478 | G73: 1 | H73: 45718.518 | I73: R_5QG2JXuUWJSNFUy | N73: 40.6844 | O73: -73.4814 | P73: anonymous | Q73: EN | R73: 1 | S73: 67bb9c72c17350b539f137bd | T73: 2 | U73: 1 | W73: 2 | Y73: 1 | Z73: 1 | AA73: 1 | AB73: 2 | AC73: 7 | AD73: 2 | AE73: 1 | AF73: 2 | AG73: 1 | AH73: 2 | AI73: 2 | AJ73: 1 | AS73: 4 | AT73: 4 | AU73: 4 | AV73: 4 | AW73: 3 | AX73: 4 | AY73: 3 | AZ73: 4 | BA73: 4 | BB73: 3 | BC73: 2 | BD73: 3 | BE73: 4 | BF73: 2 | BG73: 2 | BH73: 2 | BI73: 2 | BJ73: 3 | BK73: 4 | BL73: 4 | BM73: 3 | BN73: 3 | BO73: 2 | BP73: 2 | BQ73: 4 | BR73: 2 | BS73: 3 | BT73: 3 | BU73: 3 | BV73: 2 | BW73: 2 | BX73: 3 | BY73: 4 | BZ73: 3 | CA73: 2 | CB73: 4 | CC73: 2 | CD73: 3 | CE73: 4 | CF73: 2 | CG73: 1 | CH73: 2 | CI73: 1 | CJ73: 1 | CK73: 4 | CM73: 2 | CN73: 3 | CO73: 4 | CP73: 1 | CQ73: 1 | CS73: 4 | CT73: 2 | CU73: 4 | CV73: 3 | CX73: 1 | CY73: 1 | CZ73: 8 | DA73: homemaker | DB73: 4 | DC73: 11701 | DE73: 67bb9c72c17350b539f137bd | DF73: 1
A74: 45718.513 | B74: 45718.518 | C74: 0 | D74: 24.187.47.231 | E74: 100 | F74: 476 | G74: 1 | H74: 45718.518 | I74: R_30IW0CoxaH6GNXm | N74: 40.9451 | O74: -74.2531 | P74: anonymous | Q74: EN | R74: 1 | S74: 6126c68385863fa349a80305 | T74: 1 | U74: 3 | W74: 1 | Y74: 3 | Z74: 2 | AA74: 1 | AB74: 1 | AC74: 3 | AD74: 2 | AE74: 1 | AF74: 2 | AG74: 2 | AH74: 2 | AI74: 2 | AJ74: 1 | AS74: 4 | AT74: 4 | AU74: 4 | AV74: 4 | AW74: 4 | AX74: 4 | AY74: 4 | AZ74: 4 | BA74: 4 | BB74: 4 | BC74: 4 | BD74: 3 | BE74: 4 | BF74: 3 | BG74: 3 | BH74: 3 | BI74: 4 | BJ74: 4 | BK74: 4 | BL74: 4 | BM74: 4 | BN74: 4 | BO74: 3 | BP74: 3 | BQ74: 3 | BR74: 3 | BS74: 3 | BT74: 4 | BU74: 4 | BV74: 4 | BW74: 3 | BX74: 2 | BY74: 2 | BZ74: 2 | CA74: 2 | CB74: 4 | CC74: 4 | CD74: 2 | CE74: 4 | CF74: 2 | CG74: 2 | CL74: 2 | CQ74: 2 | CS74: 1 | CT74: 3 | CU74: 1 | CV74: 1 | CX74: 1 | CY74: 1 | CZ74: 3 | DB74: 2 | DC74: 07035 | DE74: 6126c68385863fa349a80305 | DF74: 1
A75: 45718.512 | B75: 45718.519 | C75: 0 | D75: 100.2.225.105 | E75: 100 | F75: 665 | G75: 1 | H75: 45718.519 | I75: R_3ixs6bk6deNAtsg | N75: 40.5828 | O75: -73.9532 | P75: anonymous | Q75: EN | R75: 1 | S75: 6636330bdf8206ac3b939cff | T75: 2 | U75: 2 | W75: 1 | Y75: 1 | Z75: 1 | AA75: 1 | AB75: 2 | AC75: 5 | AD75: 2 | AE75: 2 | AF75: 1 | AG75: 1 | AH75: 2 | AI75: 2 | AJ75: 1 | AS75: 3 | AT75: 3 | AU75: 4 | AV75: 3 | AW75: 2 | AX75: 3 | AY75: 1 | AZ75: 4 | BA75: 4 | BB75: 5 | BC75: 5 | BD75: 1 | BE75: 4 | BF75: 5 | BG75: 5 | BH75: 5 | BI75: 4 | BJ75: 3 | BK75: 4 | BL75: 2 | BM75: 3 | BN75: 3 | BO75: 5 | BP75: 1 | BQ75: 5 | BR75: 5 | BS75: 3 | BT75: 3 | BU75: 3 | BV75: 5 | BW75: 2 | BX75: 1 | BY75: 5 | BZ75: 2 | CA75: 3 | CB75: 4 | CC75: 1 | CD75: 1 | CE75: 4 | CF75: 5 | CG75: 1 | CL75: 5 | CQ75: 1 | CS75: 2 | CT75: 2 | CU75: 3 | CV75: 1 | CX75: 1 | CY75: 1 | CZ75: 7 | DB75: 3 | DC75: 11235 | DE75: 6636330bdf8206ac3b939cff | DF75: 1
A76: 45718.515 | B76: 45718.52 | C76: 0 | D76: 74.65.35.63 | E76: 100 | F76: 379 | G76: 1 | H76: 45718.52 | I76: R_1eY7rbZ3UxfO7vP | N76: 43.3195 | O76: -76.4178 | P76: anonymous | Q76: EN | R76: 1 | S76: 62989b11e61bf4363844f0cd | T76: 2 | U76: 5 | V76: Duplex | W76: 1 | Y76: 1 | Z76: 2 | AA76: 1 | AB76: 1 | AC76: 3 | AD76: 4 | AE76: 2 | AF76: 2 | AG76: 2 | AH76: 1 | AI76: 2 | AJ76: 1 | AS76: 2 | AT76: 1 | AU76: 2 | AV76: 2 | AW76: 1 | AX76: 4 | AY76: 1 | AZ76: 1 | BA76: 1 | BB76: 1 | BC76: 4 | BD76: 1 | BE76: 1 | BF76: 1 | BG76: 1 | BH76: 5 | BI76: 3 | BJ76: 1 | BK76: 4 | BL76: 3 | BM76: 1 | BN76: 1 | BO76: 4 | BP76: 5 | BQ76: 5 | BR76: 1 | BS76: 3 | BT76: 2 | BU76: 2 | BV76: 4 | BW76: 4 | BX76: 1 | BY76: 4 | BZ76: 1 | CA76: 1 | CB76: 4 | CC76: 1 | CD76: 1 | CE76: 4 | CF76: 1 | CG76: 1 | CL76: 3 | CQ76: 2 | CS76: 2 | CT76: 2 | CU76: 4 | CV76: 1 | CX76: 1 | CY76: 1 | CZ76: 8 | DA76: Technology installer | DB76: 4 | DC76: 13069 | DE76: 62989b11e61bf4363844f0cd | DF76: 1
A77: 45718.506 | B77: 45718.52 | C77: 0 | D77: 212.32.111.177 | E77: 100 | F77: 1196 | G77: 1 | H77: 45718.52 | I77: R_508JSo7ScYXC9lv | N77: 37.751 | O77: -97.822 | P77: anonymous | Q77: EN | R77: 1 | S77: 67ac8af036c029778042bbbb | T77: 2 | U77: 1 | W77: 1 | Y77: 6 | Z77: 2 | AA77: 1 | AB77: 2 | AC77: 4 | AD77: 3 | AE77: 1 | AF77: 1 | AG77: 1 | AH77: 2 | AI77: 2 | AJ77: 1 | AS77: 4 | AT77: 5 | AU77: 5 | AV77: 4 | AW77: 4 | AX77: 4 | AY77: 4 | AZ77: 4 | BA77: 4 | BB77: 4 | BC77: 4 | BD77: 4 | BE77: 4 | BF77: 4 | BG77: 3 | BH77: 5 | BI77: 2 | BJ77: 5 | BK77: 4 | BL77: 4 | BM77: 4 | BN77: 4 | BO77: 4 | BP77: 4 | BQ77: 4 | BR77: 3 | BS77: 3 | BT77: 5 | BU77: 5 | BV77: 5 | BW77: 5 | BX77: 5 | BY77: 4 | BZ77: 4 | CA77: 5 | CB77: 5 | CC77: 5 | CD77: 5 | CE77: 3 | CF77: 4 | CG77: 2 | CL77: 5 | CQ77: 1 | CS77: 1 | CT77: 4 | CU77: 4 | CV77: 1 | CX77: 1 | CY77: 1 | CZ77: 1 | DB77: 4 | DC77: 07008 | DE77: 67ac8af036c029778042bbbb | DF77: 1
A78: 45718.518 | B78: 45718.522 | C78: 0 | D78: 172.59.213.248 | E78: 100 | F78: 309 | G78: 1 | H78: 45718.522 | I78: R_3kUhrrI1nSNyoHD | N78: 40.7597 | O78: -74.1836 | P78: anonymous | Q78: EN | R78: 1 | S78: 5fb2041681fe9376804e1249 | T78: 2 | U78: 2 | W78: 1 | Y78: 1 | Z78: 1 | AA78: 2 | AB78: 2 | AC78: 2 | AD78: 5 | AE78: 4 | AF78: 2 | AG78: 2 | AH78: 2 | AI78: 2 | AJ78: 1 | AS78: 3 | AT78: 3 | AU78: 4 | AV78: 3 | AW78: 4 | AX78: 3 | AY78: 2 | AZ78: 2 | BA78: 3 | BB78: 1 | BC78: 3 | BD78: 3 | BE78: 3 | BF78: 4 | BG78: 3 | BH78: 3 | BI78: 3 | BJ78: 2 | BK78: 3 | BL78: 4 | BM78: 3 | BN78: 3 | BO78: 4 | BP78: 4 | BQ78: 4 | BR78: 3 | BS78: 3 | BT78: 3 | BU78: 4 | BV78: 3 | BW78: 3 | BX78: 3 | BY78: 4 | BZ78: 4 | CA78: 4 | CB78: 4 | CC78: 3 | CD78: 4 | CE78: 4 | CF78: 4 | CG78: 2 | CL78: 3 | CQ78: 1 | CS78: 3 | CT78: 3 | CU78: 1 | CV78: 1 | CX78: 1 | CY78: 1 | CZ78: 4 | DB78: 10 | DC78: 11385 | DE78: 5fb2041681fe9376804e1249 | DF78: 1
A79: 45718.515 | B79: 45718.522 | C79: 0 | D79: 72.225.43.0 | E79: 100 | F79: 646 | G79: 1 | H79: 45718.522 | I79: R_7pojaqUVCxB2hXu | N79: 43.1806 | O79: -77.5948 | P79: anonymous | Q79: EN | R79: 1 | S79: 6767d7cb119ea20af1676aeb | T79: 2 | U79: 2 | W79: 1 | Y79: 1 | Z79: 2 | AA79: 2 | AB79: 1 | AC79: 1 | AD79: 2 | AE79: 1 | AF79: 2 | AG79: 2 | AH79: 2 | AI79: 2 | AJ79: 1 | AS79: 1 | AT79: 3 | AU79: 2 | AV79: 2 | AW79: 4 | AX79: 4 | AY79: 1 | AZ79: 1 | BA79: 1 | BB79: 1 | BC79: 1 | BD79: 1 | BE79: 1 | BF79: 2 | BG79: 1 | BH79: 4 | BI79: 4 | BJ79: 1 | BK79: 4 | BL79: 4 | BM79: 2 | BN79: 1 | BO79: 4 | BP79: 4 | BQ79: 4 | BR79: 3 | BS79: 3 | BT79: 2 | BU79: 2 | BV79: 1 | BW79: 1 | BX79: 3 | BY79: 4 | BZ79: 1 | CA79: 3 | CB79: 4 | CC79: 1 | CD79: 2 | CE79: 4 | CF79: 5 | CG79: 1 | CL79: 5 | CQ79: 2 | CS79: 3 | CT79: 2 | CU79: 4 | CV79: 5 | CW79: Disabled + part time self employed | CX79: 1 | CY79: 1 | CZ79: 8 | DA79: Information Technology | DB79: 1 | DC79: 14608 | DE79: 6767d7cb119ea20af1676aeb | DF79: 1
A80: 45718.492 | B80: 45718.523 | C80: 0 | D80: 207.96.82.51 | E80: 100 | F80: 2618 | G80: 1 | H80: 45718.523 | I80: R_3EApXwpMRVnSTUd | N80: 40.7263 | O80: -73.9818 | P80: anonymous | Q80: EN | R80: 1 | S80: 6644a34a576e8e69578cca1b | T80: 2 | U80: 3 | W80: 1 | Y80: 6 | Z80: 1 | AA80: 2 | AB80: 2 | AC80: 1 | AD80: 2 | AE80: 1 | AF80: 2 | AG80: 2 | AH80: 2 | AI80: 2 | AJ80: 1 | AS80: 3 | AT80: 3 | AU80: 3 | AV80: 3 | AW80: 3 | AX80: 3 | AY80: 3 | AZ80: 4 | BA80: 4 | BB80: 4 | BC80: 5 | BD80: 4 | BE80: 5 | BF80: 5 | BG80: 4 | BH80: 2 | BI80: 2 | BJ80: 1 | BK80: 1 | BL80: 3 | BM80: 1 | BN80: 1 | BO80: 1 | BP80: 1 | BQ80: 1 | BR80: 1 | BS80: 3 | BT80: 1 | BU80: 2 | BV80: 4 | BW80: 3 | BX80: 4 | BY80: 4 | BZ80: 3 | CA80: 3 | CB80: 3 | CC80: 3 | CD80: 3 | CE80: 4 | CF80: 3 | CG80: 4 | CL80: 3 | CQ80: 1 | CS80: 1 | CT80: 3 | CU80: 2 | CV80: 1 | CX80: 1 | CY80: 1 | CZ80: 3 | DB80: 9 | DC80: 10005 | DE80: 6644a34a576e8e69578cca1b | DF80: 1
A81: 45718.52 | B81: 45718.523 | C81: 0 | D81: 142.255.44.179 | E81: 100 | F81: 293 | G81: 1 | H81: 45718.523 | I81: R_3I4Yaw4rIuySz8E | N81: 40.8596 | O81: -73.9316 | P81: anonymous | Q81: EN | R81: 1 | S81: 5e4ec71307f31c30b6636be2 | T81: 2 | U81: 2 | W81: 1 | Y81: 1 | Z81: 2 | AA81: 2 | AB81: 2 | AC81: 1 | AD81: 4 | AE81: 1 | AF81: 2 | AG81: 2 | AH81: 2 | AI81: 2 | AJ81: 1 | AS81: 4 | AT81: 4 | AU81: 4 | AV81: 4 | AW81: 3 | AX81: 4 | AY81: 5 | AZ81: 5 | BA81: 5 | BB81: 5 | BC81: 4 | BD81: 2 | BE81: 4 | BF81: 3 | BG81: 3 | BH81: 2 | BI81: 2 | BJ81: 2 | BK81: 2 | BL81: 4 | BM81: 4 | BN81: 3 | BO81: 4 | BP81: 4 | BQ81: 2 | BR81: 1 | BS81: 3 | BT81: 4 | BU81: 4 | BV81: 2 | BW81: 2 | BX81: 2 | BY81: 1 | BZ81: 1 | CA81: 1 | CB81: 2 | CC81: 2 | CD81: 1 | CE81: 4 | CF81: 2 | CG81: 1 | CL81: 4 | CQ81: 2 | CS81: 4 | CT81: 4 | CU81: 4 | CV81: 2 | CX81: 1 | CY81: 1 | CZ81: 8 | DA81: Writer | DB81: 1 | DC81: 10040 | DE81: 5e4ec71307f31c30b6636be2 | DF81: 1
A82: 45718.52 | B82: 45718.526 | C82: 0 | D82: 74.67.88.103 | E82: 100 | F82: 462 | G82: 1 | H82: 45718.526 | I82: R_32czX7iql55PaNP | N82: 42.2781 | O82: -74.916 | P82: anonymous | Q82: EN | R82: 1 | S82: 654509bce930185adab23a1a | T82: 2 | U82: 1 | W82: 1 | Y82: 1 | Z82: 2 | AA82: 1 | AB82: 1 | AC82: 3 | AD82: 3 | AE82: 1 | AF82: 2 | AG82: 2 | AH82: 2 | AI82: 2 | AJ82: 1 | AS82: 3 | AT82: 4 | AU82: 4 | AV82: 4 | AW82: 4 | AX82: 2 | AY82: 2 | AZ82: 2 | BA82: 3 | BB82: 3 | BC82: 2 | BD82: 3 | BE82: 4 | BF82: 2 | BG82: 2 | BH82: 5 | BI82: 4 | BJ82: 2 | BK82: 4 | BL82: 4 | BM82: 4 | BN82: 1 | BO82: 4 | BP82: 4 | BQ82: 4 | BR82: 4 | BS82: 3 | BT82: 2 | BU82: 2 | BV82: 4 | BW82: 4 | BX82: 4 | BY82: 5 | BZ82: 5 | CA82: 4 | CB82: 4 | CC82: 4 | CD82: 4 | CE82: 4 | CF82: 4 | CG82: 2 | CL82: 3 | CQ82: 1 | CS82: 3 | CT82: 4 | CU82: 4 | CV82: 3 | CX82: 1 | CY82: 1 | CZ82: 6 | DB82: 1 | DC82: 13856 | DE82: 654509bce930185adab23a1a | DF82: 1
A83: 45718.514 | B83: 45718.527 | C83: 0 | D83: 50.49.213.27 | E83: 100 | F83: 1161 | G83: 1 | H83: 45718.527 | I83: R_8QE4e9iPBlcCLxg | N83: 41.4535 | O83: -74.4774 | P83: anonymous | Q83: EN | R83: 1 | S83: 644f162cac2c2b8aa0583b89 | T83: 2 | U83: 1 | W83: 1 | Y83: 4 | Z83: 2 | AA83: 1 | AB83: 2 | AC83: 4 | AD83: 4 | AE83: 3 | AF83: 1 | AG83: 2 | AH83: 2 | AI83: 2 | AJ83: 1 | AS83: 4 | AT83: 3 | AU83: 3 | AV83: 3 | AW83: 3 | AX83: 2 | AY83: 2 | AZ83: 2 | BA83: 3 | BB83: 1 | BC83: 3 | BD83: 2 | BE83: 3 | BF83: 2 | BG83: 1 | BH83: 2 | BI83: 2 | BJ83: 2 | BK83: 3 | BL83: 4 | BM83: 4 | BN83: 3 | BO83: 3 | BP83: 4 | BQ83: 3 | BR83: 3 | BS83: 3 | BT83: 3 | BU83: 3 | BV83: 3 | BW83: 4 | BX83: 2 | BY83: 3 | BZ83: 3 | CA83: 3 | CB83: 4 | CC83: 4 | CD83: 2 | CE83: 4 | CF83: 3 | CG83: 1 | CL83: 4 | CQ83: 1 | CS83: 4 | CT83: 2 | CU83: 4 | CV83: 2 | CX83: 1 | CY83: 1 | CZ83: 8 | DA83: housekeeping and babysitting | DB83: 5 | DC83: 10988 | DD83: none | DE83: 644f162cac2c2b8aa0583b89 | DF83: 1
A84: 45718.523 | B84: 45718.532 | C84: 0 | D84: 74.71.112.214 | E84: 100 | F84: 730 | G84: 1 | H84: 45718.532 | I84: R_3AVW9JgfO0MC1fr | N84: 40.781 | O84: -73.9501 | P84: anonymous | Q84: EN | R84: 1 | S84: 5c5c8a688089970001788f30 | T84: 2 | U84: 2 | W84: 1 | Y84: 1 | Z84: 2 | AA84: 2 | AB84: 1 | AC84: 2 | AD84: 5 | AE84: 1 | AF84: 2 | AG84: 2 | AH84: 1 | AI84: 1 | AJ84: 2 | AK84: 4 | AL84: 2 | AN84: 1 | AO84: 2 | AP84: 4 | AQ84: purchased apartment insurance | AR84: 1 | AS84: 2 | AT84: 3 | AU84: 4 | AV84: 3 | AW84: 3 | AX84: 4 | AY84: 1 | AZ84: 3 | BA84: 3 | BB84: 2 | BC84: 4 | BD84: 1 | BE84: 1 | BF84: 4 | BG84: 1 | BH84: 3 | BI84: 3 | BJ84: 1 | BK84: 1 | BL84: 1 | BM84: 1 | BN84: 1 | BO84: 4 | BP84: 4 | BQ84: 4 | BR84: 2 | BS84: 3 | BT84: 1 | BU84: 1 | BV84: 5 | BW84: 3 | BX84: 2 | BY84: 3 | BZ84: 1 | CA84: 1 | CB84: 1 | CC84: 1 | CD84: 1 | CE84: 4 | CF84: 1 | CG84: 1 | CL84: 3 | CQ84: 1 | CS84: 6 | CT84: 3 | CU84: 4 | CV84: 2 | CX84: 1 | CY84: 1 | CZ84: 8 | DA84: internet services | DB84: 4 | DC84: 19128 | DD84: This was a clear, easy-to-work-with survey -- a relief compared to many others. | DE84: 5c5c8a688089970001788f30 | DF84: 1
A85: 45718.542 | B85: 45718.548 | C85: 0 | D85: 172.58.134.248 | E85: 100 | F85: 492 | G85: 1 | H85: 45718.548 | I85: R_73ga4Q92mrCdxxO | N85: 26.2281 | O85: -80.1648 | P85: anonymous | Q85: EN | R85: 1 | S85: 6712acd49ca5448a6e983e6c | T85: 2 | U85: 1 | W85: 1 | Y85: 4 | Z85: 1 | AA85: 2 | AB85: 2 | AC85: 1 | AD85: 2 | AE85: 1 | AF85: 2 | AG85: 2 | AH85: 2 | AI85: 1 | AJ85: 2 | AK85: 2 | AL85: 2 | AN85: 2 | AO85: 2 | AP85: 3 | AR85: 1 | AS85: 3 | AT85: 3 | AU85: 3 | AV85: 3 | AW85: 2 | AX85: 4 | AY85: 2 | AZ85: 2 | BA85: 3 | BB85: 3 | BC85: 2 | BD85: 3 | BE85: 2 | BF85: 4 | BG85: 2 | BH85: 4 | BI85: 3 | BJ85: 4 | BK85: 4 | BL85: 4 | BM85: 4 | BN85: 3 | BO85: 4 | BP85: 4 | BQ85: 4 | BR85: 2 | BS85: 3 | BT85: 3 | BU85: 4 | BV85: 3 | BW85: 3 | BX85: 3 | BY85: 3 | BZ85: 2 | CA85: 2 | CB85: 4 | CC85: 3 | CD85: 2 | CE85: 4 | CF85: 3 | CG85: 1 | CL85: 4 | CQ85: 2 | CS85: 3 | CT85: 3 | CU85: 2 | CV85: 1 | CX85: 1 | CY85: 1 | CZ85: 4 | DB85: 1 | DC85: 10012 | DE85: 6712acd49ca5448a6e983e6c | DF85: 1
A86: 45718.548 | B86: 45718.552 | C86: 0 | D86: 96.242.128.36 | E86: 100 | F86: 292 | G86: 1 | H86: 45718.552 | I86: R_6RLPzYJzulec2aZ | N86: 40.7062 | O86: -74.5493 | P86: anonymous | Q86: EN | R86: 1 | S86: 66bbb95169813caae3f912c1 | T86: 1 | U86: 3 | W86: 1 | Y86: 7 | Z86: 2 | AA86: 1 | AB86: 2 | AC86: 4 | AD86: 2 | AE86: 1 | AF86: 2 | AG86: 1 | AH86: 2 | AI86: 1 | AJ86: 2 | AK86: 2 | AL86: 2 | AN86: 2 | AO86: 2 | AP86: 5 | AR86: 1 | AS86: 4 | AT86: 4 | AU86: 4 | AV86: 4 | AW86: 4 | AX86: 4 | AY86: 3 | AZ86: 4 | BA86: 3 | BB86: 3 | BC86: 2 | BD86: 3 | BE86: 4 | BF86: 4 | BG86: 3 | BH86: 3 | BI86: 2 | BJ86: 3 | BK86: 2 | BL86: 4 | BM86: 2 | BN86: 2 | BO86: 2 | BP86: 2 | BQ86: 3 | BR86: 2 | BS86: 3 | BT86: 3 | BU86: 2 | BV86: 3 | BW86: 3 | BX86: 4 | BY86: 4 | BZ86: 3 | CA86: 4 | CB86: 4 | CC86: 3 | CD86: 4 | CE86: 4 | CF86: 3 | CG86: 1 | CL86: 3 | CQ86: 1 | CS86: 3 | CT86: 2 | CU86: 4 | CV86: 2 | CX86: 1 | CY86: 1 | CZ86: 2 | DB86: 3 | DC86: 07920 | DE86: 66bbb95169813caae3f912c1 | DF86: 1
A87: 45718.552 | B87: 45718.557 | C87: 0 | D87: 100.8.206.10 | E87: 100 | F87: 400 | G87: 1 | H87: 45718.557 | I87: R_7LzGyOlIl8mR7qN | N87: 40.7182 | O87: -74.0476 | P87: anonymous | Q87: EN | R87: 1 | S87: 66f42e274c0e28275441dc22 | T87: 1 | U87: 2 | W87: 1 | Y87: 5 | Z87: 1 | AA87: 2 | AB87: 2 | AC87: 5 | AD87: 3 | AE87: 1 | AF87: 1 | AG87: 2 | AH87: 2 | AI87: 1 | AJ87: 2 | AK87: 1 | AL87: 2 | AN87: 2 | AO87: 2 | AP87: 5 | AR87: 1 | AS87: 4 | AT87: 4 | AU87: 3 | AV87: 3 | AW87: 3 | AX87: 2 | AY87: 4 | AZ87: 2 | BA87: 4 | BB87: 2 | BC87: 4 | BD87: 1 | BE87: 1 | BF87: 4 | BG87: 1 | BH87: 2 | BI87: 4 | BJ87: 2 | BK87: 4 | BL87: 2 | BM87: 2 | BN87: 4 | BO87: 2 | BP87: 3 | BQ87: 3 | BR87: 1 | BS87: 3 | BT87: 2 | BU87: 2 | BV87: 4 | BW87: 4 | BX87: 2 | BY87: 5 | BZ87: 5 | CA87: 4 | CB87: 4 | CC87: 4 | CD87: 2 | CE87: 4 | CF87: 2 | CG87: 1 | CL87: 1 | CQ87: 1 | CS87: 3 | CT87: 4 | CU87: 4 | CV87: 3 | CX87: 1 | CY87: 1 | CZ87: 8 | DA87: Homemaker | DB87: 10 | DC87: 07030 | DE87: 66f42e274c0e28275441dc22 | DF87: 1
A88: 45718.535 | B88: 45718.559 | C88: 0 | D88: 74.68.36.169 | E88: 100 | F88: 2094 | G88: 1 | H88: 45718.559 | I88: R_3q9b3MyK3TzRRUW | N88: 40.7157 | O88: -74 | P88: anonymous | Q88: EN | R88: 1 | S88: 663a7af013938e6bbfb065d5 | T88: 2 | U88: 3 | W88: 1 | Y88: 1 | Z88: 1 | AA88: 2 | AB88: 2 | AC88: 3 | AD88: 6 | AE88: 3 | AF88: 2 | AG88: 2 | AH88: 1 | AI88: 2 | AJ88: 1 | AS88: 3 | AT88: 3 | AU88: 2 | AV88: 2 | AW88: 3 | AX88: 2 | AY88: 2 | AZ88: 2 | BA88: 3 | BB88: 3 | BC88: 2 | BD88: 1 | BE88: 4 | BF88: 4 | BG88: 3 | BH88: 1 | BI88: 1 | BJ88: 1 | BK88: 2 | BL88: 3 | BM88: 2 | BN88: 1 | BO88: 1 | BP88: 1 | BQ88: 1 | BR88: 1 | BS88: 3 | BT88: 1 | BU88: 1 | BV88: 2 | BW88: 1 | BX88: 3 | BY88: 4 | BZ88: 1 | CA88: 3 | CB88: 1 | CC88: 1 | CD88: 3 | CE88: 4 | CF88: 1 | CG88: 1 | CL88: 1 | CQ88: 2 | CS88: 2 | CT88: 3 | CU88: 4 | CV88: 2 | CX88: 1 | CY88: 1 | CZ88: 3 | DB88: 6 | DC88: 10013 | DE88: 663a7af013938e6bbfb065d5 | DF88: 1
A89: 45718.552 | B89: 45718.56 | C89: 0 | D89: 67.245.218.160 | E89: 100 | F89: 679 | G89: 1 | H89: 45718.56 | I89: R_7dzFVEj9BWLCyPd | N89: 41.717 | O89: -74.3957 | P89: anonymous | Q89: EN | R89: 1 | S89: 650ee274aa4447ac435b7830 | T89: 2 | U89: 4 | W89: 2 | Y89: 4 | Z89: 1 | AA89: 1 | AB89: 2 | AC89: 3 | AD89: 5 | AE89: 2 | AF89: 2 | AG89: 2 | AH89: 2 | AI89: 1 | AJ89: 2 | AK89: 2 | AL89: 1 | AM89: 2023 | AN89: 2 | AO89: 2 | AP89: 1 | AR89: 2 | AS89: 3 | AT89: 4 | AU89: 3 | AV89: 3 | AW89: 4 | AX89: 3 | AY89: 5 | AZ89: 5 | BA89: 4 | BB89: 5 | BC89: 4 | BD89: 5 | BE89: 3 | BF89: 4 | BG89: 4 | BH89: 3 | BI89: 5 | BJ89: 4 | BK89: 3 | BL89: 5 | BM89: 4 | BN89: 5 | BO89: 3 | BP89: 4 | BQ89: 4 | BR89: 4 | BS89: 3 | BT89: 4 | BU89: 4 | BV89: 5 | BW89: 3 | BX89: 4 | BY89: 4 | BZ89: 5 | CA89: 3 | CB89: 4 | CC89: 5 | CD89: 4 | CE89: 2 | CF89: 5 | CG89: 2 | CH89: 5 | CI89: 2 | CJ89: 4 | CK89: 1 | CM89: 1 | CN89: 3 | CO89: 2 | CP89: 4 | CQ89: 2 | CS89: 1 | CT89: 3 | CU89: 4 | CV89: 3 | CX89: 1 | CY89: 1 | CZ89: 2 | DB89: 1 | DC89: 12721 | DE89: 650ee274aa4447ac435b7830 | DF89: 1
A90: 45718.573 | B90: 45718.579 | C90: 0 | D90: 24.185.143.157 | E90: 100 | F90: 458 | G90: 1 | H90: 45718.579 | I90: R_3bOypAYBa8Ivwza | N90: 40.7597 | O90: -74.1836 | P90: anonymous | Q90: EN | R90: 1 | S90: 66d96af9964c7ebb21f5d22c | T90: 1 | U90: 2 | W90: 4 | X90: Living with parents | Y90: 1 | Z90: 2 | AA90: 1 | AB90: 2 | AC90: 5 | AD90: 4 | AE90: 2 | AF90: 2 | AG90: 2 | AH90: 2 | AI90: 1 | AJ90: 2 | AK90: 2 | AL90: 2 | AN90: 2 | AO90: 2 | AP90: 5 | AR90: 2 | AS90: 4 | AT90: 4 | AU90: 4 | AV90: 4 | AW90: 4 | AX90: 4 | AY90: 4 | AZ90: 4 | BA90: 4 | BB90: 4 | BC90: 4 | BD90: 4 | BE90: 4 | BF90: 4 | BG90: 4 | BH90: 4 | BI90: 3 | BJ90: 4 | BK90: 4 | BL90: 4 | BM90: 4 | BN90: 4 | BO90: 4 | BP90: 4 | BQ90: 4 | BR90: 3 | BS90: 3 | BT90: 4 | BU90: 4 | BV90: 4 | BW90: 3 | BX90: 4 | BY90: 4 | BZ90: 3 | CA90: 4 | CB90: 3 | CC90: 3 | CD90: 4 | CE90: 4 | CF90: 3 | CG90: 1 | CQ90: 2 | CS90: 2 | CT90: 2 | CU90: 3 | CV90: 3 | CX90: 1 | CY90: 1 | CZ90: 8 | DA90: Unemployed | DB90: 7 | DC90: 07201 | DE90: 66d96af9964c7ebb21f5d22c | DF90: 1
A91: 45718.574 | B91: 45718.58 | C91: 0 | D91: 73.150.164.117 | E91: 100 | F91: 454 | G91: 1 | H91: 45718.58 | I91: R_1LNjSJ1Qf1oEebz | N91: 40.734 | O91: -74.0712 | P91: anonymous | Q91: EN | R91: 1 | S91: 67269b19b3bf568ba3003046 | T91: 1 | U91: 3 | W91: 1 | Y91: 1 | Z91: 1 | AA91: 1 | AB91: 1 | AC91: 4 | AD91: 4 | AE91: 2 | AF91: 2 | AG91: 2 | AH91: 1 | AI91: 1 | AJ91: 2 | AK91: 2 | AL91: 1 | AM91: 2022 | AN91: 2 | AO91: 2 | AP91: 5 | AR91: 1 | AS91: 4 | AT91: 4 | AU91: 4 | AV91: 4 | AW91: 4 | AX91: 4 | AY91: 4 | AZ91: 3 | BA91: 4 | BB91: 4 | BC91: 4 | BD91: 4 | BE91: 4 | BF91: 4 | BG91: 4 | BH91: 3 | BI91: 4 | BJ91: 3 | BK91: 3 | BL91: 3 | BM91: 3 | BN91: 3 | BO91: 4 | BP91: 4 | BQ91: 4 | BR91: 3 | BS91: 3 | BT91: 3 | BU91: 3 | BV91: 3 | BW91: 3 | BX91: 4 | BY91: 4 | BZ91: 3 | CA91: 3 | CB91: 4 | CC91: 3 | CD91: 3 | CE91: 4 | CF91: 2 | CG91: 1 | CL91: 4 | CQ91: 2 | CS91: 1 | CT91: 3 | CU91: 5 | CV91: 5 | CW91: self employed | CX91: 1 | CY91: 1 | CZ91: 8 | DA91: freelance | DB91: 4 | DC91: 07302 | DD91: This survey was clear and straight to the point | DE91: 67269b19b3bf568ba3003046 | DF91: 1
A92: 45718.63 | B92: 45718.634 | C92: 0 | D92: 50.29.96.79 | E92: 100 | F92: 352 | G92: 1 | H92: 45718.634 | I92: R_5jrFzgHnocSmNDw | N92: 40.7523 | O92: -74.2172 | P92: anonymous | Q92: EN | R92: 1 | S92: 6714627f479ddab94039e823 | T92: 1 | U92: 5 | V92: Apartment | W92: 1 | Y92: 3 | Z92: 2 | AA92: 2 | AB92: 2 | AC92: 1 | AD92: 2 | AE92: 1 | AF92: 2 | AG92: 2 | AH92: 2 | AI92: 2 | AJ92: 1 | AS92: 4 | AT92: 4 | AU92: 4 | AV92: 4 | AW92: 4 | AX92: 4 | AY92: 4 | AZ92: 4 | BA92: 4 | BB92: 4 | BC92: 4 | BD92: 4 | BE92: 4 | BF92: 4 | BG92: 4 | BH92: 3 | BI92: 3 | BJ92: 3 | BK92: 4 | BL92: 4 | BM92: 4 | BN92: 4 | BO92: 4 | BP92: 3 | BQ92: 3 | BR92: 4 | BS92: 3 | BT92: 4 | BU92: 4 | BV92: 3 | BW92: 3 | BX92: 4 | BY92: 3 | BZ92: 4 | CA92: 3 | CB92: 3 | CC92: 4 | CD92: 4 | CE92: 3 | CF92: 4 | CG92: 2 | CL92: 5 | CQ92: 2 | CS92: 3 | CT92: 2 | CU92: 2 | CV92: 2 | CX92: 1 | CY92: 1 | CZ92: 8 | DA92: Warehouse | DB92: 1 | DC92: 07114 | DE92: 6714627f479ddab94039e823 | DF92: 1
A93: 45718.648 | B93: 45718.651 | C93: 0 | D93: 73.160.28.86 | E93: 100 | F93: 299 | G93: 1 | H93: 45718.651 | I93: R_72W3yGcroTjLS1z | N93: 40.3699 | O93: -74.6381 | P93: anonymous | Q93: EN | R93: 1 | S93: 677b71754229c2e3c5a7786f | T93: 1 | U93: 5 | W93: 2 | Y93: 2 | Z93: 2 | AA93: 1 | AB93: 2 | AC93: 2 | AD93: 2 | AE93: 1 | AF93: 2 | AG93: 2 | AH93: 2 | AI93: 2 | AJ93: 1 | AS93: 4 | AT93: 4 | AU93: 5 | AV93: 3 | AW93: 2 | AX93: 3 | AY93: 2 | AZ93: 3 | BA93: 3 | BB93: 4 | BC93: 4 | BD93: 3 | BE93: 4 | BF93: 4 | BG93: 3 | BH93: 4 | BI93: 3 | BJ93: 2 | BK93: 2 | BL93: 2 | BM93: 2 | BN93: 4 | BO93: 3 | BP93: 4 | BQ93: 5 | BR93: 3 | BS93: 3 | BT93: 2 | BU93: 4 | BV93: 2 | BW93: 2 | BX93: 2 | BY93: 3 | BZ93: 3 | CA93: 1 | CB93: 3 | CC93: 3 | CD93: 2 | CE93: 1 | CF93: 4 | CG93: 1 | CH93: 3 | CI93: 1 | CJ93: 2 | CK93: 3 | CM93: 1 | CN93: 2 | CO93: 3 | CP93: 4 | CQ93: 1 | CS93: 2 | CT93: 4 | CU93: 1 | CV93: 5 | CX93: 1 | CY93: 1 | CZ93: 8 | DB93: 1 | DC93: 08823 | DE93: 677b71754229c2e3c5a7786f | DF93: 1
A94: 45718.662 | B94: 45718.666 | C94: 0 | D94: 173.70.231.211 | E94: 100 | F94: 391 | G94: 1 | H94: 45718.666 | I94: R_3EHg9cLrWSQ56og | N94: 40.8949 | O94: -74.011 | P94: anonymous | Q94: EN | R94: 1 | S94: 67aa4c3d54c8e17bcc8a7975 | T94: 1 | U94: 1 | W94: 2 | Y94: 1 | Z94: 2 | AA94: 2 | AB94: 2 | AC94: 3 | AD94: 1 | AE94: 1 | AF94: 1 | AG94: 2 | AH94: 2 | AI94: 2 | AJ94: 1 | AS94: 4 | AT94: 4 | AU94: 4 | AV94: 4 | AW94: 3 | AX94: 4 | AY94: 3 | AZ94: 3 | BA94: 3 | BB94: 4 | BC94: 4 | BD94: 2 | BE94: 4 | BF94: 3 | BG94: 2 | BH94: 4 | BI94: 2 | BJ94: 4 | BK94: 2 | BL94: 2 | BM94: 2 | BN94: 2 | BO94: 3 | BP94: 3 | BQ94: 3 | BR94: 2 | BS94: 3 | BT94: 2 | BU94: 2 | BV94: 3 | BW94: 3 | BX94: 4 | BY94: 4 | BZ94: 3 | CA94: 4 | CB94: 3 | CC94: 3 | CD94: 4 | CE94: 4 | CF94: 3 | CG94: 1 | CH94: 3 | CI94: 2 | CJ94: 2 | CK94: 4 | CM94: 2 | CN94: 3 | CO94: 4 | CP94: 1 | CQ94: 1 | CS94: 1 | CT94: 4 | CU94: 4 | CV94: 1 | CX94: 1 | CY94: 1 | CZ94: 4 | DB94: 10 | DC94: 07666 | DE94: 67aa4c3d54c8e17bcc8a7975 | DF94: 1
A95: 45718.671 | B95: 45718.674 | C95: 0 | D95: 74.105.26.183 | E95: 100 | F95: 324 | G95: 1 | H95: 45718.674 | I95: R_3BPXeT2T2RH5fwX | N95: 40.9572 | O95: -74.1604 | P95: anonymous | Q95: EN | R95: 1 | S95: 6665b26a49d9b1071a67babe | T95: 1 | U95: 1 | W95: 1 | Y95: 1 | Z95: 1 | AA95: 1 | AB95: 2 | AC95: 3 | AD95: 2 | AE95: 2 | AF95: 2 | AG95: 2 | AH95: 1 | AI95: 2 | AJ95: 1 | AS95: 3 | AT95: 3 | AU95: 2 | AV95: 2 | AW95: 2 | AX95: 2 | AY95: 1 | AZ95: 1 | BA95: 1 | BB95: 1 | BC95: 2 | BD95: 1 | BE95: 1 | BF95: 1 | BG95: 1 | BH95: 4 | BI95: 3 | BJ95: 2 | BK95: 2 | BL95: 2 | BM95: 3 | BN95: 2 | BO95: 4 | BP95: 4 | BQ95: 4 | BR95: 4 | BS95: 3 | BT95: 2 | BU95: 3 | BV95: 2 | BW95: 2 | BX95: 2 | BY95: 4 | BZ95: 4 | CA95: 2 | CB95: 4 | CC95: 2 | CD95: 2 | CE95: 4 | CF95: 3 | CG95: 1 | CL95: 2 | CQ95: 1 | CS95: 3 | CT95: 3 | CU95: 4 | CV95: 1 | CX95: 1 | CY95: 1 | CZ95: 6 | DB95: 4 | DC95: 07512 | DD95: It was a short survey that was easy to understand. Thank you! | DE95: 6665b26a49d9b1071a67babe | DF95: 1
